Workbook
Name solver_adj: 'Model Summary'!$CP$66
Name solver_lhs1: 'Model Summary'!$CM$65
Name solver_opt: 'Model Summary'!$CM$65

Sheet Fee Table
C2: Wellness Referendum
C3: Fee Table – 30 years
C4: prepared by Hugh G. Graham, Campus Budget Office
C5: ='Model Summary'!B5 -> REVISED DRAFT 2/26/15
E6: Fall/Spring per semester | K6: Summer
C7: Year | E7: current base fees | F7: RSF membership fee | G7: additional fee | H7: total fee | I7: fee in 2015 dollars * | K7: current base fees | L7: RSF membership fee | M7: additional fee | N7: total fee | O7: fee in 2015 dollars *
A8: 0 | C8: 2015-16 | E8: 83.5 | F8: ='Fee Revenue'!E15 -> 8.5 | G8: 54 | H8: ='Fee Revenue'!E20 -> 146 | I8: =PV($G$39,$A8,0,-H8) -> 146 | K8: ='Fee Revenue'!E27 -> 60.5 | L8: ='Fee Revenue'!E29 -> 8.5 | M8: ='Fee Revenue'!E31 -> 41 | N8: ='Fee Revenue'!E33 -> 110 | O8: =PV($G$39,$A8,0,-N8) -> 110
A9: 1 | C9: 2016-17 | E9: ='Fee Revenue'!H12 -> 86.25 | F9: ='Fee Revenue'!H15 -> 8.75 | G9: ='Fee Revenue'!H18 -> 57 | H9: ='Fee Revenue'!H20 -> 152 | I9: =PV($G$39,$A9,0,-H9) -> 147.57282 | K9: same as Fall/Spring
A10: =A9+1 -> 2 | C10: 2017-18 | E10: ='Fee Revenue'!K12 -> 90 | F10: ='Fee Revenue'!K15 -> 9 | G10: ='Fee Revenue'!K18 -> 60 | H10: ='Fee Revenue'!K20 -> 159 | I10: =PV($G$39,$A10,0,-H10) -> 149.87275 | K10: " "
A11: =A10+1 -> 3 | C11: 2018-19 | E11: ='Fee Revenue'!N12 -> 93.75 | F11: ='Fee Revenue'!N15 -> 9.25 | G11: ='Fee Revenue'!N18 -> 64 | H11: ='Fee Revenue'!N20 -> 167 | I11: =PV($G$39,$A11,0,-H11) -> 152.82866 | K11: " "
A12: =A11+1 -> 4 | C12: 2019-20 | E12: ='Fee Revenue'!Q12 -> 97.5 | F12: ='Fee Revenue'!Q15 -> 9.5 | G12: ='Fee Revenue'!Q18 -> 68 | H12: ='Fee Revenue'!Q20 -> 175 | I12: =PV($G$39,$A12,0,-H12) -> 155.48523 | K12: " "
A13: =A12+1 -> 5 | C13: 2020-21 | E13: ='Fee Revenue'!T12 -> 100.25 | F13: ='Fee Revenue'!T15 -> 9.75 | G13: ='Fee Revenue'!T18 -> 72 | H13: ='Fee Revenue'!T20 -> 182 | I13: =PV($G$39,$A13,0,-H13) -> 156.9948 | K13: " "
A14: =A13+1 -> 6 | C14: 2021-22 | E14: ='Fee Revenue'!W12 -> 104 | F14: ='Fee Revenue'!W15 -> 10 | G14: ='Fee Revenue'!W18 -> 76 | H14: ='Fee Revenue'!W20 -> 190 | I14: =PV($G$39,$A14,0,-H14) -> 159.12201 | K14: " "
A15: =A14+1 -> 7 | C15: 2022-23 | E15: ='Fee Revenue'!Z12 -> 107.75 | F15: ='Fee Revenue'!Z15 -> 10.25 | G15: ='Fee Revenue'!Z18 -> 81 | H15: ='Fee Revenue'!Z20 -> 199 | I15: =PV($G$39,$A15,0,-H15) -> 161.80521 | K15: " "
A16: =A15+1 -> 8 | C16: 2023-24 | E16: ='Fee Revenue'!AC12 -> 111.5 | F16: ='Fee Revenue'!AC15 -> 10.5 | G16: ='Fee Revenue'!AC18 -> 86 | H16: ='Fee Revenue'!AC20 -> 208 | I16: =PV($G$39,$A16,0,-H16) -> 164.19712 | K16: " "
A17: =A16+1 -> 9 | C17: 2024-25 | E17: ='Fee Revenue'!AF12 -> 115.25 | F17: ='Fee Revenue'!AF15 -> 10.75 | G17: ='Fee Revenue'!AF18 -> 91 | H17: ='Fee Revenue'!AF20 -> 217 | I17: =PV($G$39,$A17,0,-H17) -> 166.31243 | K17: " "
A18: =A17+1 -> 10 | C18: 2025-26 | E18: ='Fee Revenue'!AI12 -> 120 | F18: ='Fee Revenue'!AI15 -> 11 | G18: ='Fee Revenue'!AI18 -> 97 | H18: ='Fee Revenue'!AI20 -> 228 | I18: =PV($G$39,$A18,0,-H18) -> 169.65341 | K18: " "
A19: =A18+1 -> 11 | C19: 2026-27 | E19: ='Fee Revenue'!AL12 -> 124.75 | F19: ='Fee Revenue'!AL15 -> 11.25 | G19: ='Fee Revenue'!AL18 -> 103 | H19: ='Fee Revenue'!AL20 -> 239 | I19: =PV($G$39,$A19,0,-H19) -> 172.65869 | K19: " "
A20: =A19+1 -> 12 | C20: 2027-28 | E20: ='Fee Revenue'!AO12 -> 128.5 | F20: ='Fee Revenue'!AO15 -> 11.5 | G20: ='Fee Revenue'!AO18 -> 109 | H20: ='Fee Revenue'!AO20 -> 249 | I20: =PV($G$39,$A20,0,-H20) -> 174.64359 | K20: " "
A21: =A20+1 -> 13 | C21: 2028-29 | E21: ='Fee Revenue'!AR12 -> 132.25 | F21: ='Fee Revenue'!AR15 -> 11.75 | G21: ='Fee Revenue'!AR18 -> 116 | H21: ='Fee Revenue'!AR20 -> 260 | I21: =PV($G$39,$A21,0,-H21) -> 177.04735 | K21: " "
A22: =A21+1 -> 14 | C22: 2029-30 | E22: ='Fee Revenue'!AU12 -> 137 | F22: ='Fee Revenue'!AU15 -> 12 | G22: ='Fee Revenue'!AU18 -> 123 | H22: ='Fee Revenue'!AU20 -> 272 | I22: =PV($G$39,$A22,0,-H22) -> 179.82404 | K22: " "
A23: =A22+1 -> 15 | C23: 2030-31 | E23: ='Fee Revenue'!AX12 -> 141.75 | F23: ='Fee Revenue'!AX15 -> 12.25 | G23: ='Fee Revenue'!AX18 -> 130 | H23: ='Fee Revenue'!AX20 -> 284 | I23: =PV($G$39,$A23,0,-H23) -> 182.28879 | K23: " "
A24: =A23+1 -> 16 | C24: 2031-32 | E24: ='Fee Revenue'!BA12 -> 146.5 | F24: ='Fee Revenue'!BA15 -> 12.5 | G24: ='Fee Revenue'!BA18 -> 138 | H24: ='Fee Revenue'!BA20 -> 297 | I24: =PV($G$39,$A24,0,-H24) -> 185.08058 | K24: " "
A25: =A24+1 -> 17 | C25: 2032-33 | E25: ='Fee Revenue'!BD12 -> 152 | F25: ='Fee Revenue'!BD15 -> 13 | G25: ='Fee Revenue'!BD18 -> 146 | H25: ='Fee Revenue'!BD20 -> 311 | I25: =PV($G$39,$A25,0,-H25) -> 188.16011 | K25: " "
A26: =A25+1 -> 18 | C26: 2033-34 | E26: ='Fee Revenue'!BG12 -> 157.5 | F26: ='Fee Revenue'!BG15 -> 13.5 | G26: ='Fee Revenue'!BG18 -> 155 | H26: ='Fee Revenue'!BG20 -> 326 | I26: =PV($G$39,$A26,0,-H26) -> 191.49064 | K26: " "
A27: =A26+1 -> 19 | C27: 2034-35 | E27: ='Fee Revenue'!BJ12 -> 163 | F27: ='Fee Revenue'!BJ15 -> 14 | G27: ='Fee Revenue'!BJ18 -> 164 | H27: ='Fee Revenue'!BJ20 -> 341 | I27: =PV($G$39,$A27,0,-H27) -> 194.46754 | K27: " "
A28: =A27+1 -> 20 | C28: 2035-36 | E28: ='Fee Revenue'!BM12 -> 168.5 | F28: ='Fee Revenue'!BM15 -> 14.5 | G28: ='Fee Revenue'!BM18 -> 174 | H28: ='Fee Revenue'!BM20 -> 357 | I28: =PV($G$39,$A28,0,-H28) -> 197.66224 | K28: " "
A29: =A28+1 -> 21 | C29: 2036-37 | E29: ='Fee Revenue'!BP12 -> 175 | F29: ='Fee Revenue'!BP15 -> 15 | G29: ='Fee Revenue'!BP18 -> 185 | H29: ='Fee Revenue'!BP20 -> 375 | I29: =PV($G$39,$A29,0,-H29) -> 201.58098 | K29: " "
A30: =A29+1 -> 22 | C30: 2037-38 | E30: ='Fee Revenue'!BS12 -> 180.5 | F30: ='Fee Revenue'!BS15 -> 15.5 | G30: ='Fee Revenue'!BS18 -> 196 | H30: ='Fee Revenue'!BS20 -> 392 | I30: =PV($G$39,$A30,0,-H30) -> 204.58186 | K30: " "
A31: =A30+1 -> 23 | C31: 2038-39 | E31: ='Fee Revenue'!BV12 -> 187 | F31: ='Fee Revenue'!BV15 -> 16 | G31: ='Fee Revenue'!BV18 -> 208 | H31: ='Fee Revenue'!BV20 -> 411 | I31: =PV($G$39,$A31,0,-H31) -> 208.25031 | K31: " "
A32: =A31+1 -> 24 | C32: 2039-40 | E32: ='Fee Revenue'!BY12 -> 193.5 | F32: ='Fee Revenue'!BY15 -> 16.5 | G32: ='Fee Revenue'!BY18 -> 221 | H32: ='Fee Revenue'!BY20 -> 431 | I32: =PV($G$39,$A32,0,-H32) -> 212.02344 | K32: " "
A33: =A32+1 -> 25 | C33: 2040-41 | E33: ='Fee Revenue'!CB12 -> 200 | F33: ='Fee Revenue'!CB15 -> 17 | G33: ='Fee Revenue'!CB18 -> 234 | H33: ='Fee Revenue'!CB20 -> 451 | I33: =PV($G$39,$A33,0,-H33) -> 215.40011 | K33: " "
A34: =A33+1 -> 26 | C34: 2041-42 | E34: ='Fee Revenue'!CE12 -> 206.5 | F34: ='Fee Revenue'!CE15 -> 17.5 | G34: ='Fee Revenue'!CE18 -> 248 | H34: ='Fee Revenue'!CE20 -> 472 | I34: =PV($G$39,$A34,0,-H34) -> 218.86391 | K34: " "
A35: =A34+1 -> 27 | C35: 2042-43 | E35: ='Fee Revenue'!CH12 -> 214 | F35: ='Fee Revenue'!CH15 -> 18 | G35: ='Fee Revenue'!CH18 -> 263 | H35: ='Fee Revenue'!CH20 -> 495 | I35: =PV($G$39,$A35,0,-H35) -> 222.84358 | K35: " "
A36: =A35+1 -> 28 | C36: 2043-44 | E36: ='Fee Revenue'!CK12 -> 220.5 | F36: ='Fee Revenue'!CK15 -> 18.5 | G36: ='Fee Revenue'!CK18 -> 279 | H36: ='Fee Revenue'!CK20 -> 518 | I36: =PV($G$39,$A36,0,-H36) -> 226.40576 | K36: " "
A37: =A36+1 -> 29 | C37: 2044-45 | E37: ='Fee Revenue'!CN12 -> 228 | F37: ='Fee Revenue'!CN15 -> 19 | G37: ='Fee Revenue'!CN18 -> 296 | H37: ='Fee Revenue'!CN20 -> 543 | I37: =PV($G$39,$A37,0,-H37) -> 230.42007 | K37: " "
C39: * assumes inflation of: | G39: 0.03

Sheet Fee Breakdown
B2: Wellness Referendum
B3: Fee Breakdown
B4: prepared by Hugh G. Graham, Campus Budget Office
B7: Approximate break-down of gross fee revenue (subject to change) | D7: 2015-16
B9: 1 | C9: Return-to-aid | D9: =-'Model Summary'!F9 -> 0.26604692
C10: (33% for all UC students, 0% non-UC summer students)
B12: 2 | C12: RSF Existing Services & Programs | D12: ='Model Summary'!F38 -> 0.48079816
B14: 3 | C14: UHS extended hours, sexual assault student resources, and improved mental health counseling along with operational, furnishing, and alteration costs to provide such services | D14: ='Model Summary'!F42 -> 0.13360953
B16: 4 | C16: New wellness services including operational, furnishings, and alteration costs to provide such services | D16: ='Model Summary'!F46 -> 0.077352887
B18: 5 | C18: Diversity student wellness programs and associated costs | D18: ='Model Summary'!F50 -> 0.028128322
B20: 6 | C20: Wellness sustainability plan to lower student costs over time | D20: ='Model Summary'!F53 -> 0.0070320806
B22: 7 | C22: Sexual assault prevention and support | D22: ='Model Summary'!F56 -> 0.0070320806
D24: ='Model Summary'!F58 -> 0
B26: TOTAL | D26: =SUM(D9:D25) -> 0.99999999

Sheet New Services - Budget Breakdown
B2: Wellness Referendum
B3: New Services – Budget Breakdown
B4: prepared by Hugh G. Graham, Campus Budget Office
B5: ='Model Summary'!B5 -> REVISED DRAFT 2/26/15
B7: 5a. | C7: UHS extended hours and improved mental health counseling along with operational, furnishing, and alteration costs to provide such services
D10: TOTAL | F10: UHS
D11: $ | F11: % | G11: $
C12: Hours of operation:
C13: 2 evenings until 8pm | D13: 235638 | F13: 1 | G13: =$D13*F13 -> 235638
C14: Sunday | D14: 412376 | F14: 1 | G14: =$D14*F14 -> 412376
C15: Saturday | D15: 111568 | F15: 1 | G15: =$D15*F15 -> 111568
C16: subtotal | D16: =SUM(D13:D15) -> 759582 | F16: 1 | G16: =$D16*F16 -> 759582
C18: counselings in academic bldgs | D18: 0 | F18: 1 | G18: =$D18*F18 -> 0
C20: counselings in primary care | D20: 1023731 | F20: 1 | G20: =$D20*F20 -> 1023731
C22: TOTAL | D22: =SUM(D16:D21) -> 1783313 | F22: 1 | G22: =$D22*F22 -> 1783313
B25: 5b. | C25: New wellness services including operational, furnishings, and alteration costs to provide such services
D27: TOTAL | F27: UHS | I27: RSF
D28: $ | F28: % | G28: $ | I28: % | J28: $
C30: Item X | D30: 0 | F30: 0 | G30: =$D30*F30 -> 0 | I30: 0 | J30: =$D30*I30 -> 0
C32: Item Y | D32: 0 | F32: 0 | G32: =$D32*F32 -> 0 | I32: 0 | J32: =$D32*I32 -> 0
C34: Item Z | D34: 0 | F34: 0 | G34: =$D34*F34 -> 0 | I34: 0 | J34: =$D34*I34 -> 0
C36: TOTAL | D36: =SUM(D30:D35) -> 0 | F36: 1 | G36: =$D36*F36 -> 0 | I36: 0 | J36: =$D36*I36 -> 0
B38: 5c. | C38: Diversity student wellness programs and associated costs
D40: TOTAL | F40: UHS | I40: RSF
D41: $ | F41: % | G41: $ | I41: % | J41: $
C43: Item X | D43: 0 | F43: 0 | G43: =$D43*F43 -> 0 | I43: 0 | J43: =$D43*I43 -> 0
C45: Item Y | D45: 0 | F45: 0 | G45: =$D45*F45 -> 0 | I45: 0 | J45: =$D45*I45 -> 0
C47: Item Z | D47: 0 | F47: 0 | G47: =$D47*F47 -> 0 | I47: 0 | J47: =$D47*I47 -> 0
C49: TOTAL | D49: =SUM(D43:D48) -> 0 | F49: 1 | G49: =$D49*F49 -> 0 | I49: 0 | J49: =$D49*I49 -> 0
B51: 5d. | C51: Wellness sustainability plan to lower student costs over time
D53: TOTAL | F53: UHS | I53: RSF
D54: $ | F54: % | G54: $ | I54: % | J54: $
C56: Item X | D56: 0 | F56: 0 | G56: =$D56*F56 -> 0 | I56: 0 | J56: =$D56*I56 -> 0
C58: Item Y | D58: 0 | F58: 0 | G58: =$D58*F58 -> 0 | I58: 0 | J58: =$D58*I58 -> 0
C60: Item Z | D60: 0 | F60: 0 | G60: =$D60*F60 -> 0 | I60: 0 | J60: =$D60*I60 -> 0
C62: TOTAL | D62: =SUM(D56:D61) -> 0 | F62: 1 | G62: =$D62*F62 -> 0 | I62: 0 | J62: =$D62*I62 -> 0
B64: 5e. | C64: Sexual assault prevention and support
D66: TOTAL | F66: Dean of Students
D67: $ | F67: % | G67: $
C69: Item X | D69: 0 | F69: 1 | G69: =$D69*F69 -> 0
C71: Item Y | D71: 0 | F71: 1 | G71: =$D71*F71 -> 0
C73: Item Z | D73: 0 | F73: 1 | G73: =$D73*F73 -> 0
C75: TOTAL | D75: =SUM(D69:D74) -> 0 | F75: 1 | G75: =$D75*F75 -> 0
B77: 5f. | C77: Campus-wide wellness incentive program
D79: TOTAL | F79: UHS | I79: RSF
D80: $ | F80: % | G80: $ | I80: % | J80: $
C82: Item X | D82: 0 | F82: 0 | G82: =$D82*F82 -> 0 | I82: 0 | J82: =$D82*I82 -> 0
C84: Item Y | D84: 0 | F84: 0 | G84: =$D84*F84 -> 0 | I84: 0 | J84: =$D84*I84 -> 0
C86: Item Z | D86: 0 | F86: 0 | G86: =$D86*F86 -> 0 | I86: 0 | J86: =$D86*I86 -> 0
C88: TOTAL | D88: =SUM(D82:D87) -> 0 | F88: 1 | G88: =$D88*F88 -> 0 | I88: 0 | J88: =$D88*I88 -> 0

Sheet Chart - Surplus (Deficit)
B2: Wellness Referendum Model Surplus (Deficit) Chart – 30 years
B4: prepared by Hugh G. Graham, Campus Budget Office
B5: ='Model Summary'!B5 -> REVISED DRAFT 2/26/15
B7: $ in millions
B8: Surplus (Deficit) | C8: 2015-16 | D8: 2016-17 | E8: 2017-18 | F8: 2018-19 | G8: 2019-20 | H8: 2020-21 | I8: 2021-22 | J8: 2022-23 | K8: 2023-24 | L8: 2024-25 | M8: 2025-26 | N8: 2026-27 | O8: 2027-28 | P8: 2028-29 | Q8: 2029-30 | R8: 2030-31 | S8: 2031-32 | T8: 2032-33 | U8: 2033-34 | V8: 2034-35 | W8: 2035-36 | X8: 2036-37 | Y8: 2037-38 | Z8: 2038-39 | AA8: 2039-40 | AB8: 2040-41 | AC8: 2041-42 | AD8: 2042-43 | AE8: 2043-44 | AF8: 2044-45 | AG8: TOTAL
B9: RSF Existing Services | C9: ='Model Summary'!D64 -> 0.15666667 | D9: ='Model Summary'!G64 -> 0 | E9: ='Model Summary'!J64 -> 0 | F9: ='Model Summary'!M64 -> 0 | G9: ='Model Summary'!P64 -> 0 | H9: ='Model Summary'!S64 -> 0 | I9: ='Model Summary'!V64 -> 0 | J9: ='Model Summary'!Y64 -> 0 | K9: ='Model Summary'!AB64 -> 0 | L9: ='Model Summary'!AE64 -> 0 | M9: ='Model Summary'!AH64 -> 0 | N9: ='Model Summary'!AK64 -> 0 | O9: ='Model Summary'!AN64 -> 0 | P9: ='Model Summary'!AQ64 -> 0 | Q9: ='Model Summary'!AT64 -> 0 | R9: ='Model Summary'!AW64 -> 0 | S9: ='Model Summary'!AZ64 -> 0 | T9: ='Model Summary'!BC64 -> 0 | U9: ='Model Summary'!BF64 -> 0 | V9: ='Model Summary'!BI64 -> 0 | W9: ='Model Summary'!BL64 -> 0 | X9: ='Model Summary'!BO64 -> 0 | Y9: ='Model Summary'!BR64 -> 0 | Z9: ='Model Summary'!BU64 -> 0 | AA9: ='Model Summary'!BX64 -> 0 | AB9: ='Model Summary'!CA64 -> 0 | AC9: ='Model Summary'!CD64 -> 0 | AD9: ='Model Summary'!CG64 -> 0 | AE9: ='Model Summary'!CJ64 -> 0 | AF9: ='Model Summary'!CM64 -> 0 | AG9: =SUM(C9:AF9) -> 0.15666667
B10: New Services | C10: ='Model Summary'!D65 -> 0 | D10: ='Model Summary'!G65 -> -6867.7778 | E10: ='Model Summary'!J65 -> -24783.9 | F10: ='Model Summary'!M65 -> 5848.7546 | G10: ='Model Summary'!P65 -> 23910.221 | H10: ='Model Summary'!S65 -> 28559.951 | I10: ='Model Summary'!V65 -> 18899.743 | J10: ='Model Summary'!Y65 -> 54303.072 | K10: ='Model Summary'!AB65 -> 73410.811 | L10: ='Model Summary'!AE65 -> 62793.32 | M10: ='Model Summary'!AH65 -> 106278.88 | N10: ='Model Summary'!AK65 -> 117615.14 | O10: ='Model Summary'!AN65 -> 120130.13 | P10: ='Model Summary'!AQ65 -> 148059.67 | Q10: ='Model Summary'!AT65 -> 151874.22 | R10: ='Model Summary'!AW65 -> 142272.06 | S10: ='Model Summary'!AZ65 -> 153171.96 | T10: ='Model Summary'!BC65 -> 134705.27 | U10: ='Model Summary'!BF65 -> 132874.25 | V10: ='Model Summary'!BI65 -> 109876.39 | W10: ='Model Summary'!BL65 -> 111428.1 | X10: ='Model Summary'!BO65 -> 122754.47 | Y10: ='Model Summary'!BR65 -> 93244.918 | Z10: ='Model Summary'!BU65 -> 80441.391 | AA10: ='Model Summary'!BX65 -> 81359.13 | AB10: ='Model Summary'!CA65 -> 32473.183 | AC10: ='Model Summary'!CD65 -> -21629.346 | AD10: ='Model Summary'!CG65 -> -72264.722 | AE10: ='Model Summary'!CJ65 -> -123335.75 | AF10: ='Model Summary'!CM65 -> -179016.08 | AG10: =SUM(C10:AF10) -> 1678387.5
B11: COMBINED | C11: =SUM(C9:C10) -> 0.15666667 | D11: =SUM(D9:D10) -> -6867.7778 | E11: =SUM(E9:E10) -> -24783.9 | F11: =SUM(F9:F10) -> 5848.7546 | G11: =SUM(G9:G10) -> 23910.221 | H11: =SUM(H9:H10) -> 28559.951 | I11: =SUM(I9:I10) -> 18899.743 | J11: =SUM(J9:J10) -> 54303.072 | ... AF11: =SUM(AF9:AF10) -> -179016.08 | AG11: =SUM(C11:AF11) -> 1678387.6

Sheet Chart - Fee Breakdown
B2: Wellness Referendum Model Fee $'s Per Year Breakdown – 30 years
B4: prepared by Hugh G. Graham, Campus Budget Office
B5: ='Model Summary'!B5 -> REVISED DRAFT 2/26/15
B7: $ in millions
B8: Breakdown of Fee $'s Per Year | C8: 2015-16 | D8: 2016-17 | E8: 2017-18 | F8: 2018-19 | G8: 2019-20 | H8: 2020-21 | I8: 2021-22 | J8: 2022-23 | K8: 2023-24 | L8: 2024-25 | M8: 2025-26 | N8: 2026-27 | O8: 2027-28 | P8: 2028-29 | Q8: 2029-30 | R8: 2030-31 | S8: 2031-32 | T8: 2032-33 | U8: 2033-34 | V8: 2034-35 | W8: 2035-36 | X8: 2036-37 | Y8: 2037-38 | Z8: 2038-39 | AA8: 2039-40 | AB8: 2040-41 | AC8: 2041-42 | AD8: 2042-43 | AE8: 2043-44 | AF8: 2044-45
B9: Return-to-aid | C9: =-'Model Summary'!F9*'Fee Revenue'!E20*2 -> 77.685702 | D9: =-'Model Summary'!I9*'Fee Revenue'!H20*2 -> 81.517037 | E9: =-'Model Summary'!L9*'Fee Revenue'!K20*2 -> 101.48118 | F9: =-'Model Summary'!O9*'Fee Revenue'!N20*2 -> 106.59458 | G9: =-'Model Summary'!R9*'Fee Revenue'!Q20*2 -> 111.70797 | H9: =-'Model Summary'!U9*'Fee Revenue'!T20*2 -> 116.18907 | I9: =-'Model Summary'!X9*'Fee Revenue'!W20*2 -> 121.30246 | J9: =-'Model Summary'!AA9*'Fee Revenue'!Z20*2 -> 127.04816 | K9: =-'Model Summary'!AD9*'Fee Revenue'!AC20*2 -> 132.79801 | L9: =-'Model Summary'!AG9*'Fee Revenue'!AF20*2 -> 138.57792 | M9: =-'Model Summary'!AJ9*'Fee Revenue'!AI20*2 -> 145.59653 | N9: =-'Model Summary'!AM9*'Fee Revenue'!AL20*2 -> 152.64522 | O9: =-'Model Summary'!AP9*'Fee Revenue'!AO20*2 -> 159.03151 | P9: =-'Model Summary'!AS9*'Fee Revenue'!AR20*2 -> 166.0802 | Q9: =-'Model Summary'!AV9*'Fee Revenue'!AU20*2 -> 173.76535 | R9: =-'Model Summary'!AY9*'Fee Revenue'!AX20*2 -> 181.4204 | S9: =-'Model Summary'!BB9*'Fee Revenue'!BA20*2 -> 189.74199 | T9: =-'Model Summary'!BE9*'Fee Revenue'!BD20*2 -> 198.69592 | U9: =-'Model Summary'!BH9*'Fee Revenue'!BG20*2 -> 208.32047 | V9: =-'Model Summary'!BK9*'Fee Revenue'!BJ20*2 -> 217.91084 | W9: =-'Model Summary'!BN9*'Fee Revenue'!BM20*2 -> 228.13764 | X9: =-'Model Summary'!BQ9*'Fee Revenue'!BP20*2 -> 239.66335 | Y9: =-'Model Summary'!BT9*'Fee Revenue'!BS20*2 -> 250.5567 | Z9: =-'Model Summary'!BW9*'Fee Revenue'!BV20*2 -> 262.71885 | AA9: =-'Model Summary'!BZ9*'Fee Revenue'!BY20*2 -> 275.51742 | AB9: =-'Model Summary'!CC9*'Fee Revenue'!CB20*2 -> 288.31599 | AC9: =-'Model Summary'!CF9*'Fee Revenue'!CE20*2 -> 301.78112 | AD9: =-'Model Summary'!CI9*'Fee Revenue'!CH20*2 -> 316.51506 | AE9: =-'Model Summary'!CL9*'Fee Revenue'!CK20*2 -> 331.25301 | AF9: =-'Model Summary'!CO9*'Fee Revenue'!CN20*2 -> 347.25577
B10: ISF Debt Service | C10: ='Model Summary'!F34*'Fee Revenue'!E20*2 -> 22.006891 | D10: ='Model Summary'!I34*'Fee Revenue'!H20*2 -> 16.259105 | E10: ='Model Summary'!L34*'Fee Revenue'!K20*2 -> 0 | F10: ='Model Summary'!O34*'Fee Revenue'!N20*2 -> 0 | G10: ='Model Summary'!R34*'Fee Revenue'!Q20*2 -> 0 | H10: ='Model Summary'!U34*'Fee Revenue'!T20*2 -> 0 | I10: ='Model Summary'!X34*'Fee Revenue'!W20*2 -> 0 | J10: ='Model Summary'!AA34*'Fee Revenue'!Z20*2 -> 0 | K10: ='Model Summary'!AD34*'Fee Revenue'!AC20*2 -> 0 | L10: ='Model Summary'!AG34*'Fee Revenue'!AF20*2 -> 0 | M10: ='Model Summary'!AJ34*'Fee Revenue'!AI20*2 -> 0 | N10: ='Model Summary'!AM34*'Fee Revenue'!AL20*2 -> 0 | O10: ='Model Summary'!AP34*'Fee Revenue'!AO20*2 -> 0 | P10: ='Model Summary'!AS34*'Fee Revenue'!AR20*2 -> 0 | Q10: ='Model Summary'!AV34*'Fee Revenue'!AU20*2 -> 0 | R10: ='Model Summary'!AY34*'Fee Revenue'!AX20*2 -> 0 | S10: ='Model Summary'!BB34*'Fee Revenue'!BA20*2 -> 0 | T10: ='Model Summary'!BE34*'Fee Revenue'!BD20*2 -> 0 | U10: ='Model Summary'!BH34*'Fee Revenue'!BG20*2 -> 0 | V10: ='Model Summary'!BK34*'Fee Revenue'!BJ20*2 -> 0 | W10: ='Model Summary'!BN34*'Fee Revenue'!BM20*2 -> 0 | X10: ='Model Summary'!BQ34*'Fee Revenue'!BP20*2 -> 0 | Y10: ='Model Summary'!BT34*'Fee Revenue'!BS20*2 -> 0 | Z10: ='Model Summary'!BW34*'Fee Revenue'!BV20*2 -> 0 | AA10: ='Model Summary'!BZ34*'Fee Revenue'!BY20*2 -> 0 | AB10: ='Model Summary'!CC34*'Fee Revenue'!CB20*2 -> 0 | AC10: ='Model Summary'!CF34*'Fee Revenue'!CE20*2 -> 0 | AD10: ='Model Summary'!CI34*'Fee Revenue'!CH20*2 -> 0 | AE10: ='Model Summary'!CL34*'Fee Revenue'!CK20*2 -> 0 | AF10: ='Model Summary'!CO34*'Fee Revenue'!CN20*2 -> 0
B11: RSF Existing Services | C11: ='Model Summary'!F32*'Fee Revenue'!E20*2 -> 116.03732 | D11: ='Model Summary'!I32*'Fee Revenue'!H20*2 -> 120.27752 | E11: ='Model Summary'!L32*'Fee Revenue'!K20*2 -> 123.46607 | F11: ='Model Summary'!O32*'Fee Revenue'!N20*2 -> 127.65527 | G11: ='Model Summary'!R32*'Fee Revenue'!Q20*2 -> 131.98873 | H11: ='Model Summary'!U32*'Fee Revenue'!T20*2 -> 136.48893 | I11: ='Model Summary'!X32*'Fee Revenue'!W20*2 -> 135.46184 | J11: ='Model Summary'!AA32*'Fee Revenue'!Z20*2 -> 140.43542 | K11: ='Model Summary'!AD32*'Fee Revenue'!AC20*2 -> 145.47231 | L11: ='Model Summary'!AG32*'Fee Revenue'!AF20*2 -> 150.71554 | M11: ='Model Summary'!AJ32*'Fee Revenue'!AI20*2 -> 156.14917 | N11: ='Model Summary'!AM32*'Fee Revenue'!AL20*2 -> 156.05297 | O11: ='Model Summary'!AP32*'Fee Revenue'!AO20*2 -> 161.79259 | P11: ='Model Summary'!AS32*'Fee Revenue'!AR20*2 -> 167.82863 | Q11: ='Model Summary'!AV32*'Fee Revenue'!AU20*2 -> 174.041 | R11: ='Model Summary'!AY32*'Fee Revenue'!AX20*2 -> 180.43388 | S11: ='Model Summary'!BB32*'Fee Revenue'!BA20*2 -> 187.04775 | T11: ='Model Summary'!BE32*'Fee Revenue'!BD20*2 -> 193.95211 | U11: ='Model Summary'!BH32*'Fee Revenue'!BG20*2 -> 200.99971 | V11: ='Model Summary'!BK32*'Fee Revenue'!BJ20*2 -> 208.34902 | W11: ='Model Summary'!BN32*'Fee Revenue'!BM20*2 -> 215.91996 | X11: ='Model Summary'!BQ32*'Fee Revenue'!BP20*2 -> 223.8122 | Y11: ='Model Summary'!BT32*'Fee Revenue'!BS20*2 -> 231.90556 | Z11: ='Model Summary'!BW32*'Fee Revenue'!BV20*2 -> 240.30813 | AA11: ='Model Summary'!BZ32*'Fee Revenue'!BY20*2 -> 248.96719 | AB11: ='Model Summary'!CC32*'Fee Revenue'!CB20*2 -> 257.91739 | AC11: ='Model Summary'!CF32*'Fee Revenue'!CE20*2 -> 267.17064 | AD11: ='Model Summary'!CI32*'Fee Revenue'!CH20*2 -> 276.76867 | AE11: ='Model Summary'!CL32*'Fee Revenue'!CK20*2 -> 286.60518 | AF11: ='Model Summary'!CO32*'Fee Revenue'!CN20*2 -> 296.88797
B12: RSF equip/maint reserves | C12: ='Model Summary'!F36*'Fee Revenue'!E20*2 -> 2.3488507 | D12: ='Model Summary'!I36*'Fee Revenue'!H20*2 -> 8.5221373 | E12: ='Model Summary'!L36*'Fee Revenue'!K20*2 -> 12.208283 | F12: ='Model Summary'!O36*'Fee Revenue'!N20*2 -> 13.511052 | G12: ='Model Summary'!R36*'Fee Revenue'!Q20*2 -> 14.669416 | H12: ='Model Summary'!U36*'Fee Revenue'!T20*2 -> 14.349438 | I12: ='Model Summary'!X36*'Fee Revenue'!W20*2 -> 20.868736 | J12: ='Model Summary'!AA36*'Fee Revenue'!Z20*2 -> 21.277218 | K12: ='Model Summary'!AD36*'Fee Revenue'!AC20*2 -> 21.698148 | L12: ='Model Summary'!AG36*'Fee Revenue'!AF20*2 -> 22.146903 | M12: ='Model Summary'!AJ36*'Fee Revenue'!AI20*2 -> 23.446178 | N12: ='Model Summary'!AM36*'Fee Revenue'!AL20*2 -> 30.507739 | O12: ='Model Summary'!AP36*'Fee Revenue'!AO20*2 -> 30.194077 | P12: ='Model Summary'!AS36*'Fee Revenue'!AR20*2 -> 29.701428 | Q12: ='Model Summary'!AV36*'Fee Revenue'!AU20*2 -> 30.420225 | R12: ='Model Summary'!AY36*'Fee Revenue'!AX20*2 -> 30.726739 | S12: ='Model Summary'!BB36*'Fee Revenue'!BA20*2 -> 31.012475 | T12: ='Model Summary'!BE36*'Fee Revenue'!BD20*2 -> 32.308948 | U12: ='Model Summary'!BH36*'Fee Revenue'!BG20*2 -> 33.750907 | V12: ='Model Summary'!BK36*'Fee Revenue'!BJ20*2 -> 34.570685 | W12: ='Model Summary'!BN36*'Fee Revenue'!BM20*2 -> 35.138238 | X12: ='Model Summary'!BQ36*'Fee Revenue'!BP20*2 -> 36.881835 | Y12: ='Model Summary'!BT36*'Fee Revenue'!BS20*2 -> 37.125373 | Z12: ='Model Summary'!BW36*'Fee Revenue'!BV20*2 -> 38.326879 | AA12: ='Model Summary'!BZ36*'Fee Revenue'!BY20*2 -> 39.24212 | AB12: ='Model Summary'!CC36*'Fee Revenue'!CB20*2 -> 39.865883 | AC12: ='Model Summary'!CF36*'Fee Revenue'!CE20*2 -> 40.385399 | AD12: ='Model Summary'!CI36*'Fee Revenue'!CH20*2 -> 41.824921 | AE12: ='Model Summary'!CL36*'Fee Revenue'!CK20*2 -> 41.705255 | AF12: ='Model Summary'!CO36*'Fee Revenue'!CN20*2 -> 42.300128
B13: New Services | C13: ='Model Summary'!F60*'Fee Revenue'!E20*2 -> 73.921231 | D13: ='Model Summary'!I60*'Fee Revenue'!H20*2 -> 77.586989 | E13: ='Model Summary'!L60*'Fee Revenue'!K20*2 -> 81.427767 | F13: ='Model Summary'!O60*'Fee Revenue'!N20*2 -> 86.101442 | G13: ='Model Summary'!R60*'Fee Revenue'!Q20*2 -> 91.07108 | H13: ='Model Summary'!U60*'Fee Revenue'!T20*2 -> 96.300674 | I13: ='Model Summary'!X60*'Fee Revenue'!W20*2 -> 101.9223 | J13: ='Model Summary'!AA60*'Fee Revenue'!Z20*2 -> 107.96085 | K13: ='Model Summary'!AD60*'Fee Revenue'!AC20*2 -> 114.30363 | L13: ='Model Summary'!AG60*'Fee Revenue'!AF20*2 -> 121.08155 | M13: ='Model Summary'!AJ60*'Fee Revenue'!AI20*2 -> 128.30609 | N13: ='Model Summary'!AM60*'Fee Revenue'!AL20*2 -> 136.02427 | O13: ='Model Summary'!AP60*'Fee Revenue'!AO20*2 -> 144.1537 | P13: ='Model Summary'!AS60*'Fee Revenue'!AR20*2 -> 152.90306 | Q13: ='Model Summary'!AV60*'Fee Revenue'!AU20*2 -> 162.19651 | R13: ='Model Summary'!AY60*'Fee Revenue'!AX20*2 -> 172.06842 | S13: ='Model Summary'!BB60*'Fee Revenue'!BA20*2 -> 182.59067 | T13: ='Model Summary'!BE60*'Fee Revenue'!BD20*2 -> 193.86983 | U13: ='Model Summary'!BH60*'Fee Revenue'!BG20*2 -> 205.79936 | V13: ='Model Summary'!BK60*'Fee Revenue'!BJ20*2 -> 218.58118 | W13: ='Model Summary'!BN60*'Fee Revenue'!BM20*2 -> 232.17929 | X13: ='Model Summary'!BQ60*'Fee Revenue'!BP20*2 -> 246.75006 | Y13: ='Model Summary'!BT60*'Fee Revenue'!BS20*2 -> 262.21514 | Z13: ='Model Summary'!BW60*'Fee Revenue'!BV20*2 -> 278.75031 | AA13: ='Model Summary'!BZ60*'Fee Revenue'!BY20*2 -> 296.35572 | AB13: ='Model Summary'!CC60*'Fee Revenue'!CB20*2 -> 315.13535 | AC13: ='Model Summary'!CF60*'Fee Revenue'!CE20*2 -> 335.17267 | AD13: ='Model Summary'!CI60*'Fee Revenue'!CH20*2 -> 356.595 | AE13: ='Model Summary'!CL60*'Fee Revenue'!CK20*2 -> 379.34382 | AF13: ='Model Summary'!CO60*'Fee Revenue'!CN20*2 -> 403.77702
B14: TOTAL | C14: =SUM(C9:C13) -> 292 | D14: =SUM(D9:D13) -> 304.16279 | E14: =SUM(E9:E13) -> 318.5833 | F14: =SUM(F9:F13) -> 333.86234 | G14: =SUM(G9:G13) -> 349.4372 | H14: =SUM(H9:H13) -> 363.32811 | I14: =SUM(I9:I13) -> 379.55534 | J14: =SUM(J9:J13) -> 396.72164 | ... AF14: =SUM(AF9:AF13) -> 1090.2209

Sheet Model Summary
B2: Wellness Referendum Model
B3: Model Summary – 30 years
B4: prepared by Hugh G. Graham, Campus Budget Office | D4: 2015-16 | G4: 2016-17 | J4: 2017-18 | M4: 2018-19 | P4: 2019-20 | S4: 2020-21 | V4: 2021-22 | Y4: 2022-23 | AB4: 2023-24 | AE4: 2024-25 | AH4: 2025-26 | AK4: 2026-27 | AN4: 2027-28 | AQ4: 2028-29 | AT4: 2029-30 | AW4: 2030-31 | AZ4: 2031-32 | BC4: 2032-33 | BF4: 2033-34 | BI4: 2034-35 | BL4: 2035-36 | BO4: 2036-37 | BR4: 2037-38 | BU4: 2038-39 | BX4: 2039-40 | CA4: 2040-41 | CD4: 2041-42 | CG4: 2042-43 | CJ4: 2043-44 | CM4: 2044-45
B5: REVISED DRAFT 2/26/15 | D5: $ | E5: % growth | F5: % of gross fee | G5: $ | H5: % growth | I5: % of gross fee | J5: $ | K5: % growth | L5: % of gross fee | M5: $ | N5: % growth | O5: % of gross fee | P5: $ | Q5: % growth | R5: % of gross fee | S5: $ | T5: % growth | U5: % of gross fee | V5: $ | W5: % growth | X5: % of gross fee | Y5: $ | Z5: % growth | AA5: % of gross fee | AB5: $ | AC5: % growth | AD5: % of gross fee | AE5: $ | AF5: % growth | AG5: % of gross fee | AH5: $ | AI5: % growth | AJ5: % of gross fee | AK5: $ | AL5: % growth | AM5: % of gross fee | AN5: $ | AO5: % growth | AP5: % of gross fee | AQ5: $ | AR5: % growth | AS5: % of gross fee | AT5: $ | AU5: % growth | AV5: % of gross fee | AW5: $ | AX5: % growth | AY5: % of gross fee | AZ5: $ | BA5: % growth | BB5: % of gross fee | BC5: $ | BD5: % growth | BE5: % of gross fee | BF5: $ | BG5: % growth | BH5: % of gross fee | BI5: $ | BJ5: % growth | BK5: % of gross fee | BL5: $ | BM5: % growth | BN5: % of gross fee | BO5: $ | BP5: % growth | BQ5: % of gross fee | BR5: $ | BS5: % growth | BT5: % of gross fee | BU5: $ | BV5: % growth | BW5: % of gross fee | BX5: $ | BY5: % growth | BZ5: % of gross fee | CA5: $ | CB5: % growth | CC5: % of gross fee | CD5: $ | CE5: % growth | CF5: % of gross fee | CG5: $ | CH5: % growth | CI5: % of gross fee | CJ5: $ | CK5: % growth | CL5: % of gross fee | CM5: $ | CN5: % growth | CO5: % of gross fee
B6: REVENUE / INFLOWS
B7: 1 | C7: Net Fee Revenue - TOTAL
B8: a. | C8: Gross Fee Revenue | D8: ='Fee Revenue'!E70+'Fee Revenue'!E72+'Fee Revenue'!E74 -> 12236250 | E8: n/a | F8: =D8/D8 -> 1 | G8: ='Fee Revenue'!H70+'Fee Revenue'!H72+'Fee Revenue'!H74 -> 12825000 | H8: =(G8-D8)/D8 -> 0.048115231 | I8: =G8/G8 -> 1 | J8: ='Fee Revenue'!K70+'Fee Revenue'!K72+'Fee Revenue'!K74 -> 13511500 | K8: =(J8-G8)/G8 -> 0.053528265 | L8: =J8/J8 -> 1 | M8: ='Fee Revenue'!N70+'Fee Revenue'!N72+'Fee Revenue'!N74 -> 14190500 | N8: =(M8-J8)/J8 -> 0.050253488 | O8: =M8/M8 -> 1 | P8: ='Fee Revenue'!Q70+'Fee Revenue'!Q72+'Fee Revenue'!Q74 -> 14869500 | Q8: =(P8-M8)/M8 -> 0.047848913 | R8: =P8/P8 -> 1 | S8: ='Fee Revenue'!T70+'Fee Revenue'!T72+'Fee Revenue'!T74 -> 15472500 | T8: =(S8-P8)/P8 -> 0.040552809 | U8: =S8/S8 -> 1 | V8: ='Fee Revenue'!W70+'Fee Revenue'!W72+'Fee Revenue'!W74 -> 16151500 | W8: =(V8-S8)/S8 -> 0.043884311 | X8: =V8/V8 -> 1 | Y8: ='Fee Revenue'!Z70+'Fee Revenue'!Z72+'Fee Revenue'!Z74 -> 16906500 | Z8: =(Y8-V8)/V8 -> 0.046744884 | AA8: =Y8/Y8 -> 1 | AB8: ='Fee Revenue'!AC70+'Fee Revenue'!AC72+'Fee Revenue'!AC74 -> 17674000 | AC8: =(AB8-Y8)/Y8 -> 0.045396741 | AD8: =AB8/AB8 -> 1 | AE8: ='Fee Revenue'!AF70+'Fee Revenue'!AF72+'Fee Revenue'!AF74 -> 18437500 | AF8: =(AE8-AB8)/AB8 -> 0.043199049 | AG8: =AE8/AE8 -> 1 | AH8: ='Fee Revenue'!AI70+'Fee Revenue'!AI72+'Fee Revenue'!AI74 -> 19369500 | AI8: =(AH8-AE8)/AE8 -> 0.050549153 | AJ8: =AH8/AH8 -> 1 | AK8: ='Fee Revenue'!AL70+'Fee Revenue'!AL72+'Fee Revenue'!AL74 -> 20297500 | AL8: =(AK8-AH8)/AH8 -> 0.047910375 | AM8: =AK8/AK8 -> 1 | AN8: ='Fee Revenue'!AO70+'Fee Revenue'!AO72+'Fee Revenue'!AO74 -> 21153500 | AO8: =(AN8-AK8)/AK8 -> 0.042172681 | AP8: =AN8/AN8 -> 1 | AQ8: ='Fee Revenue'!AR70+'Fee Revenue'!AR72+'Fee Revenue'!AR74 -> 22081500 | AR8: =(AQ8-AN8)/AN8 -> 0.043869809 | AS8: =AQ8/AQ8 -> 1 | AT8: ='Fee Revenue'!AU70+'Fee Revenue'!AU72+'Fee Revenue'!AU74 -> 23098000 | AU8: =(AT8-AQ8)/AQ8 -> 0.04603401 | AV8: =AT8/AT8 -> 1 | AW8: ='Fee Revenue'!AX70+'Fee Revenue'!AX72+'Fee Revenue'!AX74 -> 24118500 | AX8: =(AW8-AT8)/AT8 -> 0.044181314 | AY8: =AW8/AW8 -> 1 | AZ8: ='Fee Revenue'!BA70+'Fee Revenue'!BA72+'Fee Revenue'!BA74 -> 25223500 | BA8: =(AZ8-AW8)/AW8 -> 0.045815453 | BB8: =AZ8/AZ8 -> 1 | BC8: ='Fee Revenue'!BD70+'Fee Revenue'!BD72+'Fee Revenue'!BD74 -> 26404500 | BD8: =(BC8-AZ8)/AZ8 -> 0.046821417 | BE8: =BC8/BC8 -> 1 | BF8: ='Fee Revenue'!BG70+'Fee Revenue'!BG72+'Fee Revenue'!BG74 -> 27682500 | BG8: =(BF8-BC8)/BC8 -> 0.048400841 | BH8: =BF8/BF8 -> 1 | BI8: ='Fee Revenue'!BJ70+'Fee Revenue'!BJ72+'Fee Revenue'!BJ74 -> 28952000 | BJ8: =(BI8-BF8)/BF8 -> 0.045859297 | BK8: =BI8/BI8 -> 1 | BL8: ='Fee Revenue'!BM70+'Fee Revenue'!BM72+'Fee Revenue'!BM74 -> 30310000 | BM8: =(BL8-BI8)/BI8 -> 0.046905222 | BN8: =BL8/BL8 -> 1 | BO8: ='Fee Revenue'!BP70+'Fee Revenue'!BP72+'Fee Revenue'!BP74 -> 31828500 | BP8: =(BO8-BL8)/BL8 -> 0.050098977 | BQ8: =BO8/BO8 -> 1 | BR8: ='Fee Revenue'!BS70+'Fee Revenue'!BS72+'Fee Revenue'!BS74 -> 33271000 | BS8: =(BR8-BO8)/BO8 -> 0.045321017 | BT8: =BR8/BR8 -> 1 | BU8: ='Fee Revenue'!BV70+'Fee Revenue'!BV72+'Fee Revenue'!BV74 -> 34878000 | BV8: =(BU8-BR8)/BR8 -> 0.048300322 | BW8: =BU8/BU8 -> 1 | BX8: ='Fee Revenue'!BY70+'Fee Revenue'!BY72+'Fee Revenue'!BY74 -> 36573500 | BY8: =(BX8-BU8)/BU8 -> 0.048612306 | BZ8: =BX8/BX8 -> 1 | CA8: ='Fee Revenue'!CB70+'Fee Revenue'!CB72+'Fee Revenue'!CB74 -> 38269000 | CB8: =(CA8-BX8)/BX8 -> 0.046358702 | CC8: =CA8/CA8 -> 1 | CD8: ='Fee Revenue'!CE70+'Fee Revenue'!CE72+'Fee Revenue'!CE74 -> 40049000 | CE8: =(CD8-CA8)/CA8 -> 0.046512843 | CF8: =CD8/CD8 -> 1 | CG8: ='Fee Revenue'!CH70+'Fee Revenue'!CH72+'Fee Revenue'!CH74 -> 41993500 | CH8: =(CG8-CD8)/CD8 -> 0.048553023 | CI8: =CG8/CG8 -> 1 | CJ8: ='Fee Revenue'!CK70+'Fee Revenue'!CK72+'Fee Revenue'!CK74 -> 43950500 | CK8: =(CJ8-CG8)/CG8 -> 0.04660245 | CL8: =CJ8/CJ8 -> 1 | CM8: ='Fee Revenue'!CN70+'Fee Revenue'!CN72+'Fee Revenue'!CN74 -> 46059500 | CN8: =(CM8-CJ8)/CJ8 -> 0.047985802 | CO8: =CM8/CM8 -> 1
B9: b. | C9: Less: Return-to-Aid (UC students only) | D9: ='Fee Revenue'!E71+'Fee Revenue'!E73 -> -3255416.7 | E9: n/a | F9: =D9/D8 -> -0.26604692 | G9: ='Fee Revenue'!H71+'Fee Revenue'!H73 -> -3439000 | H9: =(G9-D9)/D9 -> 0.056393191 | I9: =G9/G8 -> -0.26814815 | J9: ='Fee Revenue'!K71+'Fee Revenue'!K73 -> -4311833.3 | K9: =(J9-G9)/G9 -> 0.2538044 | L9: =J9/J8 -> -0.31912322 | M9: ='Fee Revenue'!N71+'Fee Revenue'!N73 -> -4528833.3 | N9: =(M9-J9)/J9 -> 0.050326621 | O9: =M9/M8 -> -0.31914544 | P9: ='Fee Revenue'!Q71+'Fee Revenue'!Q73 -> -4745833.3 | Q9: =(P9-M9)/M9 -> 0.04791521 | R9: =P9/P8 -> -0.31916563 | S9: ='Fee Revenue'!T71+'Fee Revenue'!T73 -> -4938833.3 | T9: =(S9-P9)/P9 -> 0.040667252 | U9: =S9/S8 -> -0.31920073 | V9: ='Fee Revenue'!W71+'Fee Revenue'!W73 -> -5155833.3 | W9: =(V9-S9)/S9 -> 0.043937502 | X9: =V9/V8 -> -0.319217 | Y9: ='Fee Revenue'!Z71+'Fee Revenue'!Z73 -> -5396833.3 | Z9: =(Y9-V9)/V9 -> 0.046743171 | AA9: =Y9/Y8 -> -0.31921647 | AB9: ='Fee Revenue'!AC71+'Fee Revenue'!AC73 -> -5642000 | AC9: =(AB9-Y9)/Y9 -> 0.045427874 | AD9: =AB9/AB8 -> -0.31922598 | AE9: ='Fee Revenue'!AF71+'Fee Revenue'!AF73 -> -5887166.7 | AF9: =(AE9-AB9)/AB9 -> 0.043453858 | AG9: =AE9/AE8 -> -0.31930395 | AH9: ='Fee Revenue'!AI71+'Fee Revenue'!AI73 -> -6184500 | AI9: =(AH9-AE9)/AE9 -> 0.050505336 | AJ9: =AH9/AH8 -> -0.31929064 | AK9: ='Fee Revenue'!AL71+'Fee Revenue'!AL73 -> -6481833.3 | AL9: =(AK9-AH9)/AH9 -> 0.048077182 | AM9: =AK9/AK8 -> -0.31934146 | AN9: ='Fee Revenue'!AO71+'Fee Revenue'!AO73 -> -6755166.7 | AO9: =(AN9-AK9)/AK9 -> 0.042169139 | AP9: =AN9/AN8 -> -0.31934038 | AQ9: ='Fee Revenue'!AR71+'Fee Revenue'!AR73 -> -7052500 | AR9: =(AQ9-AN9)/AN9 -> 0.044015692 | AS9: =AQ9/AQ8 -> -0.31938501 | AT9: ='Fee Revenue'!AU71+'Fee Revenue'!AU73 -> -7378000 | AU9: =(AT9-AQ9)/AQ9 -> 0.046153846 | AV9: =AT9/AT8 -> -0.31942159 | AW9: ='Fee Revenue'!AX71+'Fee Revenue'!AX73 -> -7703500 | AX9: =(AW9-AT9)/AT9 -> 0.044117647 | AY9: =AW9/AW8 -> -0.31940212 | AZ9: ='Fee Revenue'!BA71+'Fee Revenue'!BA73 -> -8057166.7 | BA9: =(AZ9-AW9)/AW9 -> 0.045909868 | BB9: =AZ9/AZ8 -> -0.31943095 | BC9: ='Fee Revenue'!BD71+'Fee Revenue'!BD73 -> -8434833.3 | BD9: =(BC9-AZ9)/AZ9 -> 0.046873384 | BE9: =BC9/BC8 -> -0.31944681 | BF9: ='Fee Revenue'!BG71+'Fee Revenue'!BG73 -> -8844833.3 | BG9: =(BF9-BC9)/BC9 -> 0.048607955 | BH9: =BF9/BF8 -> -0.31950992 | BI9: ='Fee Revenue'!BJ71+'Fee Revenue'!BJ73 -> -9250666.7 | BJ9: =(BI9-BF9)/BF9 -> 0.045883661 | BK9: =BI9/BI8 -> -0.31951736 | BL9: ='Fee Revenue'!BM71+'Fee Revenue'!BM73 -> -9684666.7 | BM9: =(BL9-BI9)/BI9 -> 0.046915538 | BN9: =BL9/BL8 -> -0.31952051 | BO9: ='Fee Revenue'!BP71+'Fee Revenue'!BP73 -> -10170833 | BP9: =(BO9-BL9)/BL9 -> 0.050199628 | BQ9: =BO9/BO8 -> -0.31955114 | BR9: ='Fee Revenue'!BS71+'Fee Revenue'!BS73 -> -10633000 | BS9: =(BR9-BO9)/BO9 -> 0.045440393 | BT9: =BR9/BR8 -> -0.31958763 | BU9: ='Fee Revenue'!BV71+'Fee Revenue'!BV73 -> -11147333 | BV9: =(BU9-BR9)/BR9 -> 0.048371422 | BW9: =BU9/BU8 -> -0.3196093 | BX9: ='Fee Revenue'!BY71+'Fee Revenue'!BY73 -> -11689833 | BY9: =(BX9-BU9)/BU9 -> 0.048666348 | BZ9: =BX9/BX8 -> -0.31962578 | CA9: ='Fee Revenue'!CB71+'Fee Revenue'!CB73 -> -12232333 | CB9: =(CA9-BX9)/BX9 -> 0.046407847 | CC9: =CA9/CA8 -> -0.31964079 | CD9: ='Fee Revenue'!CE71+'Fee Revenue'!CE73 -> -12803000 | CE9: =(CD9-CA9)/CA9 -> 0.046652315 | CF9: =CD9/CD8 -> -0.31968339 | CG9: ='Fee Revenue'!CH71+'Fee Revenue'!CH73 -> -13425833 | CH9: =(CG9-CD9)/CD9 -> 0.048647452 | CI9: =CG9/CG8 -> -0.31971218 | CJ9: ='Fee Revenue'!CK71+'Fee Revenue'!CK73 -> -14052833 | CK9: =(CJ9-CG9)/CG9 -> 0.046701012 | CL9: =CJ9/CJ8 -> -0.31974229 | CM9: ='Fee Revenue'!CN71+'Fee Revenue'!CN73 -> -14727833 | CN9: =(CM9-CJ9)/CJ9 -> 0.048033018 | CO9: =CM9/CM8 -> -0.31975669
B10: c. | C10: TOTAL NET FEE REVENUE (= line 3) | D10: ='Fee Revenue'!E75 -> 8980833.3 | E10: n/a | F10: =D10/D8 -> 0.73395308 | G10: ='Fee Revenue'!H75 -> 9386000 | H10: =(G10-D10)/D10 -> 0.045114596 | I10: =G10/G8 -> 0.73185185 | J10: ='Fee Revenue'!K75 -> 9199666.7 | K10: =(J10-G10)/G10 -> -0.019852262 | L10: =J10/J8 -> 0.68087678 | M10: ='Fee Revenue'!N75 -> 9661666.7 | N10: =(M10-J10)/J10 -> 0.050219211 | O10: =M10/M8 -> 0.68085456 | P10: ='Fee Revenue'!Q75 -> 10123667 | Q10: =(P10-M10)/M10 -> 0.047817837 | R10: =P10/P8 -> 0.68083437 | S10: ='Fee Revenue'!T75 -> 10533667 | T10: =(S10-P10)/P10 -> 0.04049916 | U10: =S10/S8 -> 0.68079927 | V10: ='Fee Revenue'!W75 -> 10995667 | W10: =(V10-S10)/S10 -> 0.043859372 | X10: =V10/V8 -> 0.680783 | Y10: ='Fee Revenue'!Z75 -> 11509667 | Z10: =(Y10-V10)/V10 -> 0.046745688 | AA10: =Y10/Y8 -> 0.68078353 | AB10: ='Fee Revenue'!AC75 -> 12032000 | AC10: =(AB10-Y10)/Y10 -> 0.045382143 | AD10: =AB10/AB8 -> 0.68077402 | AE10: ='Fee Revenue'!AF75 -> 12550333 | AF10: =(AE10-AB10)/AB10 -> 0.043079566 | AG10: =AE10/AE8 -> 0.68069605 | AH10: ='Fee Revenue'!AI75 -> 13185000 | AI10: =(AH10-AE10)/AE10 -> 0.050569706 | AJ10: =AH10/AH8 -> 0.68070936 | AK10: ='Fee Revenue'!AL75 -> 13815667 | AL10: =(AK10-AH10)/AH10 -> 0.047832132 | AM10: =AK10/AK8 -> 0.68065854 | AN10: ='Fee Revenue'!AO75 -> 14398333 | AO10: =(AN10-AK10)/AK10 -> 0.042174343 | AP10: =AN10/AN8 -> 0.68065962 | AQ10: ='Fee Revenue'!AR75 -> 15029000 | AR10: =(AQ10-AN10)/AN10 -> 0.043801366 | AS10: =AQ10/AQ8 -> 0.68061499 | AT10: ='Fee Revenue'!AU75 -> 15720000 | AU10: =(AT10-AQ10)/AQ10 -> 0.045977776 | AV10: =AT10/AT8 -> 0.68057841 | AW10: ='Fee Revenue'!AX75 -> 16415000 | AX10: =(AW10-AT10)/AT10 -> 0.044211196 | AY10: =AW10/AW8 -> 0.68059788 | AZ10: ='Fee Revenue'!BA75 -> 17166333 | BA10: =(AZ10-AW10)/AW10 -> 0.045771144 | BB10: =AZ10/AZ8 -> 0.68056905 | BC10: ='Fee Revenue'!BD75 -> 17969667 | BD10: =(BC10-AZ10)/AZ10 -> 0.046797025 | BE10: =BC10/BC8 -> 0.68055319 | BF10: ='Fee Revenue'!BG75 -> 18837667 | BG10: =(BF10-BC10)/BC10 -> 0.048303623 | BH10: =BF10/BF8 -> 0.68049008 | BI10: ='Fee Revenue'!BJ75 -> 19701333 | BJ10: =(BI10-BF10)/BF10 -> 0.045847858 | BK10: =BI10/BI8 -> 0.68048264 | BL10: ='Fee Revenue'!BM75 -> 20625333 | BM10: =(BL10-BI10)/BI10 -> 0.046900379 | BN10: =BL10/BL8 -> 0.68047949 | BO10: ='Fee Revenue'!BP75 -> 21657667 | BP10: =(BO10-BL10)/BL10 -> 0.050051716 | BQ10: =BO10/BO8 -> 0.68044886 | BR10: ='Fee Revenue'!BS75 -> 22638000 | BS10: =(BR10-BO10)/BO10 -> 0.045264956 | BT10: =BR10/BR8 -> 0.68041237 | BU10: ='Fee Revenue'!BV75 -> 23730667 | BV10: =(BU10-BR10)/BR10 -> 0.048266926 | BW10: =BU10/BU8 -> 0.6803907 | BX10: ='Fee Revenue'!BY75 -> 24883667 | BY10: =(BX10-BU10)/BU10 -> 0.04858692 | BZ10: =BX10/BX8 -> 0.68037422 | CA10: ='Fee Revenue'!CB75 -> 26036667 | CB10: =(CA10-BX10)/BX10 -> 0.046335615 | CC10: =CA10/CA8 -> 0.68035921 | CD10: ='Fee Revenue'!CE75 -> 27246000 | CE10: =(CD10-CA10)/CA10 -> 0.046447318 | CF10: =CD10/CD8 -> 0.68031661 | CG10: ='Fee Revenue'!CH75 -> 28567667 | CH10: =(CG10-CD10)/CD10 -> 0.04850865 | CI10: =CG10/CG8 -> 0.68028782 | CJ10: ='Fee Revenue'!CK75 -> 29897667 | CK10: =(CJ10-CG10)/CG10 -> 0.04655613 | CL10: =CJ10/CJ8 -> 0.68025771 | CM10: ='Fee Revenue'!CN75 -> 31331667 | CN10: =(CM10-CJ10)/CJ10 -> 0.047963609 | CO10: =CM10/CM8 -> 0.68024331
B12: 2 | C12: Net Fee Revenue - BREAKDOWN
B13: a. | C13: RSF Base Fee Revenue | D13: ='Fee Revenue'!E51 -> 5370333.3 | E13: n/a | F13: =D13/D$8 -> 0.43888719 | G13: ='Fee Revenue'!H51 -> 5591750 | I13: =G13/G$8 -> 0.4360039 | J13: ='Fee Revenue'!K51 -> 5221666.7 | L13: =J13/J$8 -> 0.38646092 | M13: ='Fee Revenue'!N51 -> 5439583.3 | O13: =M13/M$8 -> 0.3833257 | P13: ='Fee Revenue'!Q51 -> 5657500 | R13: =P13/P$8 -> 0.38047682 | S13: ='Fee Revenue'!T51 -> 5823416.7 | U13: =S13/S$8 -> 0.37637206 | V13: ='Fee Revenue'!W51 -> 6041333.3 | X13: =V13/V$8 -> 0.37404163 | Y13: ='Fee Revenue'!Z51 -> 6250916.7 | AA13: =Y13/Y$8 -> 0.36973452 | AB13: ='Fee Revenue'!AC51 -> 6468833.3 | AD13: =AB13/AB$8 -> 0.36600845 | AE13: ='Fee Revenue'!AF51 -> 6695083.3 | AG13: =AE13/AE$8 -> 0.36312316 | AH13: ='Fee Revenue'!AI51 -> 6965000 | AJ13: =AH13/AH$8 -> 0.35958595 | AK13: ='Fee Revenue'!AL51 -> 7243250 | AM13: =AK13/AK$8 -> 0.35685429 | AN13: ='Fee Revenue'!AO51 -> 7461166.7 | AP13: =AN13/AN$8 -> 0.35271547 | AQ13: ='Fee Revenue'!AR51 -> 7679083.3 | AS13: =AQ13/AQ$8 -> 0.34776095 | AT13: ='Fee Revenue'!AU51 -> 7957333.3 | AV13: =AT13/AT$8 -> 0.34450313 | AW13: ='Fee Revenue'!AX51 -> 8227250 | AY13: =AW13/AW$8 -> 0.34111781 | AZ13: ='Fee Revenue'!BA51 -> 8505500 | BB13: =AZ13/AZ$8 -> 0.33720538 | BC13: ='Fee Revenue'!BD51 -> 8820666.7 | BE13: =BC13/BC$8 -> 0.33405922 | BF13: ='Fee Revenue'!BG51 -> 9152500 | BH13: =BF13/BF$8 -> 0.33062404 | BI13: ='Fee Revenue'!BJ51 -> 9467666.7 | BK13: =BI13/BI$8 -> 0.32701253 | BL13: ='Fee Revenue'!BM51 -> 9782833.3 | BN13: =BL13/BL$8 -> 0.32275927 | BO13: ='Fee Revenue'!BP51 -> 10158333 | BQ13: =BO13/BO$8 -> 0.31915841 | BR13: ='Fee Revenue'!BS51 -> 10481833 | BT13: =BR13/BR$8 -> 0.31504413 | BU13: ='Fee Revenue'!BV51 -> 10857333 | BW13: =BU13/BU$8 -> 0.31129461 | BX13: ='Fee Revenue'!BY51 -> 11232833 | BZ13: =BX13/BX$8 -> 0.30713039 | CA13: ='Fee Revenue'!CB51 -> 11608333 | CC13: =CA13/CA$8 -> 0.30333516 | CD13: ='Fee Revenue'!CE51 -> 11992167 | CF13: =CD13/CD$8 -> 0.29943736 | CG13: ='Fee Revenue'!CH51 -> 12428000 | CI13: =CG13/CG$8 -> 0.29595056 | CJ13: ='Fee Revenue'!CK51 -> 12811833 | CL13: =CJ13/CJ$8 -> 0.29150597 | CM13: ='Fee Revenue'!CN51 -> 13239333 | CO13: =CM13/CM$8 -> 0.2874398
B14: b. | C14: RSF Membership Fee Buy-Out Revenue | D14: ='Fee Revenue'!E59 -> 512833.33 | E14: n/a | F14: =D14/D$8 -> 0.041910989 | G14: ='Fee Revenue'!H59 -> 527916.67 | I14: =G14/G$8 -> 0.041163093 | J14: ='Fee Revenue'!K59 -> 543000 | L14: =J14/J$8 -> 0.040187988 | M14: ='Fee Revenue'!N59 -> 558083.33 | O14: =M14/M$8 -> 0.039327954 | P14: ='Fee Revenue'!Q59 -> 573166.67 | R14: =P14/P$8 -> 0.038546465 | S14: ='Fee Revenue'!T59 -> 588250 | U14: =S14/S$8 -> 0.038019066 | V14: ='Fee Revenue'!W59 -> 603333.33 | X14: =V14/V$8 -> 0.037354632 | Y14: ='Fee Revenue'!Z59 -> 618416.67 | AA14: =Y14/Y$8 -> 0.036578633 | AB14: ='Fee Revenue'!AC59 -> 633500 | AD14: =AB14/AB$8 -> 0.035843612 | AE14: ='Fee Revenue'!AF59 -> 648583.33 | AG14: =AE14/AE$8 -> 0.035177401 | AH14: ='Fee Revenue'!AI59 -> 663666.67 | AJ14: =AH14/AH$8 -> 0.03426349 | AK14: ='Fee Revenue'!AL59 -> 678750 | AM14: =AK14/AK$8 -> 0.033440079 | AN14: ='Fee Revenue'!AO59 -> 693833.33 | AP14: =AN14/AN$8 -> 0.032799931 | AQ14: ='Fee Revenue'!AR59 -> 708916.67 | AS14: =AQ14/AQ$8 -> 0.032104552 | AT14: ='Fee Revenue'!AU59 -> 724000 | AV14: =AT14/AT$8 -> 0.031344705 | AW14: ='Fee Revenue'!AX59 -> 739083.33 | AY14: =AW14/AW$8 -> 0.030643835 | AZ14: ='Fee Revenue'!BA59 -> 754166.67 | BB14: =AZ14/AZ$8 -> 0.029899366 | BC14: ='Fee Revenue'!BD59 -> 784333.33 | BE14: =BC14/BC$8 -> 0.029704533 | BF14: ='Fee Revenue'!BG59 -> 814500 | BH14: =BF14/BF$8 -> 0.029422921 | BI14: ='Fee Revenue'!BJ59 -> 844666.67 | BK14: =BI14/BI$8 -> 0.029174726 | BL14: ='Fee Revenue'!BM59 -> 874833.33 | BN14: =BL14/BL$8 -> 0.028862862 | BO14: ='Fee Revenue'!BP59 -> 905000 | BQ14: =BO14/BO$8 -> 0.028433637 | BR14: ='Fee Revenue'!BS59 -> 935166.67 | BT14: =BR14/BR$8 -> 0.028107561 | BU14: ='Fee Revenue'!BV59 -> 965333.33 | BW14: =BU14/BU$8 -> 0.027677428 | BX14: ='Fee Revenue'!BY59 -> 995500 | BZ14: =BX14/BX$8 -> 0.027219161 | CA14: ='Fee Revenue'!CB59 -> 1025666.7 | CC14: =CA14/CA$8 -> 0.026801502 | CD14: ='Fee Revenue'!CE59 -> 1055833.3 | CF14: =CD14/CD$8 -> 0.026363538 | CG14: ='Fee Revenue'!CH59 -> 1086000 | CI14: =CG14/CG$8 -> 0.025861145 | CJ14: ='Fee Revenue'!CK59 -> 1116166.7 | CL14: =CJ14/CJ$8 -> 0.025395995 | CM14: ='Fee Revenue'!CN59 -> 1146333.3 | CO14: =CM14/CM$8 -> 0.024888098
B15: c. | C15: RSF - TOTAL NET FEE REVENUE | D15: =SUM(D13:D14) -> 5883166.7 | E15: n/a | F15: =D15/D$8 -> 0.48079817 | G15: =SUM(G13:G14) -> 6119666.7 | H15: =(G15-D15)/D15 -> 0.040199439 | I15: =G15/G$8 -> 0.47716699 | J15: =SUM(J13:J14) -> 5764666.7 | K15: =(J15-G15)/G15 -> -0.058009696 | L15: =J15/J$8 -> 0.4266489 | M15: =SUM(M13:M14) -> 5997666.7 | N15: =(M15-J15)/J15 -> 0.040418642 | O15: =M15/M$8 -> 0.42265365 | P15: =SUM(P13:P14) -> 6230666.7 | Q15: =(P15-M15)/M15 -> 0.038848441 | R15: =P15/P$8 -> 0.41902328 | S15: =SUM(S13:S14) -> 6411666.7 | T15: =(S15-P15)/P15 -> 0.029049861 | U15: =S15/S$8 -> 0.41439112 | V15: =SUM(V13:V14) -> 6644666.7 | W15: =(V15-S15)/S15 -> 0.036340005 | X15: =V15/V$8 -> 0.41139626 | Y15: =SUM(Y13:Y14) -> 6869333.3 | Z15: =(Y15-V15)/V15 -> 0.033811578 | AA15: =Y15/Y$8 -> 0.40631315 | AB15: =SUM(AB13:AB14) -> 7102333.3 | AC15: =(AB15-Y15)/Y15 -> 0.033918866 | AD15: =AB15/AB$8 -> 0.40185206 | AE15: =SUM(AE13:AE14) -> 7343666.7 | AF15: =(AE15-AB15)/AB15 -> 0.033979443 | AG15: =AE15/AE$8 -> 0.39830056 | AH15: =SUM(AH13:AH14) -> 7628666.7 | AI15: =(AH15-AE15)/AE15 -> 0.038808951 | AJ15: =AH15/AH$8 -> 0.39384944 | AK15: =SUM(AK13:AK14) -> 7922000 | AL15: =(AK15-AH15)/AH15 -> 0.038451455 | AM15: =AK15/AK$8 -> 0.39029437 | AN15: =SUM(AN13:AN14) -> 8155000 | AO15: =(AN15-AK15)/AK15 -> 0.029411765 | AP15: =AN15/AN$8 -> 0.3855154 | AQ15: =SUM(AQ13:AQ14) -> 8388000 | AR15: =(AQ15-AN15)/AN15 -> 0.028571429 | AS15: =AQ15/AQ$8 -> 0.3798655 | AT15: =SUM(AT13:AT14) -> 8681333.3 | AU15: =(AT15-AQ15)/AQ15 -> 0.034970593 | AV15: =AT15/AT$8 -> 0.37584784 | AW15: =SUM(AW13:AW14) -> 8966333.3 | AX15: =(AW15-AT15)/AT15 -> 0.032829059 | AY15: =AW15/AW$8 -> 0.37176165 | AZ15: =SUM(AZ13:AZ14) -> 9259666.7 | BA15: =(AZ15-AW15)/AW15 -> 0.032714971 | BB15: =AZ15/AZ$8 -> 0.36710475 | BC15: =SUM(BC13:BC14) -> 9605000 | BD15: =(BC15-AZ15)/AZ15 -> 0.037294359 | BE15: =BC15/BC$8 -> 0.36376375 | BF15: =SUM(BF13:BF14) -> 9967000 | BG15: =(BF15-BC15)/BC15 -> 0.037688704 | BH15: =BF15/BF$8 -> 0.36004696 | BI15: =SUM(BI13:BI14) -> 10312333 | BJ15: =(BI15-BF15)/BF15 -> 0.034647671 | BK15: =BI15/BI$8 -> 0.35618725 | BL15: =SUM(BL13:BL14) -> 10657667 | BM15: =(BL15-BI15)/BI15 -> 0.03348741 | BN15: =BL15/BL$8 -> 0.35162213 | BO15: =SUM(BO13:BO14) -> 11063333 | BP15: =(BO15-BL15)/BL15 -> 0.038063366 | BQ15: =BO15/BO$8 -> 0.34759204 | BR15: =SUM(BR13:BR14) -> 11417000 | BS15: =(BR15-BO15)/BO15 -> 0.03196746 | BT15: =BR15/BR$8 -> 0.34315169 | BU15: =SUM(BU13:BU14) -> 11822667 | BV15: =(BU15-BR15)/BR15 -> 0.035531809 | BW15: =BU15/BU$8 -> 0.33897204 | BX15: =SUM(BX13:BX14) -> 12228333 | BY15: =(BX15-BU15)/BU15 -> 0.03431262 | BZ15: =BX15/BX$8 -> 0.33434955 | CA15: =SUM(CA13:CA14) -> 12634000 | CB15: =(CA15-BX15)/BX15 -> 0.033174322 | CC15: =CA15/CA$8 -> 0.33013666 | CD15: =SUM(CD13:CD14) -> 13048000 | CE15: =(CD15-CA15)/CA15 -> 0.032768719 | CF15: =CD15/CD$8 -> 0.32580089 | CG15: =SUM(CG13:CG14) -> 13514000 | CH15: =(CG15-CD15)/CD15 -> 0.035714286 | CI15: =CG15/CG$8 -> 0.32181171 | CJ15: =SUM(CJ13:CJ14) -> 13928000 | CK15: =(CJ15-CG15)/CG15 -> 0.030634897 | CL15: =CJ15/CJ$8 -> 0.31690197 | CM15: =SUM(CM13:CM14) -> 14385667 | CN15: =(CM15-CJ15)/CJ15 -> 0.032859468 | CO15: =CM15/CM$8 -> 0.31232789
B17: d. | C17: New Fee Increment - Net Revenue | D17: ='Fee Revenue'!E67 -> 3097666.7 | F17: =D17/D$8 -> 0.2531549 | G17: ='Fee Revenue'!H67 -> 3266333.3 | I17: =G17/G$8 -> 0.25468486 | J17: ='Fee Revenue'!K67 -> 3435000 | L17: =J17/J$8 -> 0.25422788 | M17: ='Fee Revenue'!N67 -> 3664000 | O17: =M17/M$8 -> 0.25820091 | P17: ='Fee Revenue'!Q67 -> 3893000 | R17: =P17/P$8 -> 0.26181109 | S17: ='Fee Revenue'!T67 -> 4122000 | U17: =S17/S$8 -> 0.26640814 | V17: ='Fee Revenue'!W67 -> 4351000 | X17: =V17/V$8 -> 0.26938674 | Y17: ='Fee Revenue'!Z67 -> 4640333.3 | AA17: =Y17/Y$8 -> 0.27447037 | AB17: ='Fee Revenue'!AC67 -> 4929666.7 | AD17: =AB17/AB$8 -> 0.27892196 | AE17: ='Fee Revenue'!AF67 -> 5206666.7 | AG17: =AE17/AE$8 -> 0.28239548 | AH17: ='Fee Revenue'!AI67 -> 5556333.3 | AJ17: =AH17/AH$8 -> 0.28685993 | AK17: ='Fee Revenue'!AL67 -> 5893666.7 | AM17: =AK17/AK$8 -> 0.29036417 | AN17: ='Fee Revenue'!AO67 -> 6243333.3 | AP17: =AN17/AN$8 -> 0.29514422 | AQ17: ='Fee Revenue'!AR67 -> 6641000 | AS17: =AQ17/AQ$8 -> 0.3007495 | AT17: ='Fee Revenue'!AU67 -> 7038666.7 | AV17: =AT17/AT$8 -> 0.30473057 | AW17: ='Fee Revenue'!AX67 -> 7448666.7 | AY17: =AW17/AW$8 -> 0.30883623 | AZ17: ='Fee Revenue'!BA67 -> 7906666.7 | BB17: =AZ17/AZ$8 -> 0.3134643 | BC17: ='Fee Revenue'!BD67 -> 8364666.7 | BE17: =BC17/BC$8 -> 0.31678944 | BF17: ='Fee Revenue'!BG67 -> 8870666.7 | BH17: =BF17/BF$8 -> 0.32044312 | BI17: ='Fee Revenue'!BJ67 -> 9389000 | BK17: =BI17/BI$8 -> 0.32429539 | BL17: ='Fee Revenue'!BM67 -> 9967666.7 | BN17: =BL17/BL$8 -> 0.32885736 | BO17: ='Fee Revenue'!BP67 -> 10594333 | BQ17: =BO17/BO$8 -> 0.33285682 | BR17: ='Fee Revenue'!BS67 -> 11221000 | BT17: =BR17/BR$8 -> 0.33726068 | BU17: ='Fee Revenue'!BV67 -> 11908000 | BW17: =BU17/BU$8 -> 0.34141866 | BX17: ='Fee Revenue'!BY67 -> 12655333 | BZ17: =BX17/BX$8 -> 0.34602467 | CA17: ='Fee Revenue'!CB67 -> 13402667 | CC17: =CA17/CA$8 -> 0.35022255 | CD17: ='Fee Revenue'!CE67 -> 14198000 | CF17: =CD17/CD$8 -> 0.35451572 | CG17: ='Fee Revenue'!CH67 -> 15053667 | CI17: =CG17/CG$8 -> 0.35847611 | CJ17: ='Fee Revenue'!CK67 -> 15969667 | CL17: =CJ17/CJ$8 -> 0.36335574 | CM17: ='Fee Revenue'!CN67 -> 16946000 | CO17: =CM17/CM$8 -> 0.36791541
B19: 3 | C19: TOTAL NET FEE REVENUE (= line 1c) | D19: ='Fee Revenue'!E75 -> 8980833.3 | E19: n/a | F19: =D19/D$8 -> 0.73395308 | G19: ='Fee Revenue'!H75 -> 9386000 | H19: =(G19-D19)/D19 -> 0.045114596 | I19: =G19/G$8 -> 0.73185185 | J19: ='Fee Revenue'!K75 -> 9199666.7 | K19: =(J19-G19)/G19 -> -0.019852262 | L19: =J19/J$8 -> 0.68087678 | M19: ='Fee Revenue'!N75 -> 9661666.7 | N19: =(M19-J19)/J19 -> 0.050219211 | O19: =M19/M$8 -> 0.68085456 | P19: ='Fee Revenue'!Q75 -> 10123667 | Q19: =(P19-M19)/M19 -> 0.047817837 | R19: =P19/P$8 -> 0.68083437 | S19: ='Fee Revenue'!T75 -> 10533667 | T19: =(S19-P19)/P19 -> 0.04049916 | U19: =S19/S$8 -> 0.68079927 | V19: ='Fee Revenue'!W75 -> 10995667 | W19: =(V19-S19)/S19 -> 0.043859372 | X19: =V19/V$8 -> 0.680783 | Y19: ='Fee Revenue'!Z75 -> 11509667 | Z19: =(Y19-V19)/V19 -> 0.046745688 | AA19: =Y19/Y$8 -> 0.68078353 | AB19: ='Fee Revenue'!AC75 -> 12032000 | AC19: =(AB19-Y19)/Y19 -> 0.045382143 | AD19: =AB19/AB$8 -> 0.68077402 | AE19: ='Fee Revenue'!AF75 -> 12550333 | AF19: =(AE19-AB19)/AB19 -> 0.043079566 | AG19: =AE19/AE$8 -> 0.68069605 | AH19: ='Fee Revenue'!AI75 -> 13185000 | AI19: =(AH19-AE19)/AE19 -> 0.050569706 | AJ19: =AH19/AH$8 -> 0.68070936 | AK19: ='Fee Revenue'!AL75 -> 13815667 | AL19: =(AK19-AH19)/AH19 -> 0.047832132 | AM19: =AK19/AK$8 -> 0.68065854 | AN19: ='Fee Revenue'!AO75 -> 14398333 | AO19: =(AN19-AK19)/AK19 -> 0.042174343 | AP19: =AN19/AN$8 -> 0.68065962 | AQ19: ='Fee Revenue'!AR75 -> 15029000 | AR19: =(AQ19-AN19)/AN19 -> 0.043801366 | AS19: =AQ19/AQ$8 -> 0.68061499 | AT19: ='Fee Revenue'!AU75 -> 15720000 | AU19: =(AT19-AQ19)/AQ19 -> 0.045977776 | AV19: =AT19/AT$8 -> 0.68057841 | AW19: ='Fee Revenue'!AX75 -> 16415000 | AX19: =(AW19-AT19)/AT19 -> 0.044211196 | AY19: =AW19/AW$8 -> 0.68059788 | AZ19: ='Fee Revenue'!BA75 -> 17166333 | BA19: =(AZ19-AW19)/AW19 -> 0.045771144 | BB19: =AZ19/AZ$8 -> 0.68056905 | BC19: ='Fee Revenue'!BD75 -> 17969667 | BD19: =(BC19-AZ19)/AZ19 -> 0.046797025 | BE19: =BC19/BC$8 -> 0.68055319 | BF19: ='Fee Revenue'!BG75 -> 18837667 | BG19: =(BF19-BC19)/BC19 -> 0.048303623 | BH19: =BF19/BF$8 -> 0.68049008 | BI19: ='Fee Revenue'!BJ75 -> 19701333 | BJ19: =(BI19-BF19)/BF19 -> 0.045847858 | BK19: =BI19/BI$8 -> 0.68048264 | BL19: ='Fee Revenue'!BM75 -> 20625333 | BM19: =(BL19-BI19)/BI19 -> 0.046900379 | BN19: =BL19/BL$8 -> 0.68047949 | BO19: ='Fee Revenue'!BP75 -> 21657667 | BP19: =(BO19-BL19)/BL19 -> 0.050051716 | BQ19: =BO19/BO$8 -> 0.68044886 | BR19: ='Fee Revenue'!BS75 -> 22638000 | BS19: =(BR19-BO19)/BO19 -> 0.045264956 | BT19: =BR19/BR$8 -> 0.68041237 | BU19: ='Fee Revenue'!BV75 -> 23730667 | BV19: =(BU19-BR19)/BR19 -> 0.048266926 | BW19: =BU19/BU$8 -> 0.6803907 | BX19: ='Fee Revenue'!BY75 -> 24883667 | BY19: =(BX19-BU19)/BU19 -> 0.04858692 | BZ19: =BX19/BX$8 -> 0.68037422 | CA19: ='Fee Revenue'!CB75 -> 26036667 | CB19: =(CA19-BX19)/BX19 -> 0.046335615 | CC19: =CA19/CA$8 -> 0.68035921 | CD19: ='Fee Revenue'!CE75 -> 27246000 | CE19: =(CD19-CA19)/CA19 -> 0.046447318 | CF19: =CD19/CD$8 -> 0.68031661 | CG19: ='Fee Revenue'!CH75 -> 28567667 | CH19: =(CG19-CD19)/CD19 -> 0.04850865 | CI19: =CG19/CG$8 -> 0.68028782 | CJ19: ='Fee Revenue'!CK75 -> 29897667 | CK19: =(CJ19-CG19)/CG19 -> 0.04655613 | CL19: =CJ19/CJ$8 -> 0.68025771 | CM19: ='Fee Revenue'!CN75 -> 31331667 | CN19: =(CM19-CJ19)/CJ19 -> 0.047963609 | CO19: =CM19/CM$8 -> 0.68024331
B21: EXPENSES / OUTFLOWS
B23: 4 | C23: RSF - Existing Services
B25: a. | C25: Programs & Services supported by previous fees, net of other revenues | D25: =4862540-D28 -> 4238508 | E25: n/a | F25: =D25/D$8 -> 0.34638946 | G25: =5074208-G28 -> 4415281.9 | H25: =(G25-D25)/D25 -> 0.041706634 | I25: =G25/G$8 -> 0.34427149 | J25: =5245949-J28 -> 4574605.1 | K25: =(J25-G25)/G25 -> 0.036084495 | L25: =J25/J$8 -> 0.33857123 | M25: =5423629-M28 -> 4739494.8 | N25: =(M25-J25)/J25 -> 0.036044572 | O25: =M25/M$8 -> 0.33399068 | P25: =5607447-P28 -> 4910138.8 | Q25: =(P25-M25)/M25 -> 0.036004676 | R25: =P25/P$8 -> 0.33021546 | S25: =5801717-S28 -> 5090839.5 | T25: =(S25-P25)/P25 -> 0.036801557 | U25: =S25/S$8 -> 0.32902501 | V25: =5757663-V28 -> 5277809.2 | W25: =(V25-S25)/S25 -> 0.036726688 | X25: =V25/V$8 -> 0.32676898 | Y25: =5965506-Y28 -> 5471256.6 | Z25: =(Y25-V25)/V25 -> 0.036652971 | AA25: =Y25/Y$8 -> 0.32361852 | AB25: =6180475-AB28 -> 5671398.1 | AC25: =(AB25-Y25)/Y25 -> 0.036580539 | AD25: =AB25/AB$8 -> 0.32088933 | AE25: =6402806-AE28 -> 5878456.8 | AF25: =(AE25-AB25)/AB25 -> 0.036509286 | AG25: =AE25/AE$8 -> 0.31883156 | AH25: =6632744-AH28 -> 6092664.3 | AI25: =(AH25-AE25)/AE25 -> 0.036439415 | AJ25: =AH25/AH$8 -> 0.31454939 | AK25: =6626538-AK28 -> 6070255.9 | AL25: =(AK25-AH25)/AH25 -> -0.0036779296 | AM25: =AK25/AK$8 -> 0.29906422 | AN25: =6872449-AN28 -> 6299478.5 | AO25: =(AN25-AK25)/AK25 -> 0.037761594 | AP25: =AN25/AN$8 -> 0.2977984 | AQ25: =7126746-AQ28 -> 6536586.4 | AR25: =(AQ25-AN25)/AN25 -> 0.037639288 | AS25: =AQ25/AQ$8 -> 0.29602094 | AT25: =7389704-AT28 -> 6781839.6 | AU25: =(AT25-AQ25)/AQ25 -> 0.037520075 | AV25: =AT25/AT$8 -> 0.29361155 | AW25: =7661610-AW28 -> 7035509.6 | AX25: =(AW25-AT25)/AT25 -> 0.037404316 | AY25: =AW25/AW$8 -> 0.29170594 | AZ25: =7942759-AZ28 -> 7297875.6 | BA25: =(AZ25-AW25)/AW25 -> 0.037291682 | BB25: =AZ25/AZ$8 -> 0.28932843 | BC25: =8233454-BC28 -> 7569224.1 | BD25: =(BC25-AZ25)/AZ25 -> 0.037181848 | BE25: =BC25/BC$8 -> 0.28666417 | BF25: =8534010-BF28 -> 7849853.2 | BG25: =(BF25-BC25)/BC25 -> 0.037075016 | BH25: =BF25/BF$8 -> 0.28356735 | BI25: =8844752-BI28 -> 8140070.5 | BJ25: =(BI25-BF25)/BF25 -> 0.036971048 | BK25: =BI25/BI$8 -> 0.28115745 | BL25: =9166014-BL28 -> 8440192.1 | BM25: =(BL25-BI25)/BI25 -> 0.036869651 | BN25: =BL25/BL$8 -> 0.27846229 | BO25: =9498142-BO28 -> 8750545.4 | BP25: =(BO25-BL25)/BL25 -> 0.036770886 | BQ25: =BO25/BO$8 -> 0.27492799 | BR25: =9841492-BR28 -> 9071467.5 | BS25: =(BR25-BO25)/BO25 -> 0.036674526 | BT25: =BR25/BR$8 -> 0.27265389 | BU25: =10196432-BU28 -> 9403306.8 | BV25: =(BU25-BR25)/BR25 -> 0.036580549 | BW25: =BU25/BU$8 -> 0.26960568 | BX25: =10563343-BX28 -> 9746424 | BY25: =(BX25-BU25)/BU25 -> 0.036488998 | BZ25: =BX25/BX$8 -> 0.26648869 | CA25: =10942617-CA28 -> 10101190 | CB25: =(CA25-BX25)/BX25 -> 0.036399651 | CC25: =CA25/CA$8 -> 0.2639523 | CD25: =11334658-CD28 -> 10467989 | CE25: =(CD25-CA25)/CA25 -> 0.036312374 | CF25: =CD25/CD$8 -> 0.26137953 | CG25: =11739884-CG28 -> 10847215 | CH25: =(CG25-CD25)/CD25 -> 0.0362272 | CI25: =CG25/CG$8 -> 0.25830699 | CJ25: =12158727-CJ28 -> 11239278 | CK25: =(CJ25-CG25)/CG25 -> 0.03614411 | CL25: =CJ25/CJ$8 -> 0.25572582 | CM25: =12591631-CM28 -> 11644598 | CN25: =(CM25-CJ25)/CJ25 -> 0.036062862 | CO25: =CM25/CM$8 -> 0.25281642
B28: b. | C28: California Memorial Stadium Fitness Center | D28: 624032 | E28: n/a | F28: =D28/D$8 -> 0.050998631 | G28: =G29+G30 -> 658926.1 | H28: =(G28-D28)/D28 -> 0.055917164 | I28: =G28/G$8 -> 0.051378253 | J28: =J29+J30 -> 671343.88 | K28: =(J28-G28)/G28 -> 0.018845487 | L28: =J28/J$8 -> 0.049686851 | M28: =M29+M30 -> 684134.2 | N28: =(M28-J28)/J28 -> 0.019051811 | O28: =M28/M$8 -> 0.048210718 | P28: =P29+P30 -> 697308.23 | Q28: =(P28-M28)/M28 -> 0.019256494 | R28: =P28/P$8 -> 0.046895203 | S28: =S29+S30 -> 710877.47 | T28: =(S28-P28)/P28 -> 0.019459468 | U28: =S28/S$8 -> 0.045944577 | V28: =V29+V30 -> 479853.8 | W28: =(V28-S28)/S28 -> -0.32498382 | X28: =V28/V$8 -> 0.02970955 | Y28: =Y29+Y30 -> 494249.41 | Z28: =(Y28-V28)/V28 -> 0.03 | AA28: =Y28/Y$8 -> 0.029234283 | AB28: =AB29+AB30 -> 509076.89 | AC28: =(AB28-Y28)/Y28 -> 0.03 | AD28: =AB28/AB$8 -> 0.028803717 | AE28: =AE29+AE30 -> 524349.2 | AF28: =(AE28-AB28)/AB28 -> 0.03 | AG28: =AE28/AE$8 -> 0.028439279 | AH28: =AH29+AH30 -> 540079.68 | AI28: =(AH28-AE28)/AE28 -> 0.03 | AJ28: =AH28/AH$8 -> 0.027882995 | AK28: =AK29+AK30 -> 556282.07 | AL28: =(AK28-AH28)/AH28 -> 0.03 | AM28: =AK28/AK$8 -> 0.027406433 | AN28: =AN29+AN30 -> 572970.53 | AO28: =(AN28-AK28)/AK28 -> 0.03 | AP28: =AN28/AN$8 -> 0.027086323 | AQ28: =AQ29+AQ30 -> 590159.64 | AR28: =(AQ28-AN28)/AN28 -> 0.03 | AS28: =AQ28/AQ$8 -> 0.026726429 | AT28: =AT29+AT30 -> 607864.43 | AU28: =(AT28-AQ28)/AQ28 -> 0.03 | AV28: =AT28/AT$8 -> 0.026316756 | AW28: =AW29+AW30 -> 626100.37 | AX28: =(AW28-AT28)/AT28 -> 0.03 | AY28: =AW28/AW$8 -> 0.025959341 | AZ28: =AZ29+AZ30 -> 644883.38 | BA28: =(AZ28-AW28)/AW28 -> 0.03 | BB28: =AZ28/AZ$8 -> 0.025566768 | BC28: =BC29+BC30 -> 664229.88 | BD28: =(BC28-AZ28)/AZ28 -> 0.03 | BE28: =BC28/BC$8 -> 0.025155935 | BF28: =BF29+BF30 -> 684156.77 | BG28: =(BF28-BC28)/BC28 -> 0.03 | BH28: =BF28/BF$8 -> 0.024714414 | BI28: =BI29+BI30 -> 704681.48 | BJ28: =(BI28-BF28)/BF28 -> 0.03 | BK28: =BI28/BI$8 -> 0.024339648 | BL28: =BL29+BL30 -> 725821.92 | BM28: =(BL28-BI28)/BI28 -> 0.03 | BN28: =BL28/BL$8 -> 0.023946616 | BO28: =BO29+BO30 -> 747596.58 | BP28: =(BO28-BL28)/BL28 -> 0.03 | BQ28: =BO28/BO$8 -> 0.023488276 | BR28: =BR29+BR30 -> 770024.48 | BS28: =(BR28-BO28)/BO28 -> 0.03 | BT28: =BR28/BR$8 -> 0.023144014 | BU28: =BU29+BU30 -> 793125.21 | BV28: =(BU28-BR28)/BR28 -> 0.03 | BW28: =BU28/BU$8 -> 0.022739985 | BX28: =BX29+BX30 -> 816918.97 | BY28: =(BX28-BU28)/BU28 -> 0.03 | BZ28: =BX28/BX$8 -> 0.022336363 | CA28: =CA29+CA30 -> 841426.54 | CB28: =(CA28-BX28)/BX28 -> 0.03 | CC28: =CA28/CA$8 -> 0.021987158 | CD28: =CD29+CD30 -> 866669.33 | CE28: =(CD28-CA28)/CA28 -> 0.03 | CF28: =CD28/CD$8 -> 0.021640224 | CG28: =CG29+CG30 -> 892669.41 | CH28: =(CG28-CD28)/CD28 -> 0.03 | CI28: =CG28/CG$8 -> 0.021257323 | CJ28: =CJ29+CJ30 -> 919449.5 | CK28: =(CJ28-CG28)/CG28 -> 0.03 | CL28: =CJ28/CJ$8 -> 0.020920115 | CM28: =CM29+CM30 -> 947032.98 | CN28: =(CM28-CJ28)/CJ28 -> 0.03 | CO28: =CM28/CM$8 -> 0.020561078
C29: Operations net deficit | D29: 379032 | G29: =(D29+22838)*1.03 -> 413926.1 | J29: =G29*1.03 -> 426343.88 | M29: =J29*1.03 -> 439134.2 | P29: =M29*1.03 -> 452308.23 | S29: =P29*1.03 -> 465877.47 | V29: =S29*1.03 -> 479853.8 | Y29: =V29*1.03 -> 494249.41 | AB29: =Y29*1.03 -> 509076.89 | AE29: =AB29*1.03 -> 524349.2 | AH29: =AE29*1.03 -> 540079.68 | AK29: =AH29*1.03 -> 556282.07 | AN29: =AK29*1.03 -> 572970.53 | AQ29: =AN29*1.03 -> 590159.64 | AT29: =AQ29*1.03 -> 607864.43 | AW29: =AT29*1.03 -> 626100.37 | AZ29: =AW29*1.03 -> 644883.38 | BC29: =AZ29*1.03 -> 664229.88 | BF29: =BC29*1.03 -> 684156.77 | BI29: =BF29*1.03 -> 704681.48 | BL29: =BI29*1.03 -> 725821.92 | BO29: =BL29*1.03 -> 747596.58 | BR29: =BO29*1.03 -> 770024.48 | BU29: =BR29*1.03 -> 793125.21 | BX29: =BU29*1.03 -> 816918.97 | CA29: =BX29*1.03 -> 841426.54 | CD29: =CA29*1.03 -> 866669.33 | CG29: =CD29*1.03 -> 892669.41 | CJ29: =CG29*1.03 -> 919449.49 | CM29: =CJ29*1.03 -> 947032.98
C30: Debt service | D30: 245000 | G30: 245000 | J30: 245000 | M30: 245000 | P30: 245000 | S30: 245000 | V30: 1e-05 | Y30: 1e-05 | AB30: 1e-05 | AE30: 1e-05 | AH30: 1e-05 | AK30: 1e-05 | AN30: 1e-05 | AQ30: 1e-05 | AT30: 1e-05 | AW30: 1e-05 | AZ30: 1e-05 | BC30: 1e-05 | BF30: 1e-05 | BI30: 1e-05 | BL30: 1e-05 | BO30: 1e-05 | BR30: 1e-05 | BU30: 1e-05 | BX30: 1e-05 | CA30: 1e-05 | CD30: 1e-05 | CG30: 1e-05 | CJ30: 1e-05 | CM30: 1e-05
B32: c. | C32: subtotal - RSF operations | D32: =D25+D28 -> 4862540 | E32: n/a | F32: =D32/D$8 -> 0.39738809 | G32: =G25+G28 -> 5074208 | H32: n/a | I32: =G32/G$8 -> 0.39564975 | J32: =J25+J28 -> 5245949 | K32: n/a | L32: =J32/J$8 -> 0.38825808 | M32: =M25+M28 -> 5423629 | N32: n/a | O32: =M32/M$8 -> 0.3822014 | P32: =P25+P28 -> 5607447 | Q32: n/a | R32: =P32/P$8 -> 0.37711066 | S32: =S25+S28 -> 5801717 | T32: n/a | U32: =S32/S$8 -> 0.37496959 | V32: =V25+V28 -> 5757663 | W32: n/a | X32: =V32/V$8 -> 0.35647853 | Y32: =Y25+Y28 -> 5965506 | Z32: n/a | AA32: =Y32/Y$8 -> 0.35285281 | AB32: =AB25+AB28 -> 6180475 | AC32: n/a | AD32: =AB32/AB$8 -> 0.34969305 | AE32: =AE25+AE28 -> 6402806 | AF32: n/a | AG32: =AE32/AE$8 -> 0.34727083 | AH32: =AH25+AH28 -> 6632744 | AI32: n/a | AJ32: =AH32/AH$8 -> 0.34243238 | AK32: =AK25+AK28 -> 6626538 | AL32: n/a | AM32: =AK32/AK$8 -> 0.32647065 | AN32: =AN25+AN28 -> 6872449 | AO32: n/a | AP32: =AN32/AN$8 -> 0.32488472 | AQ32: =AQ25+AQ28 -> 7126746 | AR32: n/a | AS32: =AQ32/AQ$8 -> 0.32274737 | AT32: =AT25+AT28 -> 7389704 | AU32: n/a | AV32: =AT32/AT$8 -> 0.31992831 | AW32: =AW25+AW28 -> 7661610 | AX32: n/a | AY32: =AW32/AW$8 -> 0.31766528 | AZ32: =AZ25+AZ28 -> 7942759 | BA32: n/a | BB32: =AZ32/AZ$8 -> 0.3148952 | BC32: =BC25+BC28 -> 8233454 | BD32: n/a | BE32: =BC32/BC$8 -> 0.31182011 | BF32: =BF25+BF28 -> 8534010 | BG32: n/a | BH32: =BF32/BF$8 -> 0.30828177 | BI32: =BI25+BI28 -> 8844752 | BJ32: n/a | BK32: =BI32/BI$8 -> 0.3054971 | BL32: =BL25+BL28 -> 9166014 | BM32: n/a | BN32: =BL32/BL$8 -> 0.30240891 | BO32: =BO25+BO28 -> 9498142 | BP32: n/a | BQ32: =BO32/BO$8 -> 0.29841626 | BR32: =BR25+BR28 -> 9841492 | BS32: n/a | BT32: =BR32/BR$8 -> 0.2957979 | BU32: =BU25+BU28 -> 10196432 | BV32: n/a | BW32: =BU32/BU$8 -> 0.29234566 | BX32: =BX25+BX28 -> 10563343 | BY32: n/a | BZ32: =BX32/BX$8 -> 0.28882505 | CA32: =CA25+CA28 -> 10942617 | CB32: n/a | CC32: =CA32/CA$8 -> 0.28593945 | CD32: =CD25+CD28 -> 11334658 | CE32: n/a | CF32: =CD32/CD$8 -> 0.28301975 | CG32: =CG25+CG28 -> 11739884 | CH32: n/a | CI32: =CG32/CG$8 -> 0.27956431 | CJ32: =CJ25+CJ28 -> 12158727 | CK32: n/a | CL32: =CJ32/CJ$8 -> 0.27664593 | CM32: =CM25+CM28 -> 12591631 | CN32: n/a | CO32: =CM32/CM$8 -> 0.2733775
B34: d. | C34: ISF Debt service (expires in Spring 2017) | D34: 922198 | E34: n/a | F34: =D34/D$8 -> 0.075366064 | G34: 685931 | H34: n/a | I34: =G34/G$8 -> 0.053483899 | L34: =J34/J$8 -> 0 | O34: =M34/M$8 -> 0 | R34: =P34/P$8 -> 0 | U34: =S34/S$8 -> 0 | X34: =V34/V$8 -> 0 | AA34: =Y34/Y$8 -> 0 | AD34: =AB34/AB$8 -> 0 | AG34: =AE34/AE$8 -> 0 | AJ34: =AH34/AH$8 -> 0 | AM34: =AK34/AK$8 -> 0 | AP34: =AN34/AN$8 -> 0 | AS34: =AQ34/AQ$8 -> 0 | AV34: =AT34/AT$8 -> 0 | AY34: =AW34/AW$8 -> 0 | BB34: =AZ34/AZ$8 -> 0 | BE34: =BC34/BC$8 -> 0 | BH34: =BF34/BF$8 -> 0 | BK34: =BI34/BI$8 -> 0 | BN34: =BL34/BL$8 -> 0 | BQ34: =BO34/BO$8 -> 0 | BT34: =BR34/BR$8 -> 0 | BW34: =BU34/BU$8 -> 0 | BZ34: =BX34/BX$8 -> 0 | CC34: =CA34/CA$8 -> 0 | CF34: =CD34/CD$8 -> 0 | CI34: =CG34/CG$8 -> 0 | CL34: =CJ34/CJ$8 -> 0 | CO34: =CM34/CM$8 -> 0
B36: e. | C36: RSF equipment & maintenance reserves | D36: 98428.51 | E36: n/a | F36: =D36/D$8 -> 0.0080440094 | G36: 359527.67 | H36: n/a | I36: =G36/G$8 -> 0.028033346 | J36: 518717.67 | K36: n/a | L36: =J36/J$8 -> 0.038390828 | M36: 574037.67 | N36: n/a | O36: =M36/M$8 -> 0.040452251 | P36: 623219.67 | Q36: n/a | R36: =P36/P$8 -> 0.041912618 | S36: 609949.67 | T36: n/a | U36: =S36/S$8 -> 0.039421533 | V36: 887003.67 | W36: n/a | X36: =V36/V$8 -> 0.054917727 | Y36: 903827.33 | Z36: n/a | AA36: =Y36/Y$8 -> 0.053460346 | AB36: 921858.33 | AC36: n/a | AD36: =AB36/AB$8 -> 0.052159009 | AE36: 940860.67 | AF36: n/a | AG36: =AE36/AE$8 -> 0.051029731 | AH36: 995922.67 | AI36: n/a | AJ36: =AH36/AH$8 -> 0.051417056 | AK36: 1295462 | AL36: n/a | AM36: =AK36/AK$8 -> 0.063823722 | AN36: 1282551 | AO36: n/a | AP36: =AN36/AN$8 -> 0.060630676 | AQ36: 1261254 | AR36: n/a | AS36: =AQ36/AQ$8 -> 0.057118131 | AT36: 1291629.3 | AU36: n/a | AV36: =AT36/AT$8 -> 0.055919531 | AW36: 1304723.3 | AX36: n/a | AY36: =AW36/AW$8 -> 0.054096371 | AZ36: 1316907.7 | BA36: n/a | BB36: =AZ36/AZ$8 -> 0.052209553 | BC36: 1371546 | BD36: n/a | BE36: =BC36/BC$8 -> 0.051943646 | BF36: 1432990 | BG36: n/a | BH36: =BF36/BF$8 -> 0.051765195 | BI36: 1467581.3 | BJ36: n/a | BK36: =BI36/BI$8 -> 0.050690154 | BL36: 1491652.7 | BM36: n/a | BN36: =BL36/BL$8 -> 0.049213219 | BO36: 1565191.3 | BP36: n/a | BQ36: =BO36/BO$8 -> 0.049175781 | BR36: 1575508 | BS36: n/a | BT36: =BR36/BR$8 -> 0.047353792 | BU36: 1626234.7 | BV36: n/a | BW36: =BU36/BU$8 -> 0.046626374 | BX36: 1664990.3 | BY36: n/a | BZ36: =BX36/BX$8 -> 0.045524501 | CA36: 1691383 | CB36: n/a | CC36: =CA36/CA$8 -> 0.044197209 | CD36: 1713342 | CE36: n/a | CF36: =CD36/CD$8 -> 0.042781143 | CG36: 1774116 | CH36: n/a | CI36: =CG36/CG$8 -> 0.042247395 | CJ36: 1769273 | CK36: n/a | CL36: =CJ36/CJ$8 -> 0.040256038 | CM36: 1794035.7 | CN36: n/a | CO36: =CM36/CM$8 -> 0.038950394
B38: f. | C38: subtotal - RSF Existing Services | D38: =SUM(D32:D37) -> 5883166.5 | E38: n/a | F38: =D38/D$8 -> 0.48079816 | G38: =SUM(G32:G37) -> 6119666.7 | H38: =(G38-D38)/D38 -> 0.040199467 | I38: =G38/G$8 -> 0.47716699 | J38: =SUM(J32:J37) -> 5764666.7 | K38: =(J38-G38)/G38 -> -0.058009696 | L38: =J38/J$8 -> 0.4266489 | M38: =SUM(M32:M37) -> 5997666.7 | N38: =(M38-J38)/J38 -> 0.040418642 | O38: =M38/M$8 -> 0.42265365 | P38: =SUM(P32:P37) -> 6230666.7 | Q38: =(P38-M38)/M38 -> 0.038848441 | R38: =P38/P$8 -> 0.41902328 | S38: =SUM(S32:S37) -> 6411666.7 | T38: =(S38-P38)/P38 -> 0.029049861 | U38: =S38/S$8 -> 0.41439112 | V38: =SUM(V32:V37) -> 6644666.7 | W38: =(V38-S38)/S38 -> 0.036340005 | X38: =V38/V$8 -> 0.41139626 | Y38: =SUM(Y32:Y37) -> 6869333.3 | Z38: =(Y38-V38)/V38 -> 0.033811578 | AA38: =Y38/Y$8 -> 0.40631315 | AB38: =SUM(AB32:AB37) -> 7102333.3 | AC38: =(AB38-Y38)/Y38 -> 0.033918866 | AD38: =AB38/AB$8 -> 0.40185206 | AE38: =SUM(AE32:AE37) -> 7343666.7 | AF38: =(AE38-AB38)/AB38 -> 0.033979443 | AG38: =AE38/AE$8 -> 0.39830056 | AH38: =SUM(AH32:AH37) -> 7628666.7 | AI38: =(AH38-AE38)/AE38 -> 0.038808951 | AJ38: =AH38/AH$8 -> 0.39384944 | AK38: =SUM(AK32:AK37) -> 7922000 | AL38: =(AK38-AH38)/AH38 -> 0.038451455 | AM38: =AK38/AK$8 -> 0.39029437 | AN38: =SUM(AN32:AN37) -> 8155000 | AO38: =(AN38-AK38)/AK38 -> 0.029411765 | AP38: =AN38/AN$8 -> 0.3855154 | AQ38: =SUM(AQ32:AQ37) -> 8388000 | AR38: =(AQ38-AN38)/AN38 -> 0.028571429 | AS38: =AQ38/AQ$8 -> 0.3798655 | AT38: =SUM(AT32:AT37) -> 8681333.3 | AU38: =(AT38-AQ38)/AQ38 -> 0.034970593 | AV38: =AT38/AT$8 -> 0.37584784 | AW38: =SUM(AW32:AW37) -> 8966333.3 | AX38: =(AW38-AT38)/AT38 -> 0.032829059 | AY38: =AW38/AW$8 -> 0.37176165 | AZ38: =SUM(AZ32:AZ37) -> 9259666.7 | BA38: =(AZ38-AW38)/AW38 -> 0.032714971 | BB38: =AZ38/AZ$8 -> 0.36710475 | BC38: =SUM(BC32:BC37) -> 9605000 | BD38: =(BC38-AZ38)/AZ38 -> 0.037294359 | BE38: =BC38/BC$8 -> 0.36376375 | BF38: =SUM(BF32:BF37) -> 9967000 | BG38: =(BF38-BC38)/BC38 -> 0.037688704 | BH38: =BF38/BF$8 -> 0.36004696 | BI38: =SUM(BI32:BI37) -> 10312333 | BJ38: =(BI38-BF38)/BF38 -> 0.034647671 | BK38: =BI38/BI$8 -> 0.35618725 | BL38: =SUM(BL32:BL37) -> 10657667 | BM38: =(BL38-BI38)/BI38 -> 0.03348741 | BN38: =BL38/BL$8 -> 0.35162213 | BO38: =SUM(BO32:BO37) -> 11063333 | BP38: =(BO38-BL38)/BL38 -> 0.038063366 | BQ38: =BO38/BO$8 -> 0.34759204 | BR38: =SUM(BR32:BR37) -> 11417000 | BS38: =(BR38-BO38)/BO38 -> 0.03196746 | BT38: =BR38/BR$8 -> 0.34315169 | BU38: =SUM(BU32:BU37) -> 11822667 | BV38: =(BU38-BR38)/BR38 -> 0.035531809 | BW38: =BU38/BU$8 -> 0.33897204 | BX38: =SUM(BX32:BX37) -> 12228333 | BY38: =(BX38-BU38)/BU38 -> 0.03431262 | BZ38: =BX38/BX$8 -> 0.33434955 | CA38: =SUM(CA32:CA37) -> 12634000 | CB38: =(CA38-BX38)/BX38 -> 0.033174322 | CC38: =CA38/CA$8 -> 0.33013666 | CD38: =SUM(CD32:CD37) -> 13048000 | CE38: =(CD38-CA38)/CA38 -> 0.032768719 | CF38: =CD38/CD$8 -> 0.32580089 | CG38: =SUM(CG32:CG37) -> 13514000 | CH38: =(CG38-CD38)/CD38 -> 0.035714286 | CI38: =CG38/CG$8 -> 0.32181171 | CJ38: =SUM(CJ32:CJ37) -> 13928000 | CK38: =(CJ38-CG38)/CG38 -> 0.030634897 | CL38: =CJ38/CJ$8 -> 0.31690197 | CM38: =SUM(CM32:CM37) -> 14385667 | CN38: =(CM38-CJ38)/CJ38 -> 0.032859468 | CO38: =CM38/CM$8 -> 0.31232789
B40: 5 | C40: New Services
B42: a. | C42: UHS extended hours & improved mental health counseling along with operational, furnishing, & alteration costs to provide such services | D42: =19/36*D$17 -> 1634879.6 | E42: n/a | F42: =D42/D$8 -> 0.13360953 | G42: =D42*(1+H42) -> 1749321.2 | H42: 0.07 | I42: =G42/G$8 -> 0.13639931 | J42: =G42*(1+K42) -> 1871773.7 | K42: =H42 -> 0.07 | L42: =J42/J$8 -> 0.13853189 | M42: =J42*(1+N42) -> 2002797.8 | N42: =K42 -> 0.07 | O42: =M42/M$8 -> 0.14113652 | P42: =M42*(1+Q42) -> 2142993.7 | Q42: =N42 -> 0.07 | R42: =P42/P$8 -> 0.14412009 | S42: =P42*(1+T42) -> 2293003.3 | T42: =Q42 -> 0.07 | U42: =S42/S$8 -> 0.14819863 | V42: =S42*(1+W42) -> 2453513.5 | W42: =T42 -> 0.07 | X42: =V42/V$8 -> 0.15190623 | Y42: =V42*(1+Z42) -> 2625259.4 | Z42: =W42 -> 0.07 | AA42: =Y42/Y$8 -> 0.15528107 | AB42: =Y42*(1+AC42) -> 2809027.6 | AC42: =Z42 -> 0.07 | AD42: =AB42/AB$8 -> 0.15893559 | AE42: =AB42*(1+AF42) -> 3005659.5 | AF42: =AC42 -> 0.07 | AG42: =AE42/AE$8 -> 0.16301882 | AH42: =AE42*(1+AI42) -> 3216055.7 | AI42: =AF42 -> 0.07 | AJ42: =AH42/AH$8 -> 0.1660371 | AK42: =AH42*(1+AL42) -> 3441179.6 | AL42: =AI42 -> 0.07 | AM42: =AK42/AK$8 -> 0.16953711 | AN42: =AK42*(1+AO42) -> 3682062.2 | AO42: =AL42 -> 0.07 | AP42: =AN42/AN$8 -> 0.17406397 | AQ42: =AN42*(1+AR42) -> 3939806.5 | AR42: =AO42 -> 0.07 | AS42: =AQ42/AQ$8 -> 0.17842114 | AT42: =AQ42*(1+AU42) -> 4215593 | AU42: =AR42 -> 0.07 | AV42: =AT42/AT$8 -> 0.182509 | AW42: =AT42*(1+AX42) -> 4510684.5 | AX42: =AU42 -> 0.07 | AY42: =AW42/AW$8 -> 0.18702177 | AZ42: =AW42*(1+BA42) -> 4826432.4 | BA42: =AX42 -> 0.07 | BB42: =AZ42/AZ$8 -> 0.19134666 | BC42: =AZ42*(1+BD42) -> 5164282.6 | BD42: =BA42 -> 0.07 | BE42: =BC42/BC$8 -> 0.19558343 | BF42: =BC42*(1+BG42) -> 5525782.4 | BG42: =BD42 -> 0.07 | BH42: =BF42/BF$8 -> 0.19961284 | BI42: =BF42*(1+BJ42) -> 5912587.2 | BJ42: =BG42 -> 0.07 | BK42: =BI42/BI$8 -> 0.20422034 | BL42: =BI42*(1+BM42) -> 6326468.3 | BM42: =BJ42 -> 0.07 | BN42: =BL42/BL$8 -> 0.20872545 | BO42: =BL42*(1+BP42) -> 6769321.1 | BP42: =BM42 -> 0.07 | BQ42: =BO42/BO$8 -> 0.21268112 | BR42: =BO42*(1+BS42) -> 7243173.6 | BS42: =BP42 -> 0.07 | BT42: =BR42/BR$8 -> 0.21770231 | BU42: =BR42*(1+BV42) -> 7750195.7 | BV42: =BS42 -> 0.07 | BW42: =BU42/BU$8 -> 0.22220872 | BX42: =BU42*(1+BY42) -> 8292709.4 | BY42: =BV42 -> 0.07 | BZ42: =BX42/BX$8 -> 0.22674093 | CA42: =BX42*(1+CB42) -> 8873199.1 | CB42: =BY42 -> 0.07 | CC42: =CA42/CA$8 -> 0.23186389 | CD42: =CA42*(1+CE42) -> 9494323 | CE42: =CB42 -> 0.07 | CF42: =CD42/CD$8 -> 0.23706767 | CG42: =CD42*(1+CH42) -> 10158926 | CH42: =CE42 -> 0.07 | CI42: =CG42/CG$8 -> 0.24191662 | CJ42: =CG42*(1+CK42) -> 10870050 | CK42: =CH42 -> 0.07 | CL42: =CJ42/CJ$8 -> 0.24732484 | CM42: =CJ42*(1+CN42) -> 11630954 | CN42: =CK42 -> 0.07 | CO42: =CM42/CM$8 -> 0.2525202
B46: b. | C46: New wellness services including operational, furnishings, & alteration costs to provide such services | D46: =11/36*D$17 -> 946509.26 | E46: n/a | F46: =D46/D$8 -> 0.077352887 | G46: =D46*(1+H46) -> 974904.54 | H46: 0.03 | I46: =G46/G$8 -> 0.076015948 | J46: =G46*(1+K46) -> 1004151.7 | K46: =H46 -> 0.03 | L46: =J46/J$8 -> 0.074318297 | M46: =J46*(1+N46) -> 1034276.2 | N46: =K46 -> 0.03 | O46: =M46/M$8 -> 0.072885115 | P46: =M46*(1+Q46) -> 1065304.5 | Q46: =N46 -> 0.03 | R46: =P46/P$8 -> 0.0716436 | S46: =P46*(1+T46) -> 1097263.6 | T46: =Q46 -> 0.03 | U46: =S46/S$8 -> 0.070917023 | V46: =S46*(1+W46) -> 1130181.6 | W46: =T46 -> 0.03 | X46: =V46/V$8 -> 0.069973783 | Y46: =V46*(1+Z46) -> 1164087 | Z46: =W46 -> 0.03 | AA46: =Y46/Y$8 -> 0.068854405 | AB46: =Y46*(1+AC46) -> 1199009.6 | AC46: =Z46 -> 0.03 | AD46: =AB46/AB$8 -> 0.067840308 | AE46: =AB46*(1+AF46) -> 1234979.9 | AF46: =AC46 -> 0.03 | AG46: =AE46/AE$8 -> 0.066981961 | AH46: =AE46*(1+AI46) -> 1272029.3 | AI46: =AF46 -> 0.03 | AJ46: =AH46/AH$8 -> 0.065671767 | AK46: =AH46*(1+AL46) -> 1310190.2 | AL46: =AI46 -> 0.03 | AM46: =AK46/AK$8 -> 0.064549337 | AN46: =AK46*(1+AO46) -> 1349495.9 | AO46: =AL46 -> 0.03 | AP46: =AN46/AN$8 -> 0.063795395 | AQ46: =AN46*(1+AR46) -> 1389980.8 | AR46: =AO46 -> 0.03 | AS46: =AQ46/AQ$8 -> 0.062947751 | AT46: =AQ46*(1+AU46) -> 1431680.2 | AU46: =AR46 -> 0.03 | AV46: =AT46/AT$8 -> 0.061982863 | AW46: =AT46*(1+AX46) -> 1474630.6 | AX46: =AU46 -> 0.03 | AY46: =AW46/AW$8 -> 0.061141057 | AZ46: =AW46*(1+BA46) -> 1518869.5 | BA46: =AX46 -> 0.03 | BB46: =AZ46/AZ$8 -> 0.060216445 | BC46: =AZ46*(1+BD46) -> 1564435.6 | BD46: =BA46 -> 0.03 | BE46: =BC46/BC$8 -> 0.059248825 | BF46: =BC46*(1+BG46) -> 1611368.7 | BG46: =BD46 -> 0.03 | BH46: =BF46/BF$8 -> 0.058208928 | BI46: =BF46*(1+BJ46) -> 1659709.7 | BJ46: =BG46 -> 0.03 | BK46: =BI46/BI$8 -> 0.057326254 | BL46: =BI46*(1+BM46) -> 1709501 | BM46: =BJ46 -> 0.03 | BN46: =BL46/BL$8 -> 0.056400561 | BO46: =BL46*(1+BP46) -> 1760786 | BP46: =BM46 -> 0.03 | BQ46: =BO46/BO$8 -> 0.05532105 | BR46: =BO46*(1+BS46) -> 1813609.6 | BS46: =BP46 -> 0.03 | BT46: =BR46/BR$8 -> 0.054510223 | BU46: =BR46*(1+BV46) -> 1868017.9 | BV46: =BS46 -> 0.03 | BW46: =BU46/BU$8 -> 0.05355863 | BX46: =BU46*(1+BY46) -> 1924058.4 | BY46: =BV46 -> 0.03 | BZ46: =BX46/BX$8 -> 0.052607993 | CA46: =BX46*(1+CB46) -> 1981780.2 | CB46: =BY46 -> 0.03 | CC46: =CA46/CA$8 -> 0.051785523 | CD46: =CA46*(1+CE46) -> 2041233.6 | CE46: =CB46 -> 0.03 | CF46: =CD46/CD$8 -> 0.050968404 | CG46: =CD46*(1+CH46) -> 2102470.6 | CH46: =CE46 -> 0.03 | CI46: =CG46/CG$8 -> 0.050066572 | CJ46: =CG46*(1+CK46) -> 2165544.7 | CK46: =CH46 -> 0.03 | CL46: =CJ46/CJ$8 -> 0.049272357 | CM46: =CJ46*(1+CN46) -> 2230511.1 | CN46: =CK46 -> 0.03 | CO46: =CM46/CM$8 -> 0.048426732
B50: c. | C50: Diversity student wellness programs and associated costs | D50: =4/36*D$17 -> 344185.19 | E50: n/a | F50: =D50/D$8 -> 0.028128322 | G50: =D50*(1+H50) -> 368278.15 | H50: 0.07 | I50: =G50/G$8 -> 0.028715645 | J50: =G50*(1+K50) -> 394057.62 | K50: =H50 -> 0.07 | L50: =J50/J$8 -> 0.029164609 | M50: =J50*(1+N50) -> 421641.65 | N50: =K50 -> 0.07 | O50: =M50/M$8 -> 0.029712952 | P50: =M50*(1+Q50) -> 451156.57 | Q50: =N50 -> 0.07 | R50: =P50/P$8 -> 0.030341072 | S50: =P50*(1+T50) -> 482737.53 | T50: =Q50 -> 0.07 | U50: =S50/S$8 -> 0.031199711 | V50: =S50*(1+W50) -> 516529.15 | W50: =T50 -> 0.07 | X50: =V50/V$8 -> 0.031980259 | Y50: =V50*(1+Z50) -> 552686.19 | Z50: =W50 -> 0.07 | AA50: =Y50/Y$8 -> 0.032690752 | AB50: =Y50*(1+AC50) -> 591374.23 | AC50: =Z50 -> 0.07 | AD50: =AB50/AB$8 -> 0.033460124 | AE50: =AB50*(1+AF50) -> 632770.42 | AF50: =AC50 -> 0.07 | AG50: =AE50/AE$8 -> 0.034319752 | AH50: =AE50*(1+AI50) -> 677064.35 | AI50: =AF50 -> 0.07 | AJ50: =AH50/AH$8 -> 0.03495518 | AK50: =AH50*(1+AL50) -> 724458.86 | AL50: =AI50 -> 0.07 | AM50: =AK50/AK$8 -> 0.035692024 | AN50: =AK50*(1+AO50) -> 775170.98 | AO50: =AL50 -> 0.07 | AP50: =AN50/AN$8 -> 0.036645046 | AQ50: =AN50*(1+AR50) -> 829432.95 | AR50: =AO50 -> 0.07 | AS50: =AQ50/AQ$8 -> 0.037562346 | AT50: =AQ50*(1+AU50) -> 887493.25 | AU50: =AR50 -> 0.07 | AV50: =AT50/AT$8 -> 0.038422948 | AW50: =AT50*(1+AX50) -> 949617.78 | AX50: =AU50 -> 0.07 | AY50: =AW50/AW$8 -> 0.039373003 | AZ50: =AW50*(1+BA50) -> 1016091 | BA50: =AX50 -> 0.07 | BB50: =AZ50/AZ$8 -> 0.040283507 | BC50: =AZ50*(1+BD50) -> 1087217.4 | BD50: =BA50 -> 0.07 | BE50: =BC50/BC$8 -> 0.041175459 | BF50: =BC50*(1+BG50) -> 1163322.6 | BG50: =BD50 -> 0.07 | BH50: =BF50/BF$8 -> 0.042023756 | BI50: =BF50*(1+BJ50) -> 1244755.2 | BJ50: =BG50 -> 0.07 | BK50: =BI50/BI$8 -> 0.042993755 | BL50: =BI50*(1+BM50) -> 1331888.1 | BM50: =BJ50 -> 0.07 | BN50: =BL50/BL$8 -> 0.043942199 | BO50: =BL50*(1+BP50) -> 1425120.2 | BP50: =BM50 -> 0.07 | BQ50: =BO50/BO$8 -> 0.044774973 | BR50: =BO50*(1+BS50) -> 1524878.6 | BS50: =BP50 -> 0.07 | BT50: =BR50/BR$8 -> 0.045832065 | BU50: =BR50*(1+BV50) -> 1631620.1 | BV50: =BS50 -> 0.07 | BW50: =BU50/BU$8 -> 0.046780783 | BX50: =BU50*(1+BY50) -> 1745833.6 | BY50: =BV50 -> 0.07 | BZ50: =BX50/BX$8 -> 0.047734933 | CA50: =BX50*(1+CB50) -> 1868041.9 | CB50: =BY50 -> 0.07 | CC50: =CA50/CA$8 -> 0.04881345 | CD50: =CA50*(1+CE50) -> 1998804.8 | CE50: =CB50 -> 0.07 | CF50: =CD50/CD$8 -> 0.049908983 | CG50: =CD50*(1+CH50) -> 2138721.2 | CH50: =CE50 -> 0.07 | CI50: =CG50/CG$8 -> 0.050929815 | CJ50: =CG50*(1+CK50) -> 2288431.7 | CK50: =CH50 -> 0.07 | CL50: =CJ50/CJ$8 -> 0.052068387 | CM50: =CJ50*(1+CN50) -> 2448621.9 | CN50: =CK50 -> 0.07 | CO50: =CM50/CM$8 -> 0.053162146
B53: d. | C53: Wellness sustainability plan to lower student costs over time | D53: =1/36*D$17 -> 86046.296 | E53: n/a | F53: =D53/D$8 -> 0.0070320806 | G53: =D53*(1+H53) -> 88627.685 | H53: 0.03 | I53: =G53/G$8 -> 0.0069105408 | J53: =G53*(1+K53) -> 91286.516 | K53: =H53 -> 0.03 | L53: =J53/J$8 -> 0.0067562088 | M53: =J53*(1+N53) -> 94025.111 | N53: =K53 -> 0.03 | O53: =M53/M$8 -> 0.0066259195 | P53: =M53*(1+Q53) -> 96845.865 | Q53: =N53 -> 0.03 | R53: =P53/P$8 -> 0.0065130545 | S53: =P53*(1+T53) -> 99751.24 | T53: =Q53 -> 0.03 | U53: =S53/S$8 -> 0.0064470021 | V53: =S53*(1+W53) -> 102743.78 | W53: =T53 -> 0.03 | X53: =V53/V$8 -> 0.006361253 | Y53: =V53*(1+Z53) -> 105826.09 | Z53: =W53 -> 0.03 | AA53: =Y53/Y$8 -> 0.0062594914 | AB53: =Y53*(1+AC53) -> 109000.87 | AC53: =Z53 -> 0.03 | AD53: =AB53/AB$8 -> 0.0061673008 | AE53: =AB53*(1+AF53) -> 112270.9 | AF53: =AC53 -> 0.03 | AG53: =AE53/AE$8 -> 0.0060892692 | AH53: =AE53*(1+AI53) -> 115639.03 | AI53: =AF53 -> 0.03 | AJ53: =AH53/AH$8 -> 0.0059701607 | AK53: =AH53*(1+AL53) -> 119108.2 | AL53: =AI53 -> 0.03 | AM53: =AK53/AK$8 -> 0.0058681216 | AN53: =AK53*(1+AO53) -> 122681.44 | AO53: =AL53 -> 0.03 | AP53: =AN53/AN$8 -> 0.0057995813 | AQ53: =AN53*(1+AR53) -> 126361.89 | AR53: =AO53 -> 0.03 | AS53: =AQ53/AQ$8 -> 0.0057225228 | AT53: =AQ53*(1+AU53) -> 130152.74 | AU53: =AR53 -> 0.03 | AV53: =AT53/AT$8 -> 0.0056348058 | AW53: =AT53*(1+AX53) -> 134057.33 | AX53: =AU53 -> 0.03 | AY53: =AW53/AW$8 -> 0.0055582779 | AZ53: =AW53*(1+BA53) -> 138079.05 | BA53: =AX53 -> 0.03 | BB53: =AZ53/AZ$8 -> 0.0054742223 | BC53: =AZ53*(1+BD53) -> 142221.42 | BD53: =BA53 -> 0.03 | BE53: =BC53/BC$8 -> 0.0053862568 | BF53: =BC53*(1+BG53) -> 146488.06 | BG53: =BD53 -> 0.03 | BH53: =BF53/BF$8 -> 0.0052917207 | BI53: =BF53*(1+BJ53) -> 150882.7 | BJ53: =BG53 -> 0.03 | BK53: =BI53/BI$8 -> 0.0052114777 | BL53: =BI53*(1+BM53) -> 155409.18 | BM53: =BJ53 -> 0.03 | BN53: =BL53/BL$8 -> 0.0051273237 | BO53: =BL53*(1+BP53) -> 160071.46 | BP53: =BM53 -> 0.03 | BQ53: =BO53/BO$8 -> 0.0050291864 | BR53: =BO53*(1+BS53) -> 164873.6 | BS53: =BP53 -> 0.03 | BT53: =BR53/BR$8 -> 0.0049554748 | BU53: =BR53*(1+BV53) -> 169819.81 | BV53: =BS53 -> 0.03 | BW53: =BU53/BU$8 -> 0.0048689664 | BX53: =BU53*(1+BY53) -> 174914.4 | BY53: =BV53 -> 0.03 | BZ53: =BX53/BX$8 -> 0.0047825448 | CA53: =BX53*(1+CB53) -> 180161.84 | CB53: =BY53 -> 0.03 | CC53: =CA53/CA$8 -> 0.0047077749 | CD53: =CA53*(1+CE53) -> 185566.69 | CE53: =CB53 -> 0.03 | CF53: =CD53/CD$8 -> 0.0046334913 | CG53: =CD53*(1+CH53) -> 191133.69 | CH53: =CE53 -> 0.03 | CI53: =CG53/CG$8 -> 0.0045515066 | CJ53: =CG53*(1+CK53) -> 196867.7 | CK53: =CH53 -> 0.03 | CL53: =CJ53/CJ$8 -> 0.0044793052 | CM53: =CJ53*(1+CN53) -> 202773.73 | CN53: =CK53 -> 0.03 | CO53: =CM53/CM$8 -> 0.0044024302
B56: e. | C56: Sexual assault prevention and support | D56: =1/36*D$17 -> 86046.296 | F56: =D56/D$8 -> 0.0070320806 | G56: =D56*(1+H56) -> 92069.537 | H56: 0.07 | I56: =G56/G$8 -> 0.0071789113 | J56: =G56*(1+K56) -> 98514.405 | K56: =H56 -> 0.07 | L56: =J56/J$8 -> 0.0072911523 | M56: =J56*(1+N56) -> 105410.41 | N56: =K56 -> 0.07 | O56: =M56/M$8 -> 0.0074282381 | P56: =M56*(1+Q56) -> 112789.14 | Q56: =N56 -> 0.07 | R56: =P56/P$8 -> 0.007585268 | S56: =P56*(1+T56) -> 120684.38 | T56: =Q56 -> 0.07 | U56: =S56/S$8 -> 0.0077999277 | V56: =S56*(1+W56) -> 129132.29 | W56: =T56 -> 0.07 | X56: =V56/V$8 -> 0.0079950648 | Y56: =V56*(1+Z56) -> 138171.55 | Z56: =W56 -> 0.07 | AA56: =Y56/Y$8 -> 0.0081726879 | AB56: =Y56*(1+AC56) -> 147843.56 | AC56: =Z56 -> 0.07 | AD56: =AB56/AB$8 -> 0.008365031 | AE56: =AB56*(1+AF56) -> 158192.61 | AF56: =AC56 -> 0.07 | AG56: =AE56/AE$8 -> 0.008579938 | AH56: =AE56*(1+AI56) -> 169266.09 | AI56: =AF56 -> 0.07 | AJ56: =AH56/AH$8 -> 0.0087387949 | AK56: =AH56*(1+AL56) -> 181114.71 | AL56: =AI56 -> 0.07 | AM56: =AK56/AK$8 -> 0.008923006 | AN56: =AK56*(1+AO56) -> 193792.74 | AO56: =AL56 -> 0.07 | AP56: =AN56/AN$8 -> 0.0091612615 | AQ56: =AN56*(1+AR56) -> 207358.24 | AR56: =AO56 -> 0.07 | AS56: =AQ56/AQ$8 -> 0.0093905865 | AT56: =AQ56*(1+AU56) -> 221873.31 | AU56: =AR56 -> 0.07 | AV56: =AT56/AT$8 -> 0.009605737 | AW56: =AT56*(1+AX56) -> 237404.45 | AX56: =AU56 -> 0.07 | AY56: =AW56/AW$8 -> 0.0098432508 | AZ56: =AW56*(1+BA56) -> 254022.76 | BA56: =AX56 -> 0.07 | BB56: =AZ56/AZ$8 -> 0.010070877 | BC56: =AZ56*(1+BD56) -> 271804.35 | BD56: =BA56 -> 0.07 | BE56: =BC56/BC$8 -> 0.010293865 | BF56: =BC56*(1+BG56) -> 290830.65 | BG56: =BD56 -> 0.07 | BH56: =BF56/BF$8 -> 0.010505939 | BI56: =BF56*(1+BJ56) -> 311188.8 | BJ56: =BG56 -> 0.07 | BK56: =BI56/BI$8 -> 0.010748439 | BL56: =BI56*(1+BM56) -> 332972.02 | BM56: =BJ56 -> 0.07 | BN56: =BL56/BL$8 -> 0.01098555 | BO56: =BL56*(1+BP56) -> 356280.06 | BP56: =BM56 -> 0.07 | BQ56: =BO56/BO$8 -> 0.011193743 | BR56: =BO56*(1+BS56) -> 381219.66 | BS56: =BP56 -> 0.07 | BT56: =BR56/BR$8 -> 0.011458016 | BU56: =BR56*(1+BV56) -> 407905.04 | BV56: =BS56 -> 0.07 | BW56: =BU56/BU$8 -> 0.011695196 | BX56: =BU56*(1+BY56) -> 436458.39 | BY56: =BV56 -> 0.07 | BZ56: =BX56/BX$8 -> 0.011933733 | CA56: =BX56*(1+CB56) -> 467010.48 | CB56: =BY56 -> 0.07 | CC56: =CA56/CA$8 -> 0.012203362 | CD56: =CA56*(1+CE56) -> 499701.21 | CE56: =CB56 -> 0.07 | CF56: =CD56/CD$8 -> 0.012477246 | CG56: =CD56*(1+CH56) -> 534680.3 | CH56: =CE56 -> 0.07 | CI56: =CG56/CG$8 -> 0.012732454 | CJ56: =CG56*(1+CK56) -> 572107.92 | CK56: =CH56 -> 0.07 | CL56: =CJ56/CJ$8 -> 0.013017097 | CM56: =CJ56*(1+CN56) -> 612155.47 | CN56: =CK56 -> 0.07 | CO56: =CM56/CM$8 -> 0.013290537
B58: f. | C58: Campus-wide wellness incentive program | D58: 0 | E58: n/a | F58: =D58/D$8 -> 0 | G58: =D58*(1+H58) -> 0 | H58: 0.03 | I58: =G58/G$8 -> 0 | J58: =G58*(1+K58) -> 0 | K58: =H58 -> 0.03 | L58: =J58/J$8 -> 0 | M58: =J58*(1+N58) -> 0 | N58: =K58 -> 0.03 | O58: =M58/M$8 -> 0 | P58: =M58*(1+Q58) -> 0 | Q58: =N58 -> 0.03 | R58: =P58/P$8 -> 0 | S58: =P58*(1+T58) -> 0 | T58: =Q58 -> 0.03 | U58: =S58/S$8 -> 0 | V58: =S58*(1+W58) -> 0 | W58: =T58 -> 0.03 | X58: =V58/V$8 -> 0 | Y58: =V58*(1+Z58) -> 0 | Z58: =W58 -> 0.03 | AA58: =Y58/Y$8 -> 0 | AB58: =Y58*(1+AC58) -> 0 | AC58: =Z58 -> 0.03 | AD58: =AB58/AB$8 -> 0 | AE58: =AB58*(1+AF58) -> 0 | AF58: =AC58 -> 0.03 | AG58: =AE58/AE$8 -> 0 | AH58: =AE58*(1+AI58) -> 0 | AI58: =AF58 -> 0.03 | AJ58: =AH58/AH$8 -> 0 | AK58: =AH58*(1+AL58) -> 0 | AL58: =AI58 -> 0.03 | AM58: =AK58/AK$8 -> 0 | AN58: =AK58*(1+AO58) -> 0 | AO58: =AL58 -> 0.03 | AP58: =AN58/AN$8 -> 0 | AQ58: =AN58*(1+AR58) -> 0 | AR58: =AO58 -> 0.03 | AS58: =AQ58/AQ$8 -> 0 | AT58: =AQ58*(1+AU58) -> 0 | AU58: =AR58 -> 0.03 | AV58: =AT58/AT$8 -> 0 | AW58: =AT58*(1+AX58) -> 0 | AX58: =AU58 -> 0.03 | AY58: =AW58/AW$8 -> 0 | AZ58: =AW58*(1+BA58) -> 0 | BA58: =AX58 -> 0.03 | BB58: =AZ58/AZ$8 -> 0 | BC58: =AZ58*(1+BD58) -> 0 | BD58: =BA58 -> 0.03 | BE58: =BC58/BC$8 -> 0 | BF58: =BC58*(1+BG58) -> 0 | BG58: =BD58 -> 0.03 | BH58: =BF58/BF$8 -> 0 | BI58: =BF58*(1+BJ58) -> 0 | BJ58: =BG58 -> 0.03 | BK58: =BI58/BI$8 -> 0 | BL58: =BI58*(1+BM58) -> 0 | BM58: =BJ58 -> 0.03 | BN58: =BL58/BL$8 -> 0 | BO58: =BL58*(1+BP58) -> 0 | BP58: =BM58 -> 0.03 | BQ58: =BO58/BO$8 -> 0 | BR58: =BO58*(1+BS58) -> 0 | BS58: =BP58 -> 0.03 | BT58: =BR58/BR$8 -> 0 | BU58: =BR58*(1+BV58) -> 0 | BV58: =BS58 -> 0.03 | BW58: =BU58/BU$8 -> 0 | BX58: =BU58*(1+BY58) -> 0 | BY58: =BV58 -> 0.03 | BZ58: =BX58/BX$8 -> 0 | CA58: =BX58*(1+CB58) -> 0 | CB58: =BY58 -> 0.03 | CC58: =CA58/CA$8 -> 0 | CD58: =CA58*(1+CE58) -> 0 | CE58: =CB58 -> 0.03 | CF58: =CD58/CD$8 -> 0 | CG58: =CD58*(1+CH58) -> 0 | CH58: =CE58 -> 0.03 | CI58: =CG58/CG$8 -> 0 | CJ58: =CG58*(1+CK58) -> 0 | CK58: =CH58 -> 0.03 | CL58: =CJ58/CJ$8 -> 0 | CM58: =CJ58*(1+CN58) -> 0 | CN58: =CK58 -> 0.03 | CO58: =CM58/CM$8 -> 0
B60: g. | C60: subtotal - New Services | D60: =SUM(D42:D59) -> 3097666.7 | E60: n/a | F60: =D60/D$8 -> 0.2531549 | G60: =SUM(G42:G59) -> 3273201.1 | H60: =(G60-D60)/D60 -> 0.056666667 | I60: =G60/G$8 -> 0.25522036 | J60: =SUM(J42:J58) -> 3459783.9 | K60: =(J60-G60)/G60 -> 0.057003155 | L60: =J60/J$8 -> 0.25606216 | M60: =SUM(M42:M58) -> 3658151.2 | N60: =(M60-J60)/J60 -> 0.057335184 | O60: =M60/M$8 -> 0.25778875 | P60: =SUM(P42:P58) -> 3869089.8 | Q60: =(P60-M60)/M60 -> 0.057662606 | R60: =P60/P$8 -> 0.26020309 | S60: =SUM(S42:S58) -> 4093440 | T60: =(S60-P60)/P60 -> 0.057985284 | U60: =S60/S$8 -> 0.26456229 | V60: =SUM(V42:V58) -> 4332100.3 | W60: =(V60-S60)/S60 -> 0.058303091 | X60: =V60/V$8 -> 0.26821659 | Y60: =SUM(Y42:Y58) -> 4586030.3 | Z60: =(Y60-V60)/V60 -> 0.058615911 | AA60: =Y60/Y$8 -> 0.27125841 | AB60: =SUM(AB42:AB58) -> 4856255.9 | AC60: =(AB60-Y60)/Y60 -> 0.05892364 | AD60: =AB60/AB$8 -> 0.27476835 | AE60: =SUM(AE42:AE58) -> 5143873.3 | AF60: =(AE60-AB60)/AB60 -> 0.059226181 | AG60: =AE60/AE$8 -> 0.27898974 | AH60: =SUM(AH42:AH58) -> 5450054.4 | AI60: =(AH60-AE60)/AE60 -> 0.059523453 | AJ60: =AH60/AH$8 -> 0.28137301 | AK60: =SUM(AK42:AK58) -> 5776051.5 | AL60: =(AK60-AH60)/AH60 -> 0.05981538 | AM60: =AK60/AK$8 -> 0.2845696 | AN60: =SUM(AN42:AN58) -> 6123203.2 | AO60: =(AN60-AK60)/AK60 -> 0.0601019 | AP60: =AN60/AN$8 -> 0.28946525 | AQ60: =SUM(AQ42:AQ58) -> 6492940.3 | AR60: =(AQ60-AN60)/AN60 -> 0.06038296 | AS60: =AQ60/AQ$8 -> 0.29404435 | AT60: =SUM(AT42:AT58) -> 6886792.4 | AU60: =(AT60-AQ60)/AQ60 -> 0.060658515 | AV60: =AT60/AT$8 -> 0.29815536 | AW60: =SUM(AW42:AW58) -> 7306394.6 | AX60: =(AW60-AT60)/AT60 -> 0.060928532 | AY60: =AW60/AW$8 -> 0.30293736 | AZ60: =SUM(AZ42:AZ58) -> 7753494.7 | BA60: =(AZ60-AW60)/AW60 -> 0.061192986 | BB60: =AZ60/AZ$8 -> 0.30739171 | BC60: =SUM(BC42:BC58) -> 8229961.4 | BD60: =(BC60-AZ60)/AZ60 -> 0.061451862 | BE60: =BC60/BC$8 -> 0.31168783 | BF60: =SUM(BF42:BF58) -> 8737792.4 | BG60: =(BF60-BC60)/BC60 -> 0.061705152 | BH60: =BF60/BF$8 -> 0.31564318 | BI60: =SUM(BI42:BI58) -> 9279123.6 | BJ60: =(BI60-BF60)/BF60 -> 0.061952857 | BK60: =BI60/BI$8 -> 0.32050026 | BL60: =SUM(BL42:BL58) -> 9856238.6 | BM60: =(BL60-BI60)/BI60 -> 0.062194985 | BN60: =BL60/BL$8 -> 0.32518108 | BO60: =SUM(BO42:BO58) -> 10471579 | BP60: =(BO60-BL60)/BL60 -> 0.062431554 | BQ60: =BO60/BO$8 -> 0.32900007 | BR60: =SUM(BR42:BR58) -> 11127755 | BS60: =(BR60-BO60)/BO60 -> 0.062662587 | BT60: =BR60/BR$8 -> 0.33445809 | BU60: =SUM(BU42:BU58) -> 11827559 | BV60: =(BU60-BR60)/BR60 -> 0.062888114 | BW60: =BU60/BU$8 -> 0.33911229 | BX60: =SUM(BX42:BX58) -> 12573974 | BY60: =(BX60-BU60)/BU60 -> 0.063108171 | BZ60: =BX60/BX$8 -> 0.34380013 | CA60: =SUM(CA42:CA58) -> 13370193 | CB60: =(CA60-BX60)/BX60 -> 0.063322802 | CC60: =CA60/CA$8 -> 0.349374 | CD60: =SUM(CD42:CD58) -> 14219629 | CE60: =(CD60-CA60)/CA60 -> 0.063532055 | CF60: =CD60/CD$8 -> 0.35505579 | CG60: =SUM(CG42:CG58) -> 15125931 | CH60: =(CG60-CD60)/CD60 -> 0.063735982 | CI60: =CG60/CG$8 -> 0.36019697 | CJ60: =SUM(CJ42:CJ58) -> 16093002 | CK60: =(CJ60-CG60)/CG60 -> 0.063934643 | CL60: =CJ60/CJ$8 -> 0.36616199 | CM60: =SUM(CM42:CM58) -> 17125016 | CN60: =(CM60-CJ60)/CJ60 -> 0.0641281 | CO60: =CM60/CM$8 -> 0.37180204
B62: =B40+1 -> 6 | C62: TOTAL EXPENSES / OUTFLOWS | D62: =D38+D60 -> 8980833.2 | E62: - | F62: =D62/D$8 -> 0.73395306 | G62: =G38+G60 -> 9392867.8 | H62: =(G62-D62)/D62 -> 0.045879329 | I62: =G62/G$8 -> 0.73238735 | J62: =J38+J60 -> 9224450.6 | K62: =(J62-G62)/G62 -> -0.017930329 | L62: =J62/J$8 -> 0.68271107 | M62: =M38+M60 -> 9655817.9 | N62: =(M62-J62)/J62 -> 0.046763473 | O62: =M62/M$8 -> 0.6804424 | P62: =P38+P60 -> 10099756 | Q62: =(P62-M62)/M62 -> 0.045976274 | R62: =P62/P$8 -> 0.67922637 | S62: =S38+S60 -> 10505107 | T62: =(S62-P62)/P62 -> 0.040134658 | U62: =S62/S$8 -> 0.67895342 | V62: =V38+V60 -> 10976767 | W62: =(V62-S62)/S62 -> 0.044898183 | X62: =V62/V$8 -> 0.67961285 | Y62: =Y38+Y60 -> 11455364 | Z62: =(Y62-V62)/V62 -> 0.043600878 | AA62: =Y62/Y$8 -> 0.67757156 | AB62: =AB38+AB60 -> 11958589 | AC62: =(AB62-Y62)/Y62 -> 0.043929256 | AD62: =AB62/AB$8 -> 0.67662041 | AE62: =AE38+AE60 -> 12487540 | AF62: =(AE62-AB62)/AB62 -> 0.044231875 | AG62: =AE62/AE$8 -> 0.67729031 | AH62: =AH38+AH60 -> 13078721 | AI62: =(AH62-AE62)/AE62 -> 0.047341678 | AJ62: =AH62/AH$8 -> 0.67522244 | AK62: =AK38+AK60 -> 13698052 | AL62: =(AK62-AH62)/AH62 -> 0.04735405 | AM62: =AK62/AK$8 -> 0.67486397 | AN62: =AN38+AN60 -> 14278203 | AO62: =(AN62-AK62)/AK62 -> 0.042352861 | AP62: =AN62/AN$8 -> 0.67498065 | AQ62: =AQ38+AQ60 -> 14880940 | AR62: =(AQ62-AN62)/AN62 -> 0.042213794 | AS62: =AQ62/AQ$8 -> 0.67390985 | AT62: =AT38+AT60 -> 15568126 | AU62: =(AT62-AQ62)/AQ62 -> 0.0461789 | AV62: =AT62/AT$8 -> 0.67400319 | AW62: =AW38+AW60 -> 16272728 | AX62: =(AW62-AT62)/AT62 -> 0.045259279 | AY62: =AW62/AW$8 -> 0.674699 | AZ62: =AZ38+AZ60 -> 17013161 | BA62: =(AZ62-AW62)/AW62 -> 0.045501494 | BB62: =AZ62/AZ$8 -> 0.67449646 | BC62: =BC38+BC60 -> 17834961 | BD62: =(BC62-AZ62)/AZ62 -> 0.048303781 | BE62: =BC62/BC$8 -> 0.67545159 | BF62: =BF38+BF60 -> 18704792 | BG62: =(BF62-BC62)/BC62 -> 0.048771119 | BH62: =BF62/BF$8 -> 0.67569014 | BI62: =BI38+BI60 -> 19591457 | BJ62: =(BI62-BF62)/BF62 -> 0.047403067 | BK62: =BI62/BI$8 -> 0.67668752 | BL62: =BL38+BL60 -> 20513905 | BM62: =(BL62-BI62)/BI62 -> 0.047084211 | BN62: =BL62/BL$8 -> 0.67680321 | BO62: =BO38+BO60 -> 21534912 | BP62: =(BO62-BL62)/BL62 -> 0.049771457 | BQ62: =BO62/BO$8 -> 0.67659212 | BR62: =BR38+BR60 -> 22544755 | BS62: =(BR62-BO62)/BO62 -> 0.04689329 | BT62: =BR62/BR$8 -> 0.67760978 | BU62: =BU38+BU60 -> 23650225 | BV62: =(BU62-BR62)/BR62 -> 0.049034473 | BW62: =BU62/BU$8 -> 0.67808433 | BX62: =BX38+BX60 -> 24802308 | BY62: =(BX62-BU62)/BU62 -> 0.048713374 | BZ62: =BX62/BX$8 -> 0.67814969 | CA62: =CA38+CA60 -> 26004193 | CB62: =(CA62-BX62)/BX62 -> 0.048458634 | CC62: =CA62/CA$8 -> 0.67951066 | CD62: =CD38+CD60 -> 27267629 | CE62: =(CD62-CA62)/CA62 -> 0.048585851 | CF62: =CD62/CD$8 -> 0.68085668 | CG62: =CG38+CG60 -> 28639931 | CH62: =(CG62-CD62)/CD62 -> 0.050327149 | CI62: =CG62/CG$8 -> 0.68200868 | CJ62: =CJ38+CJ60 -> 30021002 | CK62: =(CJ62-CG62)/CG62 -> 0.048221869 | CL62: =CJ62/CJ$8 -> 0.68306396 | CM62: =CM38+CM60 -> 31510683 | CN62: =(CM62-CJ62)/CJ62 -> 0.049621272 | CO62: =CM62/CM$8 -> 0.68412994
B64: 7 | C64: RSF Existing Services – SURPLUS (DEFICIT): lines 2f - 4f | D64: =D15-D38 -> 0.15666667 | G64: =G15-G38 -> 0 | J64: =J15-J38 -> 0 | M64: =M15-M38 -> 0 | P64: =P15-P38 -> 0 | S64: =S15-S38 -> 0 | V64: =V15-V38 -> 0 | Y64: =Y15-Y38 -> 0 | AB64: =AB15-AB38 -> 0 | AE64: =AE15-AE38 -> 0 | AH64: =AH15-AH38 -> 0 | AK64: =AK15-AK38 -> 0 | AN64: =AN15-AN38 -> 0 | AQ64: =AQ15-AQ38 -> 0 | AT64: =AT15-AT38 -> 0 | AW64: =AW15-AW38 -> 0 | AZ64: =AZ15-AZ38 -> 0 | BC64: =BC15-BC38 -> 0 | BF64: =BF15-BF38 -> 0 | BI64: =BI15-BI38 -> 0 | BL64: =BL15-BL38 -> 0 | BO64: =BO15-BO38 -> 0 | BR64: =BR15-BR38 -> 0 | BU64: =BU15-BU38 -> 0 | BX64: =BX15-BX38 -> 0 | CA64: =CA15-CA38 -> 0 | CD64: =CD15-CD38 -> 0 | CG64: =CG15-CG38 -> 0 | CJ64: =CJ15-CJ38 -> 0 | CM64: =CM15-CM38 -> 0
B65: 8 | C65: New Services – SURPLUS (DEFICIT): line 2d - 5g | D65: =D17-D60 -> 0 | G65: =G17-G60 -> -6867.7778 | J65: =J17-J60 -> -24783.9 | M65: =M17-M60 -> 5848.7546 | P65: =P17-P60 -> 23910.221 | S65: =S17-S60 -> 28559.951 | V65: =V17-V60 -> 18899.743 | Y65: =Y17-Y60 -> 54303.072 | AB65: =AB17-AB60 -> 73410.811 | AE65: =AE17-AE60 -> 62793.32 | AH65: =AH17-AH60 -> 106278.88 | AK65: =AK17-AK60 -> 117615.14 | AN65: =AN17-AN60 -> 120130.13 | AQ65: =AQ17-AQ60 -> 148059.67 | AT65: =AT17-AT60 -> 151874.22 | AW65: =AW17-AW60 -> 142272.06 | AZ65: =AZ17-AZ60 -> 153171.96 | BC65: =BC17-BC60 -> 134705.27 | BF65: =BF17-BF60 -> 132874.25 | BI65: =BI17-BI60 -> 109876.39 | BL65: =BL17-BL60 -> 111428.1 | BO65: =BO17-BO60 -> 122754.47 | BR65: =BR17-BR60 -> 93244.918 | BU65: =BU17-BU60 -> 80441.391 | BX65: =BX17-BX60 -> 81359.13 | CA65: =CA17-CA60 -> 32473.183 | CD65: =CD17-CD60 -> -21629.346 | CG65: =CG17-CG60 -> -72264.722 | CJ65: =CJ17-CJ60 -> -123335.75 | CM65: =CM17-CM60 -> -179016.08 | CP65: =SUM(D65:CO65) -> 1678387.5 | CQ65: total over 30 years
B66: 9 | C66: TOTAL SURPLUS (DEFICIT) | D66: =D19-D62 -> 0.15666667 | E66: - | F66: =D66/D$8 -> 1.2803487e-08 | G66: =G19-G62 -> -6867.7778 | H66: =(G66-D66)/D66 -> -43837.879 | I66: =G66/G$8 -> -0.00053549924 | J66: =J19-J62 -> -24783.9 | K66: =(J66-G66)/G66 -> 2.6087219 | L66: =J66/J$8 -> -0.0018342819 | M66: =M19-M62 -> 5848.7546 | N66: =(M66-J66)/J66 -> -1.2359901 | O66: =M66/M$8 -> 0.00041215986 | P66: =P19-P62 -> 23910.221 | Q66: =(P66-M66)/M66 -> 3.0880876 | R66: =P66/P$8 -> 0.0016080044 | S66: =S19-S62 -> 28559.951 | T66: =(S66-P66)/P66 -> 0.19446623 | U66: =S66/S$8 -> 0.0018458524 | V66: =V19-V62 -> 18899.743 | W66: =(V66-S66)/S66 -> -0.33824315 | X66: =V66/V$8 -> 0.0011701541 | Y66: =Y19-Y62 -> 54303.072 | Z66: =(Y66-V66)/V66 -> 1.8732174 | AA66: =Y66/Y$8 -> 0.0032119641 | AB66: =AB19-AB62 -> 73410.811 | AC66: =(AB66-Y66)/Y66 -> 0.35187215 | AD66: =AB66/AB$8 -> 0.0041536048 | AE66: =AE19-AE62 -> 62793.32 | AF66: =(AE66-AB66)/AB66 -> -0.14463116 | AG66: =AE66/AE$8 -> 0.0034057394 | AH66: =AH19-AH62 -> 106278.88 | AI66: =(AH66-AE66)/AE66 -> 0.69251896 | AJ66: =AH66/AH$8 -> 0.0054869194 | AK66: =AK19-AK62 -> 117615.14 | AL66: =(AK66-AH66)/AH66 -> 0.10666517 | AM66: =AK66/AK$8 -> 0.0057945628 | AN66: =AN19-AN62 -> 120130.13 | AO66: =(AN66-AK66)/AK66 -> 0.021383256 | AP66: =AN66/AN$8 -> 0.005678972 | AQ66: =AQ19-AQ62 -> 148059.67 | AR66: =(AQ66-AN66)/AN66 -> 0.232494 | AS66: =AQ66/AQ$8 -> 0.0067051455 | AT66: =AT19-AT62 -> 151874.22 | AU66: =(AT66-AQ66)/AQ66 -> 0.025763595 | AV66: =AT66/AT$8 -> 0.0065752108 | AW66: =AW19-AW62 -> 142272.06 | AX66: =(AW66-AT66)/AT66 -> -0.063224387 | AY66: =AW66/AW$8 -> 0.005898877 | AZ66: =AZ19-AZ62 -> 153171.96 | BA66: =(AZ66-AW66)/AW66 -> 0.076613033 | BB66: =AZ66/AZ$8 -> 0.0060725894 | BC66: =BC19-BC62 -> 134705.27 | BD66: =(BC66-AZ66)/AZ66 -> -0.1205618 | BE66: =BC66/BC$8 -> 0.0051016028 | BF66: =BF19-BF62 -> 132874.25 | BG66: =(BF66-BC66)/BC66 -> -0.013592768 | BH66: =BF66/BF$8 -> 0.0047999369 | BI66: =BI19-BI62 -> 109876.39 | BJ66: =(BI66-BF66)/BF66 -> -0.17307993 | BK66: =BI66/BI$8 -> 0.0037951225 | BL66: =BL19-BL62 -> 111428.1 | BM66: =(BL66-BI66)/BI66 -> 0.014122328 | BN66: =BL66/BL$8 -> 0.0036762817 | BO66: =BO19-BO62 -> 122754.47 | BP66: =(BO66-BL66)/BL66 -> 0.10164738 | BQ66: =BO66/BO$8 -> 0.003856747 | BR66: =BR19-BR62 -> 93244.918 | BS66: =(BR66-BO66)/BO66 -> -0.24039494 | BT66: =BR66/BR$8 -> 0.0028025884 | BU66: =BU19-BU62 -> 80441.391 | BV66: =(BU66-BR66)/BR66 -> -0.13731072 | BW66: =BU66/BU$8 -> 0.0023063648 | BX66: =BX19-BX62 -> 81359.13 | BY66: =(BX66-BU66)/BU66 -> 0.011408795 | BZ66: =BX66/BX$8 -> 0.0022245377 | CA66: =CA19-CA62 -> 32473.183 | CB66: =(CA66-BX66)/BX66 -> -0.60086614 | CC66: =CA66/CA$8 -> 0.00084855061 | CD66: =CD19-CD62 -> -21629.346 | CE66: =(CD66-CA66)/CA66 -> -1.6660679 | CF66: =CD66/CD$8 -> -0.00054007206 | CG66: =CG19-CG62 -> -72264.722 | CH66: =(CG66-CD66)/CD66 -> 2.3410498 | CI66: =CG66/CG$8 -> -0.0017208549 | CJ66: =CJ19-CJ62 -> -123335.75 | CK66: =(CJ66-CG66)/CG66 -> 0.7067214 | CL66: =CJ66/CJ$8 -> -0.0028062422 | CM66: =CM19-CM62 -> -179016.08 | CN66: =(CM66-CJ66)/CJ66 -> 0.45145337 | CO66: =CM66/CM$8 -> -0.0038866268 | CP66: 0.06044 | CQ66: fee escalator (linked to Fee Revenue tab)
B68: Notes:
B70: Line 1b, Return-to-aid: this is a blended rate that includes non-UC students in Summer.
B72: Line 4a: In 2026-27, RSF pays off deficit of $244K/year paid for from other revenue sources.
B74: Line 4b: CMS expenses include full rent (no subsidy) starting in 2016-17; final year of debt service at $245K/year is 2020-21.
B76: Lines 5a-f: These numbers need to be reality-checked against the program budgets covering the scope of each component.

Sheet Fee Revenue
B2: Wellness Referendum Model
B3: Fee Revenue – 30 years
B4: prepared by Hugh G. Graham, Campus Budget Office
B5: ='Model Summary'!B5 -> REVISED DRAFT 2/26/15
E6: Fees in bold are existing fees
D7: YEAR: | E7: 1 | H7: =E7+1 -> 2 | K7: =H7+1 -> 3 | N7: =K7+1 -> 4 | Q7: =N7+1 -> 5 | T7: =Q7+1 -> 6 | W7: =T7+1 -> 7 | Z7: =W7+1 -> 8 | AC7: =Z7+1 -> 9 | AF7: =AC7+1 -> 10 | AI7: =AF7+1 -> 11 | AL7: =AI7+1 -> 12 | AO7: =AL7+1 -> 13 | AR7: =AO7+1 -> 14 | AU7: =AR7+1 -> 15 | AX7: =AU7+1 -> 16 | BA7: =AX7+1 -> 17 | BD7: =BA7+1 -> 18 | BG7: =BD7+1 -> 19 | BJ7: =BG7+1 -> 20 | BM7: =BJ7+1 -> 21 | BP7: =BM7+1 -> 22 | BS7: =BP7+1 -> 23 | BV7: =BS7+1 -> 24 | BY7: =BV7+1 -> 25 | CB7: =BY7+1 -> 26 | CE7: =CB7+1 -> 27 | CH7: =CE7+1 -> 28 | CK7: =CH7+1 -> 29 | CN7: =CK7+1 -> 30
B8: =B7+1 -> 1 | E8: 2015-16 | H8: 2016-17 | K8: 2017-18 | N8: 2018-19 | Q8: 2019-20 | T8: 2020-21 | W8: 2021-22 | Z8: 2022-23 | AC8: 2023-24 | AF8: 2024-25 | AI8: 2025-26 | AL8: 2026-27 | AO8: 2027-28 | AR8: 2028-29 | AU8: 2029-30 | AX8: 2030-31 | BA8: 2031-32 | BD8: 2032-33 | BG8: 2033-34 | BJ8: 2034-35 | BM8: 2035-36 | BP8: 2036-37 | BS8: 2037-38 | BV8: 2038-39 | BY8: 2039-40 | CB8: 2040-41 | CE8: 2041-42 | CH8: 2042-43 | CK8: 2043-44 | CN8: 2044-45
B9: =B8+1 -> 2 | C9: FALL/SPRING | E9: Fall/Spring | H9: Fall/Spring | K9: Fall/Spring | N9: Fall/Spring | Q9: Fall/Spring | T9: Fall/Spring | W9: Fall/Spring | Z9: Fall/Spring | AC9: Fall/Spring | AF9: Fall/Spring | AI9: Fall/Spring | AL9: Fall/Spring | AO9: Fall/Spring | AR9: Fall/Spring | AU9: Fall/Spring | AX9: Fall/Spring | BA9: Fall/Spring | BD9: Fall/Spring | BG9: Fall/Spring | BJ9: Fall/Spring | BM9: Fall/Spring | BP9: Fall/Spring | BS9: Fall/Spring | BV9: Fall/Spring | BY9: Fall/Spring | CB9: Fall/Spring | CE9: Fall/Spring | CH9: Fall/Spring | CK9: Fall/Spring | CN9: Fall/Spring
B10: =B9+1 -> 3 | C10: Intramural Sports Facility Fee per semester | E10: 28.5 | H10: 28.5
B11: =B10+1 -> 4 | C11: Recreational Sports Fee per semester | D11: escalator | E11: 55 | H11: =H12-H10 -> 57.75
B12: =B11+1 -> 5 | C12: subtotal - base RSF fees per semester | D12: 0.03 | E12: =SUM(E10:E11) -> 83.5 | H12: =ROUND(E12*(1+$D$12),0)+1-(H15-INT(H15)) -> 86.25 | K12: =ROUND(H12*(1+$D$12),0)+1-(K15-INT(K15)) -> 90 | N12: =ROUND(K12*(1+$D$12),0)+1-(N15-INT(N15)) -> 93.75 | Q12: =ROUND(N12*(1+$D$12),0)+1-(Q15-INT(Q15)) -> 97.5 | T12: =ROUND(Q12*(1+$D$12),0)+1-(T15-INT(T15)) -> 100.25 | W12: =ROUND(T12*(1+$D$12),0)+1-(W15-INT(W15)) -> 104 | Z12: =ROUND(W12*(1+$D$12),0)+1-(Z15-INT(Z15)) -> 107.75 | AC12: =ROUND(Z12*(1+$D$12),0)+1-(AC15-INT(AC15)) -> 111.5 | AF12: =ROUND(AC12*(1+$D$12),0)+1-(AF15-INT(AF15)) -> 115.25 | AI12: =ROUND(AF12*(1+$D$12),0)+1-(AI15-INT(AI15)) -> 120 | AL12: =ROUND(AI12*(1+$D$12),0)+1-(AL15-INT(AL15)) -> 124.75 | AO12: =ROUND(AL12*(1+$D$12),0)+1-(AO15-INT(AO15)) -> 128.5 | AR12: =ROUND(AO12*(1+$D$12),0)+1-(AR15-INT(AR15)) -> 132.25 | AU12: =ROUND(AR12*(1+$D$12),0)+1-(AU15-INT(AU15)) -> 137 | AX12: =ROUND(AU12*(1+$D$12),0)+1-(AX15-INT(AX15)) -> 141.75 | BA12: =ROUND(AX12*(1+$D$12),0)+1-(BA15-INT(BA15)) -> 146.5 | BD12: =ROUND(BA12*(1+$D$12),0)+1-(BD15-INT(BD15)) -> 152 | BG12: =ROUND(BD12*(1+$D$12),0)+1-(BG15-INT(BG15)) -> 157.5 | BJ12: =ROUND(BG12*(1+$D$12),0)+1-(BJ15-INT(BJ15)) -> 163 | BM12: =ROUND(BJ12*(1+$D$12),0)+1-(BM15-INT(BM15)) -> 168.5 | BP12: =ROUND(BM12*(1+$D$12),0)+1-(BP15-INT(BP15)) -> 175 | BS12: =ROUND(BP12*(1+$D$12),0)+1-(BS15-INT(BS15)) -> 180.5 | BV12: =ROUND(BS12*(1+$D$12),0)+1-(BV15-INT(BV15)) -> 187 | BY12: =ROUND(BV12*(1+$D$12),0)+1-(BY15-INT(BY15)) -> 193.5 | CB12: =ROUND(BY12*(1+$D$12),0)+1-(CB15-INT(CB15)) -> 200 | CE12: =ROUND(CB12*(1+$D$12),0)+1-(CE15-INT(CE15)) -> 206.5 | CH12: =ROUND(CE12*(1+$D$12),0)+1-(CH15-INT(CH15)) -> 214 | CK12: =ROUND(CH12*(1+$D$12),0)+1-(CK15-INT(CK15)) -> 220.5 | CN12: =ROUND(CK12*(1+$D$12),0)+1-(CN15-INT(CN15)) -> 228
B13: =B12+1 -> 6
B14: =B13+1 -> 7 | D14: escalator
B15: =B14+1 -> 8 | C15: RSF membership fee buy-out | D15: 0.03 | E15: 8.5 | H15: =MROUND(E15*(1+$D15),0.25) -> 8.75 | K15: =MROUND(H15*(1+$D15),0.25) -> 9 | N15: =MROUND(K15*(1+$D15),0.25) -> 9.25 | Q15: =MROUND(N15*(1+$D15),0.25) -> 9.5 | T15: =MROUND(Q15*(1+$D15),0.25) -> 9.75 | W15: =MROUND(T15*(1+$D15),0.25) -> 10 | Z15: =MROUND(W15*(1+$D15),0.25) -> 10.25 | AC15: =MROUND(Z15*(1+$D15),0.25) -> 10.5 | AF15: =MROUND(AC15*(1+$D15),0.25) -> 10.75 | AI15: =MROUND(AF15*(1+$D15),0.25) -> 11 | AL15: =MROUND(AI15*(1+$D15),0.25) -> 11.25 | AO15: =MROUND(AL15*(1+$D15),0.25) -> 11.5 | AR15: =MROUND(AO15*(1+$D15),0.25) -> 11.75 | AU15: =MROUND(AR15*(1+$D15),0.25) -> 12 | AX15: =MROUND(AU15*(1+$D15),0.25) -> 12.25 | BA15: =MROUND(AX15*(1+$D15),0.25) -> 12.5 | BD15: =MROUND(BA15*(1+$D15),0.25) -> 13 | BG15: =MROUND(BD15*(1+$D15),0.25) -> 13.5 | BJ15: =MROUND(BG15*(1+$D15),0.25) -> 14 | BM15: =MROUND(BJ15*(1+$D15),0.25) -> 14.5 | BP15: =MROUND(BM15*(1+$D15),0.25) -> 15 | BS15: =MROUND(BP15*(1+$D15),0.25) -> 15.5 | BV15: =MROUND(BS15*(1+$D15),0.25) -> 16 | BY15: =MROUND(BV15*(1+$D15),0.25) -> 16.5 | CB15: =MROUND(BY15*(1+$D15),0.25) -> 17 | CE15: =MROUND(CB15*(1+$D15),0.25) -> 17.5 | CH15: =MROUND(CE15*(1+$D15),0.25) -> 18 | CK15: =MROUND(CH15*(1+$D15),0.25) -> 18.5 | CN15: =MROUND(CK15*(1+$D15),0.25) -> 19
B16: =B15+1 -> 9
B17: =B16+1 -> 10 | D17: escalator
B18: =B17+1 -> 11 | C18: New Fee Increment | D18: ='Model Summary'!CP66 -> 0.06044 | E18: 54 | H18: =ROUND(E18*(1+$D$18),0) -> 57 | K18: =ROUND(H18*(1+$D$18),0) -> 60 | N18: =ROUND(K18*(1+$D$18),0) -> 64 | Q18: =ROUND(N18*(1+$D$18),0) -> 68 | T18: =ROUND(Q18*(1+$D$18),0) -> 72 | W18: =ROUND(T18*(1+$D$18),0) -> 76 | Z18: =ROUND(W18*(1+$D$18),0) -> 81 | AC18: =ROUND(Z18*(1+$D$18),0) -> 86 | AF18: =ROUND(AC18*(1+$D$18),0) -> 91 | AI18: =ROUND(AF18*(1+$D$18),0) -> 97 | AL18: =ROUND(AI18*(1+$D$18),0) -> 103 | AO18: =ROUND(AL18*(1+$D$18),0) -> 109 | AR18: =ROUND(AO18*(1+$D$18),0) -> 116 | AU18: =ROUND(AR18*(1+$D$18),0) -> 123 | AX18: =ROUND(AU18*(1+$D$18),0) -> 130 | BA18: =ROUND(AX18*(1+$D$18),0) -> 138 | BD18: =ROUND(BA18*(1+$D$18),0) -> 146 | BG18: =ROUND(BD18*(1+$D$18),0) -> 155 | BJ18: =ROUND(BG18*(1+$D$18),0) -> 164 | BM18: =ROUND(BJ18*(1+$D$18),0) -> 174 | BP18: =ROUND(BM18*(1+$D$18),0) -> 185 | BS18: =ROUND(BP18*(1+$D$18),0) -> 196 | BV18: =ROUND(BS18*(1+$D$18),0) -> 208 | BY18: =ROUND(BV18*(1+$D$18),0) -> 221 | CB18: =ROUND(BY18*(1+$D$18),0) -> 234 | CE18: =ROUND(CB18*(1+$D$18),0) -> 248 | CH18: =ROUND(CE18*(1+$D$18),0) -> 263 | CK18: =ROUND(CH18*(1+$D$18),0) -> 279 | CN18: =ROUND(CK18*(1+$D$18),0) -> 296
B19: =B18+1 -> 12
B20: =B19+1 -> 13 | C20: TOTAL FEE - FALL/SPRING (rounded to whole $'s) | E20: =E12+E15+E18 -> 146 | H20: =H12+H15+H18 -> 152 | K20: =K12+K15+K18 -> 159 | N20: =N12+N15+N18 -> 167 | Q20: =Q12+Q15+Q18 -> 175 | T20: =T12+T15+T18 -> 182 | W20: =W12+W15+W18 -> 190 | Z20: =Z12+Z15+Z18 -> 199 | AC20: =AC12+AC15+AC18 -> 208 | AF20: =AF12+AF15+AF18 -> 217 | AI20: =AI12+AI15+AI18 -> 228 | AL20: =AL12+AL15+AL18 -> 239 | AO20: =AO12+AO15+AO18 -> 249 | AR20: =AR12+AR15+AR18 -> 260 | AU20: =AU12+AU15+AU18 -> 272 | AX20: =AX12+AX15+AX18 -> 284 | BA20: =BA12+BA15+BA18 -> 297 | BD20: =BD12+BD15+BD18 -> 311 | BG20: =BG12+BG15+BG18 -> 326 | BJ20: =BJ12+BJ15+BJ18 -> 341 | BM20: =BM12+BM15+BM18 -> 357 | BP20: =BP12+BP15+BP18 -> 375 | BS20: =BS12+BS15+BS18 -> 392 | BV20: =BV12+BV15+BV18 -> 411 | BY20: =BY12+BY15+BY18 -> 431 | CB20: =CB12+CB15+CB18 -> 451 | CE20: =CE12+CE15+CE18 -> 472 | CH20: =CH12+CH15+CH18 -> 495 | CK20: =CK12+CK15+CK18 -> 518 | CN20: =CN12+CN15+CN18 -> 543
B21: =B20+1 -> 14 | C21: total blended growth % after rounding | E21: n/a | H21: =(H20-E20)/E20 -> 0.04109589 | K21: =(K20-H20)/H20 -> 0.046052632 | N21: =(N20-K20)/K20 -> 0.050314465 | Q21: =(Q20-N20)/N20 -> 0.047904192 | T21: =(T20-Q20)/Q20 -> 0.04 | W21: =(W20-T20)/T20 -> 0.043956044 | Z21: =(Z20-W20)/W20 -> 0.047368421 | AC21: =(AC20-Z20)/Z20 -> 0.045226131 | AF21: =(AF20-AC20)/AC20 -> 0.043269231 | AI21: =(AI20-AF20)/AF20 -> 0.050691244 | AL21: =(AL20-AI20)/AI20 -> 0.048245614 | AO21: =(AO20-AL20)/AL20 -> 0.041841004 | AR21: =(AR20-AO20)/AO20 -> 0.044176707 | AU21: =(AU20-AR20)/AR20 -> 0.046153846 | AX21: =(AX20-AU20)/AU20 -> 0.044117647 | BA21: =(BA20-AX20)/AX20 -> 0.045774648 | BD21: =(BD20-BA20)/BA20 -> 0.047138047 | BG21: =(BG20-BD20)/BD20 -> 0.048231511 | BJ21: =(BJ20-BG20)/BG20 -> 0.04601227 | BM21: =(BM20-BJ20)/BJ20 -> 0.046920821 | BP21: =(BP20-BM20)/BM20 -> 0.050420168 | BS21: =(BS20-BP20)/BP20 -> 0.045333333 | BV21: =(BV20-BS20)/BS20 -> 0.048469388 | BY21: =(BY20-BV20)/BV20 -> 0.0486618 | CB21: =(CB20-BY20)/BY20 -> 0.046403712 | CE21: =(CE20-CB20)/CB20 -> 0.046563193 | CH21: =(CH20-CE20)/CE20 -> 0.048728814 | CK21: =(CK20-CH20)/CH20 -> 0.046464646 | CN21: =(CN20-CK20)/CK20 -> 0.048262548
B22: =B21+1 -> 15
B23: =B22+1 -> 16 | E23: 2015-16 | H23: 2016-17 | K23: 2017-18 | N23: 2018-19 | Q23: 2019-20 | T23: 2020-21 | W23: 2021-22 | Z23: 2022-23 | AC23: 2023-24 | AF23: 2024-25 | AI23: 2025-26 | AL23: 2026-27 | AO23: 2027-28 | AR23: 2028-29 | AU23: 2029-30 | AX23: 2030-31 | BA23: 2031-32 | BD23: 2032-33 | BG23: 2033-34 | BJ23: 2034-35 | BM23: 2035-36 | BP23: 2036-37 | BS23: 2037-38 | BV23: 2038-39 | BY23: 2039-40 | CB23: 2040-41 | CE23: 2041-42 | CH23: 2042-43 | CK23: 2043-44 | CN23: 2044-45
B24: =B23+1 -> 17 | C24: SUMMER | E24: Summer | H24: Summer | K24: Summer | N24: Summer | Q24: Summer | T24: Summer | W24: Summer | Z24: Summer | AC24: Summer | AF24: Summer | AI24: Summer | AL24: Summer | AO24: Summer | AR24: Summer | AU24: Summer | AX24: Summer | BA24: Summer | BD24: Summer | BG24: Summer | BJ24: Summer | BM24: Summer | BP24: Summer | BS24: Summer | BV24: Summer | BY24: Summer | CB24: Summer | CE24: Summer | CH24: Summer | CK24: Summer | CN24: Summer
B25: =B24+1 -> 18 | C25: Intramural Sports Facility Fee
B26: =B25+1 -> 19 | C26: Recreational Sports Fee | E26: 55
B27: =B26+1 -> 20 | C27: subtotal - base RSF fees | E27: =E33-E31-E29 -> 60.5 | H27: =H33-H31-H29 -> 62.25 | I27: =I33-I31-I29 -> 0 | J27: =J33-J31-J29 -> 0 | K27: =K33-K31-K29 -> 65 | L27: =L33-L31-L29 -> 0 | M27: =M33-M31-M29 -> 0 | N27: =N33-N31-N29 -> 67.75 | O27: =O33-O31-O29 -> 0 | ... CN27: =CN33-CN31-CN29 -> 166
B28: =B27+1 -> 21
B29: =B28+1 -> 22 | C29: RSF membership fee buy-out | E29: 8.5 | H29: =H15 -> 8.75 | K29: =K15 -> 9 | N29: =N15 -> 9.25 | Q29: =Q15 -> 9.5 | T29: =T15 -> 9.75 | W29: =W15 -> 10 | Z29: =Z15 -> 10.25 | AC29: =AC15 -> 10.5 | AF29: =AF15 -> 10.75 | AI29: =AI15 -> 11 | AL29: =AL15 -> 11.25 | AO29: =AO15 -> 11.5 | AR29: =AR15 -> 11.75 | AU29: =AU15 -> 12 | AX29: =AX15 -> 12.25 | BA29: =BA15 -> 12.5 | BD29: =BD15 -> 13 | BG29: =BG15 -> 13.5 | BJ29: =BJ15 -> 14 | BM29: =BM15 -> 14.5 | BP29: =BP15 -> 15 | BS29: =BS15 -> 15.5 | BV29: =BV15 -> 16 | BY29: =BY15 -> 16.5 | CB29: =CB15 -> 17 | CE29: =CE15 -> 17.5 | CH29: =CH15 -> 18 | CK29: =CK15 -> 18.5 | CN29: =CN15 -> 19
B30: =B29+1 -> 23
B31: =B30+1 -> 24 | C31: New Fee Increment | E31: =ROUND(E18*0.75,0) -> 41 | F31: =F18 | G31: =G18 | H31: =ROUND(H18*0.75,0) -> 43 | I31: =ROUND(I18*0.75,0) -> 0 | J31: =ROUND(J18*0.75,0) -> 0 | K31: =ROUND(K18*0.75,0) -> 45 | L31: =ROUND(L18*0.75,0) -> 0 | M31: =ROUND(M18*0.75,0) -> 0 | N31: =ROUND(N18*0.75,0) -> 48 | O31: =ROUND(O18*0.75,0) -> 0 | ... CN31: =ROUND(CN18*0.75,0) -> 222
B32: =B31+1 -> 25
B33: =B32+1 -> 26 | C33: TOTAL FEE - SUMMER (rounded to whole $'s) | E33: =ROUND(E20*0.75,0) -> 110 | F33: =ROUND(F20*0.75,0) -> 0 | G33: =ROUND(G20*0.75,0) -> 0 | H33: =ROUND(H20*0.75,0) -> 114 | I33: =ROUND(I20*0.75,0) -> 0 | J33: =ROUND(J20*0.75,0) -> 0 | K33: =ROUND(K20*0.75,0) -> 119 | L33: =ROUND(L20*0.75,0) -> 0 | ... CN33: =ROUND(CN20*0.75,0) -> 407
B34: =B33+1 -> 27
B35: =B34+1 -> 28 | C35: Student Headcount Assumptions | E35: 2015-16 | H35: 2016-17 | K35: 2017-18 | N35: 2018-19 | Q35: 2019-20 | T35: 2020-21 | W35: 2021-22 | Z35: 2022-23 | AC35: 2023-24 | AF35: 2024-25 | AI35: 2025-26 | AL35: 2026-27 | AO35: 2027-28 | AR35: 2028-29 | AU35: 2029-30 | AX35: 2030-31 | BA35: 2031-32 | BD35: 2032-33 | BG35: 2033-34 | BJ35: 2034-35 | BM35: 2035-36 | BP35: 2036-37 | BS35: 2037-38 | BV35: 2038-39 | BY35: 2039-40 | CB35: 2040-41 | CE35: 2041-42 | CH35: 2042-43 | CK35: 2043-44 | CN35: 2044-45
B36: =B35+1 -> 29 | C36: Fall | E36: 36000 | H36: 36000 | K36: 36000 | N36: 36000 | Q36: 36000 | T36: 36000 | W36: 36000 | Z36: 36000 | AC36: 36000 | AF36: 36000 | AI36: 36000 | AL36: 36000 | AO36: 36000 | AR36: 36000 | AU36: 36000 | AX36: 36000 | BA36: 36000 | BD36: 36000 | BG36: 36000 | BJ36: 36000 | BM36: 36000 | BP36: 36000 | BS36: 36000 | BV36: 36000 | BY36: 36000 | CB36: 36000 | CE36: 36000 | CH36: 36000 | CK36: 36000 | CN36: 36000
B37: =B36+1 -> 30 | C37: Spring | E37: 36000 | H37: 36000 | K37: 36000 | N37: 36000 | Q37: 36000 | T37: 36000 | W37: 36000 | Z37: 36000 | AC37: 36000 | AF37: 36000 | AI37: 36000 | AL37: 36000 | AO37: 36000 | AR37: 36000 | AU37: 36000 | AX37: 36000 | BA37: 36000 | BD37: 36000 | BG37: 36000 | BJ37: 36000 | BM37: 36000 | BP37: 36000 | BS37: 36000 | BV37: 36000 | BY37: 36000 | CB37: 36000 | CE37: 36000 | CH37: 36000 | CK37: 36000 | CN37: 36000
B38: =B37+1 -> 31 | C38: Summer UC | E38: 12500 | H38: 12500 | K38: 12500 | N38: 12500 | Q38: 12500 | T38: 12500 | W38: 12500 | Z38: 12500 | AC38: 12500 | AF38: 12500 | AI38: 12500 | AL38: 12500 | AO38: 12500 | AR38: 12500 | AU38: 12500 | AX38: 12500 | BA38: 12500 | BD38: 12500 | BG38: 12500 | BJ38: 12500 | BM38: 12500 | BP38: 12500 | BS38: 12500 | BV38: 12500 | BY38: 12500 | CB38: 12500 | CE38: 12500 | CH38: 12500 | CK38: 12500 | CN38: 12500
B39: =B38+1 -> 32 | C39: Summer non-UC | E39: 4000 | H39: 4000 | K39: 4000 | N39: 4000 | Q39: 4000 | T39: 4000 | W39: 4000 | Z39: 4000 | AC39: 4000 | AF39: 4000 | AI39: 4000 | AL39: 4000 | AO39: 4000 | AR39: 4000 | AU39: 4000 | AX39: 4000 | BA39: 4000 | BD39: 4000 | BG39: 4000 | BJ39: 4000 | BM39: 4000 | BP39: 4000 | BS39: 4000 | BV39: 4000 | BY39: 4000 | CB39: 4000 | CE39: 4000 | CH39: 4000 | CK39: 4000 | CN39: 4000
B40: =B39+1 -> 33
B41: =B40+1 -> 34 | C41: RSF BASE FEE REVENUE
B42: =B41+1 -> 35 | C42: Intramural Sports Facility Fee
B43: =B42+1 -> 36 | C43: Gross Fee Revenue - Fall + Spring | E43: =(E10*E36)+(E10*E37) -> 2052000 | H43: =(H10*H36)+(H10*H37) -> 2052000
B44: =B43+1 -> 37 | C44: Recreational Sports Fee
B45: =B44+1 -> 38 | C45: Gross Fee Revenue - Fall + Spring | E45: =(E11*E36)+(E11*E37) -> 3960000 | H45: =(H11*H36)+(H11*H37) -> 4158000 | K45: =(K12*K36)+(K12*K37) -> 6480000 | N45: =(N12*N36)+(N12*N37) -> 6750000 | Q45: =(Q12*Q36)+(Q12*Q37) -> 7020000 | T45: =(T12*T36)+(T12*T37) -> 7218000 | W45: =(W12*W36)+(W12*W37) -> 7488000 | Z45: =(Z12*Z36)+(Z12*Z37) -> 7758000 | AC45: =(AC12*AC36)+(AC12*AC37) -> 8028000 | AF45: =(AF12*AF36)+(AF12*AF37) -> 8298000 | AI45: =(AI12*AI36)+(AI12*AI37) -> 8640000 | AL45: =(AL12*AL36)+(AL12*AL37) -> 8982000 | AO45: =(AO12*AO36)+(AO12*AO37) -> 9252000 | AR45: =(AR12*AR36)+(AR12*AR37) -> 9522000 | AU45: =(AU12*AU36)+(AU12*AU37) -> 9864000 | AX45: =(AX12*AX36)+(AX12*AX37) -> 10206000 | BA45: =(BA12*BA36)+(BA12*BA37) -> 10548000 | BD45: =(BD12*BD36)+(BD12*BD37) -> 10944000 | BG45: =(BG12*BG36)+(BG12*BG37) -> 11340000 | BJ45: =(BJ12*BJ36)+(BJ12*BJ37) -> 11736000 | BM45: =(BM12*BM36)+(BM12*BM37) -> 12132000 | BP45: =(BP12*BP36)+(BP12*BP37) -> 12600000 | BS45: =(BS12*BS36)+(BS12*BS37) -> 12996000 | BV45: =(BV12*BV36)+(BV12*BV37) -> 13464000 | BY45: =(BY12*BY36)+(BY12*BY37) -> 13932000 | CB45: =(CB12*CB36)+(CB12*CB37) -> 14400000 | CE45: =(CE12*CE36)+(CE12*CE37) -> 14868000 | CH45: =(CH12*CH36)+(CH12*CH37) -> 15408000 | CK45: =(CK12*CK36)+(CK12*CK37) -> 15876000 | CN45: =(CN12*CN36)+(CN12*CN37) -> 16416000
B46: =B45+1 -> 39 | C46: Less: return-to-aid (gross revenue / 3) | E46: =-E45/3 -> -1320000 | H46: =-H45/3 -> -1386000 | K46: =-K45/3 -> -2160000 | N46: =-N45/3 -> -2250000 | Q46: =-Q45/3 -> -2340000 | T46: =-T45/3 -> -2406000 | W46: =-W45/3 -> -2496000 | Z46: =-Z45/3 -> -2586000 | AC46: =-AC45/3 -> -2676000 | AF46: =-AF45/3 -> -2766000 | AI46: =-AI45/3 -> -2880000 | AL46: =-AL45/3 -> -2994000 | AO46: =-AO45/3 -> -3084000 | AR46: =-AR45/3 -> -3174000 | AU46: =-AU45/3 -> -3288000 | AX46: =-AX45/3 -> -3402000 | BA46: =-BA45/3 -> -3516000 | BD46: =-BD45/3 -> -3648000 | BG46: =-BG45/3 -> -3780000 | BJ46: =-BJ45/3 -> -3912000 | BM46: =-BM45/3 -> -4044000 | BP46: =-BP45/3 -> -4200000 | BS46: =-BS45/3 -> -4332000 | BV46: =-BV45/3 -> -4488000 | BY46: =-BY45/3 -> -4644000 | CB46: =-CB45/3 -> -4800000 | CE46: =-CE45/3 -> -4956000 | CH46: =-CH45/3 -> -5136000 | CK46: =-CK45/3 -> -5292000 | CN46: =-CN45/3 -> -5472000
B47: =B46+1 -> 40 | C47: Gross Fee Revenue - Summer UC | E47: =(E26*E38) -> 687500 | H47: =H27*H38 -> 778125 | K47: =K27*K38 -> 812500 | N47: =N27*N38 -> 846875 | Q47: =Q27*Q38 -> 881250 | T47: =T27*T38 -> 915625 | W47: =W27*W38 -> 950000 | Z47: =Z27*Z38 -> 971875 | AC47: =AC27*AC38 -> 1006250 | AF47: =AF27*AF38 -> 1053125 | AI47: =AI27*AI38 -> 1087500 | AL47: =AL27*AL38 -> 1134375 | AO47: =AO27*AO38 -> 1168750 | AR47: =AR27*AR38 -> 1203125 | AU47: =AU27*AU38 -> 1250000 | AX47: =AX27*AX38 -> 1284375 | BA47: =BA27*BA38 -> 1331250 | BD47: =BD27*BD38 -> 1375000 | BG47: =BG27*BG38 -> 1443750 | BJ47: =BJ27*BJ38 -> 1487500 | BM47: =BM27*BM38 -> 1531250 | BP47: =BP27*BP38 -> 1587500 | BS47: =BS27*BS38 -> 1643750 | BV47: =BV27*BV38 -> 1700000 | BY47: =BY27*BY38 -> 1756250 | CB47: =CB27*CB38 -> 1812500 | CE47: =CE27*CE38 -> 1881250 | CH47: =CH27*CH38 -> 1950000 | CK47: =CK27*CK38 -> 2018750 | CN47: =CN27*CN38 -> 2075000
B48: =B47+1 -> 41 | C48: Less: return-to-aid (gross revenue / 3) | E48: =-E47/3 -> -229166.67 | H48: =-H47/3 -> -259375 | K48: =-K47/3 -> -270833.33 | N48: =-N47/3 -> -282291.67 | Q48: =-Q47/3 -> -293750 | T48: =-T47/3 -> -305208.33 | W48: =-W47/3 -> -316666.67 | Z48: =-Z47/3 -> -323958.33 | AC48: =-AC47/3 -> -335416.67 | AF48: =-AF47/3 -> -351041.67 | AI48: =-AI47/3 -> -362500 | AL48: =-AL47/3 -> -378125 | AO48: =-AO47/3 -> -389583.33 | AR48: =-AR47/3 -> -401041.67 | AU48: =-AU47/3 -> -416666.67 | AX48: =-AX47/3 -> -428125 | BA48: =-BA47/3 -> -443750 | BD48: =-BD47/3 -> -458333.33 | BG48: =-BG47/3 -> -481250 | BJ48: =-BJ47/3 -> -495833.33 | BM48: =-BM47/3 -> -510416.67 | BP48: =-BP47/3 -> -529166.67 | BS48: =-BS47/3 -> -547916.67 | BV48: =-BV47/3 -> -566666.67 | BY48: =-BY47/3 -> -585416.67 | CB48: =-CB47/3 -> -604166.67 | CE48: =-CE47/3 -> -627083.33 | CH48: =-CH47/3 -> -650000 | CK48: =-CK47/3 -> -672916.67 | CN48: =-CN47/3 -> -691666.67
B49: =B48+1 -> 42 | C49: Gross Fee Revenue - Summer non-UC | E49: =E26*E39 -> 220000 | H49: =H27*H39 -> 249000 | K49: =K12*K39 -> 360000 | N49: =N12*N39 -> 375000 | Q49: =Q12*Q39 -> 390000 | T49: =T12*T39 -> 401000 | W49: =W12*W39 -> 416000 | Z49: =Z12*Z39 -> 431000 | AC49: =AC12*AC39 -> 446000 | AF49: =AF12*AF39 -> 461000 | AI49: =AI12*AI39 -> 480000 | AL49: =AL12*AL39 -> 499000 | AO49: =AO12*AO39 -> 514000 | AR49: =AR12*AR39 -> 529000 | AU49: =AU12*AU39 -> 548000 | AX49: =AX12*AX39 -> 567000 | BA49: =BA12*BA39 -> 586000 | BD49: =BD12*BD39 -> 608000 | BG49: =BG12*BG39 -> 630000 | BJ49: =BJ12*BJ39 -> 652000 | BM49: =BM12*BM39 -> 674000 | BP49: =BP12*BP39 -> 700000 | BS49: =BS12*BS39 -> 722000 | BV49: =BV12*BV39 -> 748000 | BY49: =BY12*BY39 -> 774000 | CB49: =CB12*CB39 -> 800000 | CE49: =CE12*CE39 -> 826000 | CH49: =CH12*CH39 -> 856000 | CK49: =CK12*CK39 -> 882000 | CN49: =CN12*CN39 -> 912000
B50: =B49+1 -> 43 | C50: Net Fee Revenue | E50: =SUM(E44:E49) -> 3318333.3 | H50: =SUM(H44:H49) -> 3539750 | K50: =SUM(K44:K49) -> 5221666.7 | N50: =SUM(N44:N49) -> 5439583.3 | Q50: =SUM(Q44:Q49) -> 5657500 | T50: =SUM(T44:T49) -> 5823416.7 | W50: =SUM(W44:W49) -> 6041333.3 | Z50: =SUM(Z44:Z49) -> 6250916.7 | AC50: =SUM(AC44:AC49) -> 6468833.3 | AF50: =SUM(AF44:AF49) -> 6695083.3 | AI50: =SUM(AI44:AI49) -> 6965000 | AL50: =SUM(AL44:AL49) -> 7243250 | AO50: =SUM(AO44:AO49) -> 7461166.7 | AR50: =SUM(AR44:AR49) -> 7679083.3 | AU50: =SUM(AU44:AU49) -> 7957333.3 | AX50: =SUM(AX44:AX49) -> 8227250 | BA50: =SUM(BA44:BA49) -> 8505500 | BD50: =SUM(BD44:BD49) -> 8820666.7 | BG50: =SUM(BG44:BG49) -> 9152500 | BJ50: =SUM(BJ44:BJ49) -> 9467666.7 | BM50: =SUM(BM44:BM49) -> 9782833.3 | BP50: =SUM(BP44:BP49) -> 10158333 | BS50: =SUM(BS44:BS49) -> 10481833 | BV50: =SUM(BV44:BV49) -> 10857333 | BY50: =SUM(BY44:BY49) -> 11232833 | CB50: =SUM(CB44:CB49) -> 11608333 | CE50: =SUM(CE44:CE49) -> 11992167 | CH50: =SUM(CH44:CH49) -> 12428000 | CK50: =SUM(CK44:CK49) -> 12811833 | CN50: =SUM(CN44:CN49) -> 13239333
B51: =B50+1 -> 44 | C51: net - RSF BASE FEE REVENUE | E51: =E43+E50 -> 5370333.3 | H51: =H43+H50 -> 5591750 | K51: =K43+K50 -> 5221666.7 | N51: =N43+N50 -> 5439583.3 | Q51: =Q43+Q50 -> 5657500 | T51: =T43+T50 -> 5823416.7 | W51: =W43+W50 -> 6041333.3 | Z51: =Z43+Z50 -> 6250916.7 | AC51: =AC43+AC50 -> 6468833.3 | AF51: =AF43+AF50 -> 6695083.3 | AI51: =AI43+AI50 -> 6965000 | AL51: =AL43+AL50 -> 7243250 | AO51: =AO43+AO50 -> 7461166.7 | AR51: =AR43+AR50 -> 7679083.3 | AU51: =AU43+AU50 -> 7957333.3 | AX51: =AX43+AX50 -> 8227250 | BA51: =BA43+BA50 -> 8505500 | BD51: =BD43+BD50 -> 8820666.7 | BG51: =BG43+BG50 -> 9152500 | BJ51: =BJ43+BJ50 -> 9467666.7 | BM51: =BM43+BM50 -> 9782833.3 | BP51: =BP43+BP50 -> 10158333 | BS51: =BS43+BS50 -> 10481833 | BV51: =BV43+BV50 -> 10857333 | BY51: =BY43+BY50 -> 11232833 | CB51: =CB43+CB50 -> 11608333 | CE51: =CE43+CE50 -> 11992167 | CH51: =CH43+CH50 -> 12428000 | CK51: =CK43+CK50 -> 12811833 | CN51: =CN43+CN50 -> 13239333
B52: =B51+1 -> 45
B53: =B52+1 -> 46 | C53: RSF MEMBERSHIP FEE BUY-OUT REVENUE
B54: =B53+1 -> 47 | C54: Gross Fee Revenue - Fall + Spring | E54: =(E15*E36)+(E15*E37) -> 612000 | H54: =(H15*H36)+(H15*H37) -> 630000 | K54: =(K15*K36)+(K15*K37) -> 648000 | N54: =(N15*N36)+(N15*N37) -> 666000 | Q54: =(Q15*Q36)+(Q15*Q37) -> 684000 | T54: =(T15*T36)+(T15*T37) -> 702000 | W54: =(W15*W36)+(W15*W37) -> 720000 | Z54: =(Z15*Z36)+(Z15*Z37) -> 738000 | AC54: =(AC15*AC36)+(AC15*AC37) -> 756000 | AF54: =(AF15*AF36)+(AF15*AF37) -> 774000 | AI54: =(AI15*AI36)+(AI15*AI37) -> 792000 | AL54: =(AL15*AL36)+(AL15*AL37) -> 810000 | AO54: =(AO15*AO36)+(AO15*AO37) -> 828000 | AR54: =(AR15*AR36)+(AR15*AR37) -> 846000 | AU54: =(AU15*AU36)+(AU15*AU37) -> 864000 | AX54: =(AX15*AX36)+(AX15*AX37) -> 882000 | BA54: =(BA15*BA36)+(BA15*BA37) -> 900000 | BD54: =(BD15*BD36)+(BD15*BD37) -> 936000 | BG54: =(BG15*BG36)+(BG15*BG37) -> 972000 | BJ54: =(BJ15*BJ36)+(BJ15*BJ37) -> 1008000 | BM54: =(BM15*BM36)+(BM15*BM37) -> 1044000 | BP54: =(BP15*BP36)+(BP15*BP37) -> 1080000 | BS54: =(BS15*BS36)+(BS15*BS37) -> 1116000 | BV54: =(BV15*BV36)+(BV15*BV37) -> 1152000 | BY54: =(BY15*BY36)+(BY15*BY37) -> 1188000 | CB54: =(CB15*CB36)+(CB15*CB37) -> 1224000 | CE54: =(CE15*CE36)+(CE15*CE37) -> 1260000 | CH54: =(CH15*CH36)+(CH15*CH37) -> 1296000 | CK54: =(CK15*CK36)+(CK15*CK37) -> 1332000 | CN54: =(CN15*CN36)+(CN15*CN37) -> 1368000
B55: =B54+1 -> 48 | C55: Less: return-to-aid (gross revenue / 3) | E55: =-E54/3 -> -204000 | H55: =-H54/3 -> -210000 | K55: =-K54/3 -> -216000 | N55: =-N54/3 -> -222000 | Q55: =-Q54/3 -> -228000 | T55: =-T54/3 -> -234000 | W55: =-W54/3 -> -240000 | Z55: =-Z54/3 -> -246000 | AC55: =-AC54/3 -> -252000 | AF55: =-AF54/3 -> -258000 | AI55: =-AI54/3 -> -264000 | AL55: =-AL54/3 -> -270000 | AO55: =-AO54/3 -> -276000 | AR55: =-AR54/3 -> -282000 | AU55: =-AU54/3 -> -288000 | AX55: =-AX54/3 -> -294000 | BA55: =-BA54/3 -> -300000 | BD55: =-BD54/3 -> -312000 | BG55: =-BG54/3 -> -324000 | BJ55: =-BJ54/3 -> -336000 | BM55: =-BM54/3 -> -348000 | BP55: =-BP54/3 -> -360000 | BS55: =-BS54/3 -> -372000 | BV55: =-BV54/3 -> -384000 | BY55: =-BY54/3 -> -396000 | CB55: =-CB54/3 -> -408000 | CE55: =-CE54/3 -> -420000 | CH55: =-CH54/3 -> -432000 | CK55: =-CK54/3 -> -444000 | CN55: =-CN54/3 -> -456000
B56: =B55+1 -> 49 | C56: Gross Fee Revenue - Summer UC | E56: =E15*E38 -> 106250 | H56: =H15*H38 -> 109375 | K56: =K15*K38 -> 112500 | N56: =N15*N38 -> 115625 | Q56: =Q15*Q38 -> 118750 | T56: =T15*T38 -> 121875 | W56: =W15*W38 -> 125000 | Z56: =Z15*Z38 -> 128125 | AC56: =AC15*AC38 -> 131250 | AF56: =AF15*AF38 -> 134375 | AI56: =AI15*AI38 -> 137500 | AL56: =AL15*AL38 -> 140625 | AO56: =AO15*AO38 -> 143750 | AR56: =AR15*AR38 -> 146875 | AU56: =AU15*AU38 -> 150000 | AX56: =AX15*AX38 -> 153125 | BA56: =BA15*BA38 -> 156250 | BD56: =BD15*BD38 -> 162500 | BG56: =BG15*BG38 -> 168750 | BJ56: =BJ15*BJ38 -> 175000 | BM56: =BM15*BM38 -> 181250 | BP56: =BP15*BP38 -> 187500 | BS56: =BS15*BS38 -> 193750 | BV56: =BV15*BV38 -> 200000 | BY56: =BY15*BY38 -> 206250 | CB56: =CB15*CB38 -> 212500 | CE56: =CE15*CE38 -> 218750 | CH56: =CH15*CH38 -> 225000 | CK56: =CK15*CK38 -> 231250 | CN56: =CN15*CN38 -> 237500
B57: =B56+1 -> 50 | C57: Less: return-to-aid (gross revenue / 3) | E57: =-E56/3 -> -35416.667 | H57: =-H56/3 -> -36458.333 | K57: =-K56/3 -> -37500 | N57: =-N56/3 -> -38541.667 | Q57: =-Q56/3 -> -39583.333 | T57: =-T56/3 -> -40625 | W57: =-W56/3 -> -41666.667 | Z57: =-Z56/3 -> -42708.333 | AC57: =-AC56/3 -> -43750 | AF57: =-AF56/3 -> -44791.667 | AI57: =-AI56/3 -> -45833.333 | AL57: =-AL56/3 -> -46875 | AO57: =-AO56/3 -> -47916.667 | AR57: =-AR56/3 -> -48958.333 | AU57: =-AU56/3 -> -50000 | AX57: =-AX56/3 -> -51041.667 | BA57: =-BA56/3 -> -52083.333 | BD57: =-BD56/3 -> -54166.667 | BG57: =-BG56/3 -> -56250 | BJ57: =-BJ56/3 -> -58333.333 | BM57: =-BM56/3 -> -60416.667 | BP57: =-BP56/3 -> -62500 | BS57: =-BS56/3 -> -64583.333 | BV57: =-BV56/3 -> -66666.667 | BY57: =-BY56/3 -> -68750 | CB57: =-CB56/3 -> -70833.333 | CE57: =-CE56/3 -> -72916.667 | CH57: =-CH56/3 -> -75000 | CK57: =-CK56/3 -> -77083.333 | CN57: =-CN56/3 -> -79166.667
B58: =B57+1 -> 51 | C58: Gross Fee Revenue - Summer non-UC | E58: =E15*E39 -> 34000 | H58: =H15*H39 -> 35000 | K58: =K15*K39 -> 36000 | N58: =N15*N39 -> 37000 | Q58: =Q15*Q39 -> 38000 | T58: =T15*T39 -> 39000 | W58: =W15*W39 -> 40000 | Z58: =Z15*Z39 -> 41000 | AC58: =AC15*AC39 -> 42000 | AF58: =AF15*AF39 -> 43000 | AI58: =AI15*AI39 -> 44000 | AL58: =AL15*AL39 -> 45000 | AO58: =AO15*AO39 -> 46000 | AR58: =AR15*AR39 -> 47000 | AU58: =AU15*AU39 -> 48000 | AX58: =AX15*AX39 -> 49000 | BA58: =BA15*BA39 -> 50000 | BD58: =BD15*BD39 -> 52000 | BG58: =BG15*BG39 -> 54000 | BJ58: =BJ15*BJ39 -> 56000 | BM58: =BM15*BM39 -> 58000 | BP58: =BP15*BP39 -> 60000 | BS58: =BS15*BS39 -> 62000 | BV58: =BV15*BV39 -> 64000 | BY58: =BY15*BY39 -> 66000 | CB58: =CB15*CB39 -> 68000 | CE58: =CE15*CE39 -> 70000 | CH58: =CH15*CH39 -> 72000 | CK58: =CK15*CK39 -> 74000 | CN58: =CN15*CN39 -> 76000
B59: =B58+1 -> 52 | C59: net - RSF MEMBERSHIP FEE BUY-OUT REVENUE | E59: =SUM(E54:E58) -> 512833.33 | H59: =SUM(H54:H58) -> 527916.67 | K59: =SUM(K54:K58) -> 543000 | N59: =SUM(N54:N58) -> 558083.33 | Q59: =SUM(Q54:Q58) -> 573166.67 | T59: =SUM(T54:T58) -> 588250 | W59: =SUM(W54:W58) -> 603333.33 | Z59: =SUM(Z54:Z58) -> 618416.67 | AC59: =SUM(AC54:AC58) -> 633500 | AF59: =SUM(AF54:AF58) -> 648583.33 | AI59: =SUM(AI54:AI58) -> 663666.67 | AL59: =SUM(AL54:AL58) -> 678750 | AO59: =SUM(AO54:AO58) -> 693833.33 | AR59: =SUM(AR54:AR58) -> 708916.67 | AU59: =SUM(AU54:AU58) -> 724000 | AX59: =SUM(AX54:AX58) -> 739083.33 | BA59: =SUM(BA54:BA58) -> 754166.67 | BD59: =SUM(BD54:BD58) -> 784333.33 | BG59: =SUM(BG54:BG58) -> 814500 | BJ59: =SUM(BJ54:BJ58) -> 844666.67 | BM59: =SUM(BM54:BM58) -> 874833.33 | BP59: =SUM(BP54:BP58) -> 905000 | BS59: =SUM(BS54:BS58) -> 935166.67 | BV59: =SUM(BV54:BV58) -> 965333.33 | BY59: =SUM(BY54:BY58) -> 995500 | CB59: =SUM(CB54:CB58) -> 1025666.7 | CE59: =SUM(CE54:CE58) -> 1055833.3 | CH59: =SUM(CH54:CH58) -> 1086000 | CK59: =SUM(CK54:CK58) -> 1116166.7 | CN59: =SUM(CN54:CN58) -> 1146333.3
B60: =B59+1 -> 53
B61: =B60+1 -> 54 | C61: NEW FEE INCREMENT REVENUE
B62: =B61+1 -> 55 | C62: Gross Fee Revenue - Fall + Spring | E62: =(E18*E36)+(E18*E37) -> 3888000 | H62: =(H18*H36)+(H18*H37) -> 4104000 | K62: =(K18*K36)+(K18*K37) -> 4320000 | N62: =(N18*N36)+(N18*N37) -> 4608000 | Q62: =(Q18*Q36)+(Q18*Q37) -> 4896000 | T62: =(T18*T36)+(T18*T37) -> 5184000 | W62: =(W18*W36)+(W18*W37) -> 5472000 | Z62: =(Z18*Z36)+(Z18*Z37) -> 5832000 | AC62: =(AC18*AC36)+(AC18*AC37) -> 6192000 | AF62: =(AF18*AF36)+(AF18*AF37) -> 6552000 | AI62: =(AI18*AI36)+(AI18*AI37) -> 6984000 | AL62: =(AL18*AL36)+(AL18*AL37) -> 7416000 | AO62: =(AO18*AO36)+(AO18*AO37) -> 7848000 | AR62: =(AR18*AR36)+(AR18*AR37) -> 8352000 | AU62: =(AU18*AU36)+(AU18*AU37) -> 8856000 | AX62: =(AX18*AX36)+(AX18*AX37) -> 9360000 | BA62: =(BA18*BA36)+(BA18*BA37) -> 9936000 | BD62: =(BD18*BD36)+(BD18*BD37) -> 10512000 | BG62: =(BG18*BG36)+(BG18*BG37) -> 11160000 | BJ62: =(BJ18*BJ36)+(BJ18*BJ37) -> 11808000 | BM62: =(BM18*BM36)+(BM18*BM37) -> 12528000 | BP62: =(BP18*BP36)+(BP18*BP37) -> 13320000 | BS62: =(BS18*BS36)+(BS18*BS37) -> 14112000 | BV62: =(BV18*BV36)+(BV18*BV37) -> 14976000 | BY62: =(BY18*BY36)+(BY18*BY37) -> 15912000 | CB62: =(CB18*CB36)+(CB18*CB37) -> 16848000 | CE62: =(CE18*CE36)+(CE18*CE37) -> 17856000 | CH62: =(CH18*CH36)+(CH18*CH37) -> 18936000 | CK62: =(CK18*CK36)+(CK18*CK37) -> 20088000 | CN62: =(CN18*CN36)+(CN18*CN37) -> 21312000
B63: =B62+1 -> 56 | C63: Less: return-to-aid (gross revenue / 3) | E63: =-E62/3 -> -1296000 | H63: =-H62/3 -> -1368000 | K63: =-K62/3 -> -1440000 | N63: =-N62/3 -> -1536000 | Q63: =-Q62/3 -> -1632000 | T63: =-T62/3 -> -1728000 | W63: =-W62/3 -> -1824000 | Z63: =-Z62/3 -> -1944000 | AC63: =-AC62/3 -> -2064000 | AF63: =-AF62/3 -> -2184000 | AI63: =-AI62/3 -> -2328000 | AL63: =-AL62/3 -> -2472000 | AO63: =-AO62/3 -> -2616000 | AR63: =-AR62/3 -> -2784000 | AU63: =-AU62/3 -> -2952000 | AX63: =-AX62/3 -> -3120000 | BA63: =-BA62/3 -> -3312000 | BD63: =-BD62/3 -> -3504000 | BG63: =-BG62/3 -> -3720000 | BJ63: =-BJ62/3 -> -3936000 | BM63: =-BM62/3 -> -4176000 | BP63: =-BP62/3 -> -4440000 | BS63: =-BS62/3 -> -4704000 | BV63: =-BV62/3 -> -4992000 | BY63: =-BY62/3 -> -5304000 | CB63: =-CB62/3 -> -5616000 | CE63: =-CE62/3 -> -5952000 | CH63: =-CH62/3 -> -6312000 | CK63: =-CK62/3 -> -6696000 | CN63: =-CN62/3 -> -7104000
B64: =B63+1 -> 57 | C64: Gross Fee Revenue - Summer UC | E64: =E31*E38 -> 512500 | H64: =H31*H38 -> 537500 | K64: =K31*K38 -> 562500 | N64: =N31*N38 -> 600000 | Q64: =Q31*Q38 -> 637500 | T64: =T31*T38 -> 675000 | W64: =W31*W38 -> 712500 | Z64: =Z31*Z38 -> 762500 | AC64: =AC31*AC38 -> 812500 | AF64: =AF31*AF38 -> 850000 | AI64: =AI31*AI38 -> 912500 | AL64: =AL31*AL38 -> 962500 | AO64: =AO31*AO38 -> 1025000 | AR64: =AR31*AR38 -> 1087500 | AU64: =AU31*AU38 -> 1150000 | AX64: =AX31*AX38 -> 1225000 | BA64: =BA31*BA38 -> 1300000 | BD64: =BD31*BD38 -> 1375000 | BG64: =BG31*BG38 -> 1450000 | BJ64: =BJ31*BJ38 -> 1537500 | BM64: =BM31*BM38 -> 1637500 | BP64: =BP31*BP38 -> 1737500 | BS64: =BS31*BS38 -> 1837500 | BV64: =BV31*BV38 -> 1950000 | BY64: =BY31*BY38 -> 2075000 | CB64: =CB31*CB38 -> 2200000 | CE64: =CE31*CE38 -> 2325000 | CH64: =CH31*CH38 -> 2462500 | CK64: =CK31*CK38 -> 2612500 | CN64: =CN31*CN38 -> 2775000
B65: =B64+1 -> 58 | C65: Less: return-to-aid (gross revenue / 3) | E65: =-E64/3 -> -170833.33 | H65: =-H64/3 -> -179166.67 | K65: =-K64/3 -> -187500 | N65: =-N64/3 -> -200000 | Q65: =-Q64/3 -> -212500 | T65: =-T64/3 -> -225000 | W65: =-W64/3 -> -237500 | Z65: =-Z64/3 -> -254166.67 | AC65: =-AC64/3 -> -270833.33 | AF65: =-AF64/3 -> -283333.33 | AI65: =-AI64/3 -> -304166.67 | AL65: =-AL64/3 -> -320833.33 | AO65: =-AO64/3 -> -341666.67 | AR65: =-AR64/3 -> -362500 | AU65: =-AU64/3 -> -383333.33 | AX65: =-AX64/3 -> -408333.33 | BA65: =-BA64/3 -> -433333.33 | BD65: =-BD64/3 -> -458333.33 | BG65: =-BG64/3 -> -483333.33 | BJ65: =-BJ64/3 -> -512500 | BM65: =-BM64/3 -> -545833.33 | BP65: =-BP64/3 -> -579166.67 | BS65: =-BS64/3 -> -612500 | BV65: =-BV64/3 -> -650000 | BY65: =-BY64/3 -> -691666.67 | CB65: =-CB64/3 -> -733333.33 | CE65: =-CE64/3 -> -775000 | CH65: =-CH64/3 -> -820833.33 | CK65: =-CK64/3 -> -870833.33 | CN65: =-CN64/3 -> -925000
B66: =B65+1 -> 59 | C66: Gross Fee Revenue - Summer non-UC | E66: =E31*E39 -> 164000 | H66: =H31*H39 -> 172000 | K66: =K31*K39 -> 180000 | N66: =N31*N39 -> 192000 | Q66: =Q31*Q39 -> 204000 | T66: =T31*T39 -> 216000 | W66: =W31*W39 -> 228000 | Z66: =Z31*Z39 -> 244000 | AC66: =AC31*AC39 -> 260000 | AF66: =AF31*AF39 -> 272000 | AI66: =AI31*AI39 -> 292000 | AL66: =AL31*AL39 -> 308000 | AO66: =AO31*AO39 -> 328000 | AR66: =AR31*AR39 -> 348000 | AU66: =AU31*AU39 -> 368000 | AX66: =AX31*AX39 -> 392000 | BA66: =BA31*BA39 -> 416000 | BD66: =BD31*BD39 -> 440000 | BG66: =BG31*BG39 -> 464000 | BJ66: =BJ31*BJ39 -> 492000 | BM66: =BM31*BM39 -> 524000 | BP66: =BP31*BP39 -> 556000 | BS66: =BS31*BS39 -> 588000 | BV66: =BV31*BV39 -> 624000 | BY66: =BY31*BY39 -> 664000 | CB66: =CB31*CB39 -> 704000 | CE66: =CE31*CE39 -> 744000 | CH66: =CH31*CH39 -> 788000 | CK66: =CK31*CK39 -> 836000 | CN66: =CN31*CN39 -> 888000
B67: =B66+1 -> 60 | C67: net - NEW FEE INCREMENT REVENUE | E67: =SUM(E62:E66) -> 3097666.7 | H67: =SUM(H62:H66) -> 3266333.3 | K67: =SUM(K62:K66) -> 3435000 | N67: =SUM(N62:N66) -> 3664000 | Q67: =SUM(Q62:Q66) -> 3893000 | T67: =SUM(T62:T66) -> 4122000 | W67: =SUM(W62:W66) -> 4351000 | Z67: =SUM(Z62:Z66) -> 4640333.3 | AC67: =SUM(AC62:AC66) -> 4929666.7 | AF67: =SUM(AF62:AF66) -> 5206666.7 | AI67: =SUM(AI62:AI66) -> 5556333.3 | AL67: =SUM(AL62:AL66) -> 5893666.7 | AO67: =SUM(AO62:AO66) -> 6243333.3 | AR67: =SUM(AR62:AR66) -> 6641000 | AU67: =SUM(AU62:AU66) -> 7038666.7 | AX67: =SUM(AX62:AX66) -> 7448666.7 | BA67: =SUM(BA62:BA66) -> 7906666.7 | BD67: =SUM(BD62:BD66) -> 8364666.7 | BG67: =SUM(BG62:BG66) -> 8870666.7 | BJ67: =SUM(BJ62:BJ66) -> 9389000 | BM67: =SUM(BM62:BM66) -> 9967666.7 | BP67: =SUM(BP62:BP66) -> 10594333 | BS67: =SUM(BS62:BS66) -> 11221000 | BV67: =SUM(BV62:BV66) -> 11908000 | BY67: =SUM(BY62:BY66) -> 12655333 | CB67: =SUM(CB62:CB66) -> 13402667 | CE67: =SUM(CE62:CE66) -> 14198000 | CH67: =SUM(CH62:CH66) -> 15053667 | CK67: =SUM(CK62:CK66) -> 15969667 | CN67: =SUM(CN62:CN66) -> 16946000
B68: =B67+1 -> 61
B69: =B68+1 -> 62 | C69: TOTAL FEE REVENUE
B70: =B69+1 -> 63 | C70: Gross Fee Revenue - Fall + Spring | E70: =E43+E45+E54+E62 -> 10512000 | H70: =H43+H45+H54+H62 -> 10944000 | K70: =K43+K45+K54+K62 -> 11448000 | N70: =N43+N45+N54+N62 -> 12024000 | Q70: =Q43+Q45+Q54+Q62 -> 12600000 | T70: =T43+T45+T54+T62 -> 13104000 | W70: =W43+W45+W54+W62 -> 13680000 | Z70: =Z43+Z45+Z54+Z62 -> 14328000 | AC70: =AC43+AC45+AC54+AC62 -> 14976000 | AF70: =AF43+AF45+AF54+AF62 -> 15624000 | AI70: =AI43+AI45+AI54+AI62 -> 16416000 | AL70: =AL43+AL45+AL54+AL62 -> 17208000 | AO70: =AO43+AO45+AO54+AO62 -> 17928000 | AR70: =AR43+AR45+AR54+AR62 -> 18720000 | AU70: =AU43+AU45+AU54+AU62 -> 19584000 | AX70: =AX43+AX45+AX54+AX62 -> 20448000 | BA70: =BA43+BA45+BA54+BA62 -> 21384000 | BD70: =BD43+BD45+BD54+BD62 -> 22392000 | BG70: =BG43+BG45+BG54+BG62 -> 23472000 | BJ70: =BJ43+BJ45+BJ54+BJ62 -> 24552000 | BM70: =BM43+BM45+BM54+BM62 -> 25704000 | BP70: =BP43+BP45+BP54+BP62 -> 27000000 | BS70: =BS43+BS45+BS54+BS62 -> 28224000 | BV70: =BV43+BV45+BV54+BV62 -> 29592000 | BY70: =BY43+BY45+BY54+BY62 -> 31032000 | CB70: =CB43+CB45+CB54+CB62 -> 32472000 | CE70: =CE43+CE45+CE54+CE62 -> 33984000 | CH70: =CH43+CH45+CH54+CH62 -> 35640000 | CK70: =CK43+CK45+CK54+CK62 -> 37296000 | CN70: =CN43+CN45+CN54+CN62 -> 39096000
B71: =B70+1 -> 64 | C71: Less: return-to-aid | E71: =E46+E55+E63 -> -2820000 | H71: =H46+H55+H63 -> -2964000 | K71: =K46+K55+K63 -> -3816000 | N71: =N46+N55+N63 -> -4008000 | Q71: =Q46+Q55+Q63 -> -4200000 | T71: =T46+T55+T63 -> -4368000 | W71: =W46+W55+W63 -> -4560000 | Z71: =Z46+Z55+Z63 -> -4776000 | AC71: =AC46+AC55+AC63 -> -4992000 | AF71: =AF46+AF55+AF63 -> -5208000 | AI71: =AI46+AI55+AI63 -> -5472000 | AL71: =AL46+AL55+AL63 -> -5736000 | AO71: =AO46+AO55+AO63 -> -5976000 | AR71: =AR46+AR55+AR63 -> -6240000 | AU71: =AU46+AU55+AU63 -> -6528000 | AX71: =AX46+AX55+AX63 -> -6816000 | BA71: =BA46+BA55+BA63 -> -7128000 | BD71: =BD46+BD55+BD63 -> -7464000 | BG71: =BG46+BG55+BG63 -> -7824000 | BJ71: =BJ46+BJ55+BJ63 -> -8184000 | BM71: =BM46+BM55+BM63 -> -8568000 | BP71: =BP46+BP55+BP63 -> -9000000 | BS71: =BS46+BS55+BS63 -> -9408000 | BV71: =BV46+BV55+BV63 -> -9864000 | BY71: =BY46+BY55+BY63 -> -10344000 | CB71: =CB46+CB55+CB63 -> -10824000 | CE71: =CE46+CE55+CE63 -> -11328000 | CH71: =CH46+CH55+CH63 -> -11880000 | CK71: =CK46+CK55+CK63 -> -12432000 | CN71: =CN46+CN55+CN63 -> -13032000
B72: =B71+1 -> 65 | C72: Gross Fee Revenue - Summer UC | E72: =E47+E56+E64 -> 1306250 | H72: =H47+H56+H64 -> 1425000 | K72: =K47+K56+K64 -> 1487500 | N72: =N47+N56+N64 -> 1562500 | Q72: =Q47+Q56+Q64 -> 1637500 | T72: =T47+T56+T64 -> 1712500 | W72: =W47+W56+W64 -> 1787500 | Z72: =Z47+Z56+Z64 -> 1862500 | AC72: =AC47+AC56+AC64 -> 1950000 | AF72: =AF47+AF56+AF64 -> 2037500 | AI72: =AI47+AI56+AI64 -> 2137500 | AL72: =AL47+AL56+AL64 -> 2237500 | AO72: =AO47+AO56+AO64 -> 2337500 | AR72: =AR47+AR56+AR64 -> 2437500 | AU72: =AU47+AU56+AU64 -> 2550000 | AX72: =AX47+AX56+AX64 -> 2662500 | BA72: =BA47+BA56+BA64 -> 2787500 | BD72: =BD47+BD56+BD64 -> 2912500 | BG72: =BG47+BG56+BG64 -> 3062500 | BJ72: =BJ47+BJ56+BJ64 -> 3200000 | BM72: =BM47+BM56+BM64 -> 3350000 | BP72: =BP47+BP56+BP64 -> 3512500 | BS72: =BS47+BS56+BS64 -> 3675000 | BV72: =BV47+BV56+BV64 -> 3850000 | BY72: =BY47+BY56+BY64 -> 4037500 | CB72: =CB47+CB56+CB64 -> 4225000 | CE72: =CE47+CE56+CE64 -> 4425000 | CH72: =CH47+CH56+CH64 -> 4637500 | CK72: =CK47+CK56+CK64 -> 4862500 | CN72: =CN47+CN56+CN64 -> 5087500
B73: =B72+1 -> 66 | C73: Less: return-to-aid | E73: =E48+E57+E65 -> -435416.67 | H73: =H48+H57+H65 -> -475000 | K73: =K48+K57+K65 -> -495833.33 | N73: =N48+N57+N65 -> -520833.33 | Q73: =Q48+Q57+Q65 -> -545833.33 | T73: =T48+T57+T65 -> -570833.33 | W73: =W48+W57+W65 -> -595833.33 | Z73: =Z48+Z57+Z65 -> -620833.33 | AC73: =AC48+AC57+AC65 -> -650000 | AF73: =AF48+AF57+AF65 -> -679166.67 | AI73: =AI48+AI57+AI65 -> -712500 | AL73: =AL48+AL57+AL65 -> -745833.33 | AO73: =AO48+AO57+AO65 -> -779166.67 | AR73: =AR48+AR57+AR65 -> -812500 | AU73: =AU48+AU57+AU65 -> -850000 | AX73: =AX48+AX57+AX65 -> -887500 | BA73: =BA48+BA57+BA65 -> -929166.67 | BD73: =BD48+BD57+BD65 -> -970833.33 | BG73: =BG48+BG57+BG65 -> -1020833.3 | BJ73: =BJ48+BJ57+BJ65 -> -1066666.7 | BM73: =BM48+BM57+BM65 -> -1116666.7 | BP73: =BP48+BP57+BP65 -> -1170833.3 | BS73: =BS48+BS57+BS65 -> -1225000 | BV73: =BV48+BV57+BV65 -> -1283333.3 | BY73: =BY48+BY57+BY65 -> -1345833.3 | CB73: =CB48+CB57+CB65 -> -1408333.3 | CE73: =CE48+CE57+CE65 -> -1475000 | CH73: =CH48+CH57+CH65 -> -1545833.3 | CK73: =CK48+CK57+CK65 -> -1620833.3 | CN73: =CN48+CN57+CN65 -> -1695833.3
B74: =B73+1 -> 67 | C74: Gross Fee Revenue - Summer non-UC | E74: =E49+E58+E66 -> 418000 | H74: =H49+H58+H66 -> 456000 | K74: =K49+K58+K66 -> 576000 | N74: =N49+N58+N66 -> 604000 | Q74: =Q49+Q58+Q66 -> 632000 | T74: =T49+T58+T66 -> 656000 | W74: =W49+W58+W66 -> 684000 | Z74: =Z49+Z58+Z66 -> 716000 | AC74: =AC49+AC58+AC66 -> 748000 | AF74: =AF49+AF58+AF66 -> 776000 | AI74: =AI49+AI58+AI66 -> 816000 | AL74: =AL49+AL58+AL66 -> 852000 | AO74: =AO49+AO58+AO66 -> 888000 | AR74: =AR49+AR58+AR66 -> 924000 | AU74: =AU49+AU58+AU66 -> 964000 | AX74: =AX49+AX58+AX66 -> 1008000 | BA74: =BA49+BA58+BA66 -> 1052000 | BD74: =BD49+BD58+BD66 -> 1100000 | BG74: =BG49+BG58+BG66 -> 1148000 | BJ74: =BJ49+BJ58+BJ66 -> 1200000 | BM74: =BM49+BM58+BM66 -> 1256000 | BP74: =BP49+BP58+BP66 -> 1316000 | BS74: =BS49+BS58+BS66 -> 1372000 | BV74: =BV49+BV58+BV66 -> 1436000 | BY74: =BY49+BY58+BY66 -> 1504000 | CB74: =CB49+CB58+CB66 -> 1572000 | CE74: =CE49+CE58+CE66 -> 1640000 | CH74: =CH49+CH58+CH66 -> 1716000 | CK74: =CK49+CK58+CK66 -> 1792000 | CN74: =CN49+CN58+CN66 -> 1876000
B75: =B74+1 -> 68 | C75: net - TOTAL FEE REVENUE | E75: =SUM(E70:E74) -> 8980833.3 | H75: =SUM(H70:H74) -> 9386000 | K75: =SUM(K70:K74) -> 9199666.7 | N75: =SUM(N70:N74) -> 9661666.7 | Q75: =SUM(Q70:Q74) -> 10123667 | T75: =SUM(T70:T74) -> 10533667 | W75: =SUM(W70:W74) -> 10995667 | Z75: =SUM(Z70:Z74) -> 11509667 | AC75: =SUM(AC70:AC74) -> 12032000 | AF75: =SUM(AF70:AF74) -> 12550333 | AI75: =SUM(AI70:AI74) -> 13185000 | AL75: =SUM(AL70:AL74) -> 13815667 | AO75: =SUM(AO70:AO74) -> 14398333 | AR75: =SUM(AR70:AR74) -> 15029000 | AU75: =SUM(AU70:AU74) -> 15720000 | AX75: =SUM(AX70:AX74) -> 16415000 | BA75: =SUM(BA70:BA74) -> 17166333 | BD75: =SUM(BD70:BD74) -> 17969667 | BG75: =SUM(BG70:BG74) -> 18837667 | BJ75: =SUM(BJ70:BJ74) -> 19701333 | BM75: =SUM(BM70:BM74) -> 20625333 | BP75: =SUM(BP70:BP74) -> 21657667 | BS75: =SUM(BS70:BS74) -> 22638000 | BV75: =SUM(BV70:BV74) -> 23730667 | BY75: =SUM(BY70:BY74) -> 24883667 | CB75: =SUM(CB70:CB74) -> 26036667 | CE75: =SUM(CE70:CE74) -> 27246000 | CH75: =SUM(CH70:CH74) -> 28567667 | CK75: =SUM(CK70:CK74) -> 29897667 | CN75: =SUM(CN70:CN74) -> 31331667
B76: =B75+1 -> 69 | C76: total check | E76: =E51+E59+E67 -> 8980833.3 | H76: =H51+H59+H67 -> 9386000 | K76: =K51+K59+K67 -> 9199666.7 | N76: =N51+N59+N67 -> 9661666.7 | Q76: =Q51+Q59+Q67 -> 10123667 | T76: =T51+T59+T67 -> 10533667 | W76: =W51+W59+W67 -> 10995667 | Z76: =Z51+Z59+Z67 -> 11509667 | AC76: =AC51+AC59+AC67 -> 12032000 | AF76: =AF51+AF59+AF67 -> 12550333 | AI76: =AI51+AI59+AI67 -> 13185000 | AL76: =AL51+AL59+AL67 -> 13815667 | AO76: =AO51+AO59+AO67 -> 14398333 | AR76: =AR51+AR59+AR67 -> 15029000 | AU76: =AU51+AU59+AU67 -> 15720000 | AX76: =AX51+AX59+AX67 -> 16415000 | BA76: =BA51+BA59+BA67 -> 17166333 | BD76: =BD51+BD59+BD67 -> 17969667 | BG76: =BG51+BG59+BG67 -> 18837667 | BJ76: =BJ51+BJ59+BJ67 -> 19701333 | BM76: =BM51+BM59+BM67 -> 20625333 | BP76: =BP51+BP59+BP67 -> 21657667 | BS76: =BS51+BS59+BS67 -> 22638000 | BV76: =BV51+BV59+BV67 -> 23730667 | BY76: =BY51+BY59+BY67 -> 24883667 | CB76: =CB51+CB59+CB67 -> 26036667 | CE76: =CE51+CE59+CE67 -> 27246000 | CH76: =CH51+CH59+CH67 -> 28567667 | CK76: =CK51+CK59+CK67 -> 29897667 | CN76: =CN51+CN59+CN67 -> 31331667
B77: =B76+1 -> 70 | C77: difference | E77: =E75-E76 -> 0 | H77: =H75-H76 -> 0 | K77: =K75-K76 -> -1.8626451e-09 | N77: =N75-N76 -> 0 | Q77: =Q75-Q76 -> -1.8626451e-09 | T77: =T75-T76 -> -1.8626451e-09 | W77: =W75-W76 -> 0 | Z77: =Z75-Z76 -> -1.8626451e-09 | AC77: =AC75-AC76 -> 0 | AF77: =AF75-AF76 -> 1.8626451e-09 | AI77: =AI75-AI76 -> 0 | AL77: =AL75-AL76 -> -1.8626451e-09 | AO77: =AO75-AO76 -> 1.8626451e-09 | AR77: =AR75-AR76 -> 0 | AU77: =AU75-AU76 -> 0 | AX77: =AX75-AX76 -> 0 | BA77: =BA75-BA76 -> 3.7252903e-09 | BD77: =BD75-BD76 -> 0 | BG77: =BG75-BG76 -> 3.7252903e-09 | BJ77: =BJ75-BJ76 -> 0 | BM77: =BM75-BM76 -> -3.7252903e-09 | BP77: =BP75-BP76 -> 0 | BS77: =BS75-BS76 -> 0 | BV77: =BV75-BV76 -> 0 | BY77: =BY75-BY76 -> 0 | CB77: =CB75-CB76 -> 3.7252903e-09 | CE77: =CE75-CE76 -> 0 | CH77: =CH75-CH76 -> 3.7252903e-09 | CK77: =CK75-CK76 -> 3.7252903e-09 | CN77: =CN75-CN76 -> 0
C79: total fee revenue per v13 | E79: 9985833.3 | H79: 10759667 | K79: 10558333 | N79: 11101333 | Q79: 11644333 | T79: 12127000 | W79: 12730333 | Z79: 13333667 | AC79: 13937000 | AF79: 14600667 | AI79: 15324667 | AL79: 16048667 | AO79: 16772667 | AR79: 17496667 | AU79: 18341333 | AX79: 19186000 | BA79: 20091000 | BD79: 21116667 | BG79: 22142333 | BJ79: 23228333 | BM79: 24374667 | BP79: 25581333 | BS79: 26788000 | BV79: 28115333 | BY79: 29503000 | CB79: 30951000 | CE79: 32459333 | CH79: 34088333 | CK79: 35717333 | CN79: 37467000
C81: difference | E81: =E75-E79 -> -1005000 | H81: =H75-H79 -> -1373666.7 | I81: =I75-I79 -> 0 | J81: =J75-J79 -> 0 | K81: =K75-K79 -> -1358666.7 | L81: =L75-L79 -> 0 | M81: =M75-M79 -> 0 | N81: =N75-N79 -> -1439666.7 | O81: =O75-O79 -> 0 | ... CN81: =CN75-CN79 -> -6135333.3
